Workbook

Sheet SL
A1: 产品 | C1: 销售情况$ | W1: 广告$ | AG1: 销售成本$ | AP1: 退款成本$ 退款部分的销售金额=系统退款金额/(1-0.15+0.2*0.15) | BA1: 汇总$
C2: 输入 | M2: 公式输出 | W2: 输入 | AC2: 公式输出 | AG2: 输入 | AJ2: 公式输出 | AP2: 输入 | AS2: 公式输出
A3: 日期 | B3: 周数 | C3: 销量 | D3: 订单量 | E3: 销售额 | F3: 促销销量 | G3: 促销订单量 | H3: 促销销售额 | I3: 促销折扣 | J3: 退款量 | K3: 退款率 | L3: 退款金额 | M3: 销量环比 | N3: 订单环比 | O3: 销售额环比 | P3: 客单 销量 | Q3: 客单 价格($) | R3: 销售 均价($) | S3: 日均 销量 | T3: 自然 订单 | U3: 自然单 占比(%) | V3: TAcos (%) | W3: 展示 | X3: 点击 | Y3: 广告订单量 | Z3: 广告花费 | AA3: 广告销售额 | AB3: CPC | AC3: Acos(%) | AD3: CTR(%) | AE3: CVR(%) | AF3: CPS(%) | AG3: 3.6FT | AH3: 5.0FT | AI3: 5.5FT | AJ3: 产品成本 | AK3: 头程 | AL3: 入仓费 | AM3: FBA物流 | AN3: 佣金 | AO3: 成本小结 | AP3: 退款3.6FT | AQ3: 退款5.0FT | AR3: 退款5.5FT | AS3: 退款 销售金额 | AT3: 退款 产品成本 | AU3: 退款头程 | AV3: 退款 入仓费 | AW3: 退款 FBA物流 | AX3: 退款佣金 | AY3: 退款 管理费用 佣金的20% | AZ3: 退款 成本小结 | BA3: 净成本 | BB3: 净销售额 | BC3: 净销售额 (-退款金额) | BD3: 毛利 | BE3: 毛利率 | BF3: BSR | BG3: 备注 | BH3: 促销 | BI3: 备用
A4: 1104~1110 | B4: 2024W45 | C4: 276 | D4: 264 | E4: 6073.25 | J4: 12 | K4: =J4/C4 -> 0.043478261 | L4: 243.5 | M4: =(C4-C3)/C3 -> #VALUE! | N4: =(D4-D3)/D3 -> #VALUE! | O4: =(E4-E3)/E3 -> #VALUE! | P4: =C4/D4 -> 1.0454545 | Q4: =E4/D4 -> 23.004735 | R4: =E4/C4 -> 22.004529 | S4: =C4/7 -> 39.428571 | T4: =D4-Y4 -> 111 | U4: =T4/D4 -> 0.42045455 | V4: =Z4/(E4-I4) -> 0.28145062 | W4: 136418 | X4: 1723 | Y4: 153 | Z4: 1709.32 | AA4: 3516.2 | AB4: 0.99 | AC4: =Z4/AA4 -> 0.48612707 | AD4: =X4/W4 -> 0.012630298 | AE4: =Y4/X4 -> 0.088798607 | AF4: =Z4/Y4 -> 11.172026 | AG4: 68 | AH4: 203 | AI4: 5 | AJ4: =AG4*产品成本!$D$2+AH4*产品成本!$D$3+AI4*产品成本!$D$4 -> 589.08451 | AK4: =AG4*产品成本!$E$2+AH4*产品成本!$E$3+AI4*产品成本!$E$4 -> 51.991677 | AL4: =AG4*产品成本!$F$2+AH4*产品成本!$F$3+AI4*产品成本!$F$4 -> 93.84 | AM4: =AG4*产品成本!$G$2+AH4*产品成本!$G$3+AI4*产品成本!$G$4 -> 1062.12 | AN4: =(E4-I4)*0.15 -> 910.9875 | AO4: =SUM(AJ4:AN4) -> 2708.0237 | AP4: 3 | AQ4: 9 | AR4: 0 | AS4: =L4/(1-0.15+0.15*0.2) -> 276.70455 | AT4: =AP4*产品成本!$D$2+AQ4*产品成本!$D$3+AR4*产品成本!$D$4 -> 25.352113 | AU4: =AP4*产品成本!$E$2+AQ4*产品成本!$E$3+AR4*产品成本!$E$4 -> 2.2559324 | AV4: =AP4*产品成本!$F$2+AQ4*产品成本!$F$3+AR4*产品成本!$F$4 -> 4.08 | AW4: 0 | AX4: =AS4*0.15 -> 41.505682 | AY4: =-AX4*0.2 -> -8.3011364 | AZ4: =SUM(AT4:AY4) -> 64.892591 | BA4: =AO4-AZ4 -> 2643.1311 | BB4: =E4-I4 -> 6073.25 | BC4: =E4-AS4-I4 -> 5796.5455 | BD4: =BC4-BA4-Z4 -> 1444.0944 | BE4: =BD4/BC4 -> 0.24913017
A5: 1111~1117 | B5: 2024W46 | C5: 296 | D5: 285 | E5: 6535.75 | J5: 12 | K5: =J5/C5 -> 0.040540541 | L5: 240.45 | M5: =(C5-C4)/C4 -> 0.072463768 | N5: =(D5-D4)/D4 -> 0.079545455 | O5: =(E5-E4)/E4 -> 0.076153625 | P5: =C5/D5 -> 1.0385965 | Q5: =E5/D5 -> 22.932456 | R5: =E5/C5 -> 22.080236 | S5: =C5/7 -> 42.285714 | T5: =D5-Y5 -> 94 | U5: =T5/D5 -> 0.32982456 | V5: =Z5/(E5-I5) -> 0.28953525 | W5: 184745 | X5: 1929 | Y5: 191 | Z5: 1892.33 | AA5: 4333.92 | AB5: 0.98 | AC5: =Z5/AA5 -> 0.43663243 | AD5: =X5/W5 -> 0.010441419 | AE5: =Y5/X5 -> 0.099015034 | AF5: =Z5/Y5 -> 9.9074869 | AG5: 68 | AH5: 216 | AI5: 12 | AJ5: =AG5*产品成本!$D$2+AH5*产品成本!$D$3+AI5*产品成本!$D$4 -> 639.71831 | AK5: =AG5*产品成本!$E$2+AH5*产品成本!$E$3+AI5*产品成本!$E$4 -> 55.967949 | AL5: =AG5*产品成本!$F$2+AH5*产品成本!$F$3+AI5*产品成本!$F$4 -> 100.64 | AM5: =AG5*产品成本!$G$2+AH5*产品成本!$G$3+AI5*产品成本!$G$4 -> 1140.12 | AN5: =(E5-I5)*0.15 -> 980.3625 | AO5: =SUM(AJ5:AN5) -> 2916.8088 | AP5: 3 | AQ5: 9 | AR5: 0 | AS5: =L5/(1-0.15+0.15*0.2) -> 273.23864 | AT5: =AP5*产品成本!$D$2+AQ5*产品成本!$D$3+AR5*产品成本!$D$4 -> 25.352113 | AU5: =AP5*产品成本!$E$2+AQ5*产品成本!$E$3+AR5*产品成本!$E$4 -> 2.2559324 | AV5: =AP5*产品成本!$F$2+AQ5*产品成本!$F$3+AR5*产品成本!$F$4 -> 4.08 | AW5: 0 | AX5: =AS5*0.15 -> 40.985795 | AY5: =-AX5*0.2 -> -8.1971591 | AZ5: =SUM(AT5:AY5) -> 64.476681 | BA5: =AO5-AZ5 -> 2852.3321 | BB5: =E5-I5 -> 6535.75 | BC5: =E5-AS5-I5 -> 6262.5114 | BD5: =BC5-BA5-Z5 -> 1517.8493 | BE5: =BD5/BC5 -> 0.2423707
A6: 1118~1124 | B6: 2024W47 | C6: 401 | D6: 366 | E6: 7627.49 | J6: 16 | K6: =J6/C6 -> 0.039900249 | L6: 329.15 | M6: =(C6-C5)/C5 -> 0.35472973 | N6: =(D6-D5)/D5 -> 0.28421053 | O6: =(E6-E5)/E5 -> 0.16704127 | P6: =C6/D6 -> 1.0956284 | Q6: =E6/D6 -> 20.840137 | R6: =E6/C6 -> 19.021172 | S6: =C6/7 -> 57.285714 | T6: =D6-Y6 -> 126 | U6: =T6/D6 -> 0.3442623 | V6: =Z6/(E6-I6) -> 0.28473194 | W6: 195302 | X6: 2172 | Y6: 240 | Z6: 2171.79 | AA6: 4918.97 | AB6: ‎1.00 | AC6: =Z6/AA6 -> 0.44151316 | AD6: =X6/W6 -> 0.011121238 | AE6: =Y6/X6 -> 0.11049724 | AF6: =Z6/Y6 -> 9.049125 | AG6: 119 | AH6: 271 | AI6: 11 | AJ6: =AG6*产品成本!$D$2+AH6*产品成本!$D$3+AI6*产品成本!$D$4 -> 860.35211 | AK6: =AG6*产品成本!$E$2+AH6*产品成本!$E$3+AI6*产品成本!$E$4 -> 75.215366 | AL6: =AG6*产品成本!$F$2+AH6*产品成本!$F$3+AI6*产品成本!$F$4 -> 136.34 | AM6: =AG6*产品成本!$G$2+AH6*产品成本!$G$3+AI6*产品成本!$G$4 -> 1538.91 | AN6: =(E6-I6)*0.15 -> 1144.1235 | AO6: =SUM(AJ6:AN6) -> 3754.941 | AP6: 2 | AQ6: 14 | AR6: 1 | AS6: =L6/(1-0.15+0.15*0.2) -> 374.03409 | AT6: =AP6*产品成本!$D$2+AQ6*产品成本!$D$3+AR6*产品成本!$D$4 -> 37.112676 | AU6: =AP6*产品成本!$E$2+AQ6*产品成本!$E$3+AR6*产品成本!$E$4 -> 3.2562761 | AV6: =AP6*产品成本!$F$2+AQ6*产品成本!$F$3+AR6*产品成本!$F$4 -> 5.78 | AW6: 0 | AX6: =AS6*0.15 -> 56.105114 | AY6: =-AX6*0.2 -> -11.221023 | AZ6: =SUM(AT6:AY6) -> 91.033043 | BA6: =AO6-AZ6 -> 3663.9079 | BB6: =E6-I6 -> 7627.49 | BC6: =E6-AS6-I6 -> 7253.4559 | BD6: =BC6-BA6-Z6 -> 1417.758 | BE6: =BD6/BC6 -> 0.19545965
A7: 1125~1201 | B7: 2024W48 | C7: 349 | D7: 339 | E7: 6352.41 | J7: 22 | K7: =J7/C7 -> 0.063037249 | L7: 390.12 | M7: =(C7-C6)/C6 -> -0.12967581 | N7: =(D7-D6)/D6 -> -0.073770492 | O7: =(E7-E6)/E6 -> -0.16716902 | P7: =C7/D7 -> 1.0294985 | Q7: =E7/D7 -> 18.738673 | R7: =E7/C7 -> 18.201748 | S7: =C7/7 -> 49.857143 | T7: =D7-Y7 -> 118 | U7: =T7/D7 -> 0.3480826 | V7: =Z7/(E7-I7) -> 0.35467799 | W7: 204302 | X7: 2295 | Y7: 221 | Z7: 2253.06 | AA7: 4084.24 | AB7: ‎0.98 | AC7: =Z7/AA7 -> 0.55164731 | AD7: =X7/W7 -> 0.01123337 | AE7: =Y7/X7 -> 0.096296296 | AF7: =Z7/Y7 -> 10.194842 | AG7: 129 | AH7: 196 | AI7: 24 | AJ7: =AG7*产品成本!$D$2+AH7*产品成本!$D$3+AI7*产品成本!$D$4 -> 766.05634 | AK7: =AG7*产品成本!$E$2+AH7*产品成本!$E$3+AI7*产品成本!$E$4 -> 65.222176 | AL7: =AG7*产品成本!$F$2+AH7*产品成本!$F$3+AI7*产品成本!$F$4 -> 118.66 | AM7: =AG7*产品成本!$G$2+AH7*产品成本!$G$3+AI7*产品成本!$G$4 -> 1334.01 | AN7: =(E7-I7)*0.15 -> 952.8615 | AO7: =SUM(AJ7:AN7) -> 3236.81 | AP7: 6 | AQ7: 16 | AR7: 0 | AS7: =L7/(1-0.15+0.15*0.2) -> 443.31818 | AT7: =AP7*产品成本!$D$2+AQ7*产品成本!$D$3+AR7*产品成本!$D$4 -> 46.478873 | AU7: =AP7*产品成本!$E$2+AQ7*产品成本!$E$3+AR7*产品成本!$E$4 -> 4.1262845 | AV7: =AP7*产品成本!$F$2+AQ7*产品成本!$F$3+AR7*产品成本!$F$4 -> 7.48 | AW7: 0 | AX7: =AS7*0.15 -> 66.497727 | AY7: =-AX7*0.2 -> -13.299545 | AZ7: =SUM(AT7:AY7) -> 111.28334 | BA7: =AO7-AZ7 -> 3125.5267 | BB7: =E7-I7 -> 6352.41 | BC7: =E7-AS7-I7 -> 5909.0918 | BD7: =BC7-BA7-Z7 -> 530.50514 | BE7: =BD7/BC7 -> 0.08977778
A8: 1202~1208 | B8: 2024W49 | C8: 319 | D8: 300 | E8: 6697.47 | J8: 23 | K8: =J8/C8 -> 0.072100313 | L8: 402.29 | M8: =(C8-C7)/C7 -> -0.085959885 | N8: =(D8-D7)/D7 -> -0.11504425 | O8: =(E8-E7)/E7 -> 0.054319542 | P8: =C8/D8 -> 1.0633333 | Q8: =E8/D8 -> 22.3249 | R8: =E8/C8 -> 20.995204 | S8: =C8/7 -> 45.571429 | T8: =D8-Y8 -> 122 | U8: =T8/D8 -> 0.40666667 | V8: =Z8/(E8-I8) -> 0.32161846 | W8: 215967 | X8: 2203 | Y8: 178 | Z8: 2154.03 | AA8: 4084.54 | AB8: ‎0.98 | AC8: =Z8/AA8 -> 0.52736171 | AD8: =X8/W8 -> 0.010200633 | AE8: =Y8/X8 -> 0.080798911 | AF8: =Z8/Y8 -> 12.101292 | AG8: 106 | AH8: 197 | AI8: 16 | AJ8: =AG8*产品成本!$D$2+AH8*产品成本!$D$3+AI8*产品成本!$D$4 -> 693.09859 | AK8: =AG8*产品成本!$E$2+AH8*产品成本!$E$3+AI8*产品成本!$E$4 -> 59.742004 | AL8: =AG8*产品成本!$F$2+AH8*产品成本!$F$3+AI8*产品成本!$F$4 -> 108.46 | AM8: =AG8*产品成本!$G$2+AH8*产品成本!$G$3+AI8*产品成本!$G$4 -> 1221.84 | AN8: =(E8-I8)*0.15 -> 1004.6205 | AO8: =SUM(AJ8:AN8) -> 3087.7611 | AP8: 10 | AQ8: 13 | AR8: 2 | AS8: =L8/(1-0.15+0.15*0.2) -> 457.14773 | AT8: =AP8*产品成本!$D$2+AQ8*产品成本!$D$3+AR8*产品成本!$D$4 -> 55.211268 | AU8: =AP8*产品成本!$E$2+AQ8*产品成本!$E$3+AR8*产品成本!$E$4 -> 4.6623423 | AV8: =AP8*产品成本!$F$2+AQ8*产品成本!$F$3+AR8*产品成本!$F$4 -> 8.5 | AW8: 0 | AX8: =AS8*0.15 -> 68.572159 | AY8: =-AX8*0.2 -> -13.714432 | AZ8: =SUM(AT8:AY8) -> 123.23134 | BA8: =AO8-AZ8 -> 2964.5298 | BB8: =E8-I8 -> 6697.47 | BC8: =E8-AS8-I8 -> 6240.3223 | BD8: =BC8-BA8-Z8 -> 1121.7625 | BE8: =BD8/BC8 -> 0.17976035
A9: 1209~1215 | B9: 2024W50 | C9: 299 | D9: 285 | E9: 7065.55 | J9: 21 | K9: =J9/C9 -> 0.070234114 | L9: 418.94 | M9: =(C9-C8)/C8 -> -0.062695925 | N9: =(D9-D8)/D8 -> -0.05 | O9: =(E9-E8)/E8 -> 0.054958066 | P9: =C9/D9 -> 1.0491228 | Q9: =E9/D9 -> 24.791404 | R9: =E9/C9 -> 23.630602 | S9: =C9/7 -> 42.714286 | T9: =D9-Y9 -> 93 | U9: =T9/D9 -> 0.32631579 | V9: =Z9/(E9-I9) -> 0.24653849 | W9: 158506 | X9: 1791 | Y9: 192 | Z9: 1741.93 | AA9: 4780.29 | AB9: ‎0.97 | AC9: =Z9/AA9 -> 0.36439839 | AD9: =X9/W9 -> 0.011299257 | AE9: =Y9/X9 -> 0.10720268 | AF9: =Z9/Y9 -> 9.0725521 | AG9: 98 | AH9: 187 | AI9: 14 | AJ9: =AG9*产品成本!$D$2+AH9*产品成本!$D$3+AI9*产品成本!$D$4 -> 648.4507 | AK9: =AG9*产品成本!$E$2+AH9*产品成本!$E$3+AI9*产品成本!$E$4 -> 56.005246 | AL9: =AG9*产品成本!$F$2+AH9*产品成本!$F$3+AI9*产品成本!$F$4 -> 101.66 | AM9: =AG9*产品成本!$G$2+AH9*产品成本!$G$3+AI9*产品成本!$G$4 -> 1145.52 | AN9: =(E9-I9)*0.15 -> 1059.8325 | AO9: =SUM(AJ9:AN9) -> 3011.4685 | AP9: 6 | AQ9: 15 | AR9: 2 | AS9: =L9/(1-0.15+0.15*0.2) -> 476.06818 | AT9: =AP9*产品成本!$D$2+AQ9*产品成本!$D$3+AR9*产品成本!$D$4 -> 50.985915 | AU9: =AP9*产品成本!$E$2+AQ9*产品成本!$E$3+AR9*产品成本!$E$4 -> 4.3534944 | AV9: =AP9*产品成本!$F$2+AQ9*产品成本!$F$3+AR9*产品成本!$F$4 -> 7.82 | AW9: 0 | AX9: =AS9*0.15 -> 71.410227 | AY9: =-AX9*0.2 -> -14.282045 | AZ9: =SUM(AT9:AY9) -> 120.28759 | BA9: =AO9-AZ9 -> 2891.1809 | BB9: =E9-I9 -> 7065.55 | BC9: =E9-AS9-I9 -> 6589.4818 | BD9: =BC9-BA9-Z9 -> 1956.371 | BE9: =BD9/BC9 -> 0.29689299
A10: 1216~1222 | B10: 2024W51 | C10: 261 | D10: 250 | E10: 6230.89 | J10: 29 | K10: =J10/C10 -> 0.11111111 | L10: 586.11 | M10: =(C10-C9)/C9 -> -0.1270903 | N10: =(D10-D9)/D9 -> -0.12280702 | O10: =(E10-E9)/E9 -> -0.11813093 | P10: =C10/D10 -> 1.044 | Q10: =E10/D10 -> 24.92356 | R10: =E10/C10 -> 23.873142 | S10: =C10/7 -> 37.285714 | T10: =D10-Y10 -> 110 | U10: =T10/D10 -> 0.44 | V10: =Z10/(E10-I10) -> 0.27256941 | W10: 166059 | X10: 1726 | Y10: 140 | Z10: 1698.35 | AA10: 3468.95 | AB10: ‎0.98 | AC10: =Z10/AA10 -> 0.48958619 | AD10: =X10/W10 -> 0.010393896 | AE10: =Y10/X10 -> 0.081112399 | AF10: =Z10/Y10 -> 12.131071 | AG10: 76 | AH10: 160 | AI10: 26 | AJ10: =AG10*产品成本!$D$2+AH10*产品成本!$D$3+AI10*产品成本!$D$4 -> 584.64789 | AK10: =AG10*产品成本!$E$2+AH10*产品成本!$E$3+AI10*产品成本!$E$4 -> 49.500558 | AL10: =AG10*产品成本!$F$2+AH10*产品成本!$F$3+AI10*产品成本!$F$4 -> 89.08 | AM10: =AG10*产品成本!$G$2+AH10*产品成本!$G$3+AI10*产品成本!$G$4 -> 1005.84 | AN10: =(E10-I10)*0.15 -> 934.6335 | AO10: =SUM(AJ10:AN10) -> 2663.7019 | AP10: 12 | AQ10: 14 | AR10: 3 | AS10: =L10/(1-0.15+0.15*0.2) -> 666.03409 | AT10: =AP10*产品成本!$D$2+AQ10*产品成本!$D$3+AR10*产品成本!$D$4 -> 64.859155 | AU10: =AP10*产品成本!$E$2+AQ10*产品成本!$E$3+AR10*产品成本!$E$4 -> 5.4123465 | AV10: =AP10*产品成本!$F$2+AQ10*产品成本!$F$3+AR10*产品成本!$F$4 -> 9.86 | AW10: 0 | AX10: =AS10*0.15 -> 99.905114 | AY10: =-AX10*0.2 -> -19.981023 | AZ10: =SUM(AT10:AY10) -> 160.05559 | BA10: =AO10-AZ10 -> 2503.6464 | BB10: =E10-I10 -> 6230.89 | BC10: =E10-AS10-I10 -> 5564.8559 | BD10: =BC10-BA10-Z10 -> 1362.8596 | BE10: =BD10/BC10 -> 0.24490473
A11: 1223~1229 | B11: 2024W52 | C11: 305 | D11: 290 | E11: 6636.34 | J11: 18 | K11: =J11/C11 -> 0.059016393 | L11: 268.6 | M11: =(C11-C10)/C10 -> 0.16858238 | N11: =(D11-D10)/D10 -> 0.16 | O11: =(E11-E10)/E10 -> 0.065070961 | P11: =C11/D11 -> 1.0517241 | Q11: =E11/D11 -> 22.883931 | R11: =E11/C11 -> 21.758492 | S11: =C11/7 -> 43.571429 | T11: =D11-Y11 -> 95 | U11: =T11/D11 -> 0.32758621 | V11: =Z11/(E11-I11) -> 0.3061115 | W11: 175575 | X11: 1917 | Y11: 195 | Z11: 2031.46 | AA11: 4467.78 | AB11: ‎1.06 | AC11: =Z11/AA11 -> 0.45469114 | AD11: =X11/W11 -> 0.010918411 | AE11: =Y11/X11 -> 0.10172144 | AF11: =Z11/Y11 -> 10.417744 | AG11: 97 | AH11: 170 | AI11: 38 | AJ11: =AG11*产品成本!$D$2+AH11*产品成本!$D$3+AI11*产品成本!$D$4 -> 689.85915 | AK11: =AG11*产品成本!$E$2+AH11*产品成本!$E$3+AI11*产品成本!$E$4 -> 57.594207 | AL11: =AG11*产品成本!$F$2+AH11*产品成本!$F$3+AI11*产品成本!$F$4 -> 103.7 | AM11: =AG11*产品成本!$G$2+AH11*产品成本!$G$3+AI11*产品成本!$G$4 -> 1169.13 | AN11: =(E11-I11)*0.15 -> 995.451 | AO11: =SUM(AJ11:AN11) -> 3015.7344 | AP11: 7 | AQ11: 11 | AR11: 0 | AS11: =L11/(1-0.15+0.15*0.2) -> 305.22727 | AT11: =AP11*产品成本!$D$2+AQ11*产品成本!$D$3+AR11*产品成本!$D$4 -> 38.028169 | AU11: =AP11*产品成本!$E$2+AQ11*产品成本!$E$3+AR11*产品成本!$E$4 -> 3.3359408 | AV11: =AP11*产品成本!$F$2+AQ11*产品成本!$F$3+AR11*产品成本!$F$4 -> 6.12 | AW11: 0 | AX11: =AS11*0.15 -> 45.784091 | AY11: =-AX11*0.2 -> -9.1568182 | AZ11: =SUM(AT11:AY11) -> 84.111383 | BA11: =AO11-AZ11 -> 2931.623 | BB11: =E11-I11 -> 6636.34 | BC11: =E11-AS11-I11 -> 6331.1127 | BD11: =BC11-BA11-Z11 -> 1368.0297 | BE11: =BD11/BC11 -> 0.21608046
A12: 1230~0105 | B12: 2025W01 | C12: 351 | D12: 331 | E12: 7526.09 | J12: 21 | K12: =J12/C12 -> 0.05982906 | L12: 410.76 | M12: =(C12-C11)/C11 -> 0.15081967 | N12: =(D12-D11)/D11 -> 0.14137931 | O12: =(E12-E11)/E11 -> 0.1340724 | P12: =C12/D12 -> 1.060423 | Q12: =E12/D12 -> 22.737432 | R12: =E12/C12 -> 21.441852 | S12: =C12/7 -> 50.142857 | T12: =D12-Y12 -> 139 | U12: =T12/D12 -> 0.41993958 | V12: =Z12/(E12-I12) -> 0.26822693 | W12: 197397 | X12: 2078 | Y12: 192 | Z12: 2018.7 | AA12: 4366.84 | AB12: ‎0.97 | AC12: =Z12/AA12 -> 0.46227936 | AD12: =X12/W12 -> 0.010527009 | AE12: =Y12/X12 -> 0.092396535 | AF12: =Z12/Y12 -> 10.514062 | AG12: 112 | AH12: 212 | AI12: 27 | AJ12: =AG12*产品成本!$D$2+AH12*产品成本!$D$3+AI12*产品成本!$D$4 -> 773.87324 | AK12: =AG12*产品成本!$E$2+AH12*产品成本!$E$3+AI12*产品成本!$E$4 -> 65.985499 | AL12: =AG12*产品成本!$F$2+AH12*产品成本!$F$3+AI12*产品成本!$F$4 -> 119.34 | AM12: =AG12*产品成本!$G$2+AH12*产品成本!$G$3+AI12*产品成本!$G$4 -> 1345.38 | AN12: =(E12-I12)*0.15 -> 1128.9135 | AO12: =SUM(AJ12:AN12) -> 3433.4922 | AP12: 5 | AQ12: 14 | AR12: 2 | AS12: =L12/(1-0.15+0.15*0.2) -> 466.77273 | AT12: =AP12*产品成本!$D$2+AQ12*产品成本!$D$3+AR12*产品成本!$D$4 -> 46.760563 | AU12: =AP12*产品成本!$E$2+AQ12*产品成本!$E$3+AR12*产品成本!$E$4 -> 3.9870972 | AV12: =AP12*产品成本!$F$2+AQ12*产品成本!$F$3+AR12*产品成本!$F$4 -> 7.14 | AW12: 0 | AX12: =AS12*0.15 -> 70.015909 | AY12: =-AX12*0.2 -> -14.003182 | AZ12: =SUM(AT12:AY12) -> 113.90039 | BA12: =AO12-AZ12 -> 3319.5919 | BB12: =E12-I12 -> 7526.09 | BC12: =E12-AS12-I12 -> 7059.3173 | BD12: =BC12-BA12-Z12 -> 1721.0254 | BE12: =BD12/BC12 -> 0.24379488 | BG12: 九折
A13: 0106~0112 | B13: 2025W02 | C13: 290 | D13: 271 | E13: 6846.76 | J13: 25 | K13: =J13/C13 -> 0.086206897 | L13: 471.02 | M13: =(C13-C12)/C12 -> -0.17378917 | N13: =(D13-D12)/D12 -> -0.18126888 | O13: =(E13-E12)/E12 -> -0.090263337 | P13: =C13/D13 -> 1.0701107 | Q13: =E13/D13 -> 25.264797 | R13: =E13/C13 -> 23.609517 | S13: =C13/7 -> 41.428571 | T13: =D13-Y13 -> 104 | U13: =T13/D13 -> 0.38376384 | V13: =Z13/(E13-I13) -> 0.2637262 | W13: 175351 | X13: 1841 | Y13: 167 | Z13: 1805.67 | AA13: 4166.77 | AB13: ‎0.98 | AC13: =Z13/AA13 -> 0.43335005 | AD13: =X13/W13 -> 0.010498942 | AE13: =Y13/X13 -> 0.09071157 | AF13: =Z13/Y13 -> 10.812395 | AG13: 81 | AH13: 199 | AI13: 10 | AJ13: =AG13*产品成本!$D$2+AH13*产品成本!$D$3+AI13*产品成本!$D$4 -> 624.64789 | AK13: =AG13*产品成本!$E$2+AH13*产品成本!$E$3+AI13*产品成本!$E$4 -> 54.527408 | AL13: =AG13*产品成本!$F$2+AH13*产品成本!$F$3+AI13*产品成本!$F$4 -> 98.6 | AM13: =AG13*产品成本!$G$2+AH13*产品成本!$G$3+AI13*产品成本!$G$4 -> 1113.99 | AN13: =(E13-I13)*0.15 -> 1027.014 | AO13: =SUM(AJ13:AN13) -> 2918.7793 | AP13: 7 | AQ13: 15 | AR13: 3 | AS13: =L13/(1-0.15+0.15*0.2) -> 535.25 | AT13: =AP13*产品成本!$D$2+AQ13*产品成本!$D$3+AR13*产品成本!$D$4 -> 56.408451 | AU13: =AP13*产品成本!$E$2+AQ13*产品成本!$E$3+AR13*产品成本!$E$4 -> 4.7371014 | AV13: =AP13*产品成本!$F$2+AQ13*产品成本!$F$3+AR13*产品成本!$F$4 -> 8.5 | AW13: 0 | AX13: =AS13*0.15 -> 80.2875 | AY13: =-AX13*0.2 -> -16.0575 | AZ13: =SUM(AT13:AY13) -> 133.87555 | BA13: =AO13-AZ13 -> 2784.9037 | BB13: =E13-I13 -> 6846.76 | BC13: =E13-AS13-I13 -> 6311.51 | BD13: =BC13-BA13-Z13 -> 1720.9363 | BE13: =BD13/BC13 -> 0.27266633 | BG13: 原价
A14: 0113~0119 | B14: 2025W03 | C14: 315 | D14: 298 | E14: 7220.89 | J14: 26 | K14: =J14/C14 -> 0.082539683 | L14: 508.77 | M14: =(C14-C13)/C13 -> 0.086206897 | N14: =(D14-D13)/D13 -> 0.099630996 | O14: =(E14-E13)/E13 -> 0.054643364 | P14: =C14/D14 -> 1.057047 | Q14: =E14/D14 -> 24.231174 | R14: =E14/C14 -> 22.92346 | S14: =C14/7 -> 45 | T14: =D14-Y14 -> 105 | U14: =T14/D14 -> 0.35234899 | V14: =Z14/(E14-I14) -> 0.28568362 | W14: 192908 | X14: 2120 | Y14: 193 | Z14: 2062.89 | AA14: 4629.61 | AB14: ‎0.97 | AC14: =Z14/AA14 -> 0.44558613 | AD14: =X14/W14 -> 0.010989695 | AE14: =Y14/X14 -> 0.091037736 | AF14: =Z14/Y14 -> 10.688549 | AG14: 80 | AH14: 212 | AI14: 23 | AJ14: =AG14*产品成本!$D$2+AH14*产品成本!$D$3+AI14*产品成本!$D$4 -> 693.02817 | AK14: =AG14*产品成本!$E$2+AH14*产品成本!$E$3+AI14*产品成本!$E$4 -> 59.590073 | AL14: =AG14*产品成本!$F$2+AH14*产品成本!$F$3+AI14*产品成本!$F$4 -> 107.1 | AM14: =AG14*产品成本!$G$2+AH14*产品成本!$G$3+AI14*产品成本!$G$4 -> 1211.7 | AN14: =(E14-I14)*0.15 -> 1083.1335 | AO14: =SUM(AJ14:AN14) -> 3154.5517 | AP14: 8 | AQ14: 16 | AR14: 2 | AS14: =L14/(1-0.15+0.15*0.2) -> 578.14773 | AT14: =AP14*产品成本!$D$2+AQ14*产品成本!$D$3+AR14*产品成本!$D$4 -> 57.323944 | AU14: =AP14*产品成本!$E$2+AQ14*产品成本!$E$3+AR14*产品成本!$E$4 -> 4.8934986 | AV14: =AP14*产品成本!$F$2+AQ14*产品成本!$F$3+AR14*产品成本!$F$4 -> 8.84 | AW14: 0 | AX14: =AS14*0.15 -> 86.722159 | AY14: =-AX14*0.2 -> -17.344432 | AZ14: =SUM(AT14:AY14) -> 140.43517 | BA14: =AO14-AZ14 -> 3014.1166 | BB14: =E14-I14 -> 7220.89 | BC14: =E14-AS14-I14 -> 6642.7423 | BD14: =BC14-BA14-Z14 -> 1565.7357 | BE14: =BD14/BC14 -> 0.23570622 | BG14: 平日原价, 周末九折 平日销量一般，周末拉升
A15: 0120~0126 | B15: 2025W04 | C15: 278 | D15: 269 | E15: 6436.56 | J15: 23 | K15: =J15/C15 -> 0.082733813 | L15: 471.54 | M15: =(C15-C14)/C14 -> -0.11746032 | N15: =(D15-D14)/D14 -> -0.097315436 | O15: =(E15-E14)/E14 -> -0.10861957 | P15: =C15/D15 -> 1.0334572 | Q15: =E15/D15 -> 23.927732 | R15: =E15/C15 -> 23.153094 | S15: =C15/7 -> 39.714286 | T15: =D15-Y15 -> 100 | U15: =T15/D15 -> 0.37174721 | V15: =Z15/(E15-I15) -> 0.27666486 | W15: 167353 | X15: 1833 | Y15: 169 | Z15: 1780.77 | AA15: 4021.03 | AB15: ‎0.97 | AC15: =Z15/AA15 -> 0.44286414 | AD15: =X15/W15 -> 0.010952896 | AE15: =Y15/X15 -> 0.092198582 | AF15: =Z15/Y15 -> 10.537101 | AG15: 49 | AH15: 177 | AI15: 52 | AJ15: =AG15*产品成本!$D$2+AH15*产品成本!$D$3+AI15*产品成本!$D$4 -> 649.57746 | AK15: =AG15*产品成本!$E$2+AH15*产品成本!$E$3+AI15*产品成本!$E$4 -> 53.5506 | AL15: =AG15*产品成本!$F$2+AH15*产品成本!$F$3+AI15*产品成本!$F$4 -> 94.52 | AM15: =AG15*产品成本!$G$2+AH15*产品成本!$G$3+AI15*产品成本!$G$4 -> 1073.91 | AN15: =(E15-I15)*0.15 -> 965.484 | AO15: =SUM(AJ15:AN15) -> 2837.0421 | AP15: 10 | AQ15: 13 | AR15: 1 | AS15: =L15/(1-0.15+0.15*0.2) -> 535.84091 | AT15: =AP15*产品成本!$D$2+AQ15*产品成本!$D$3+AR15*产品成本!$D$4 -> 51.901408 | AU15: =AP15*产品成本!$E$2+AQ15*产品成本!$E$3+AR15*产品成本!$E$4 -> 4.4523423 | AV15: =AP15*产品成本!$F$2+AQ15*产品成本!$F$3+AR15*产品成本!$F$4 -> 8.16 | AW15: 0 | AX15: =AS15*0.15 -> 80.376136 | AY15: =-AX15*0.2 -> -16.075227 | AZ15: =SUM(AT15:AY15) -> 128.81466 | BA15: =AO15-AZ15 -> 2708.2274 | BB15: =E15-I15 -> 6436.56 | BC15: =E15-AS15-I15 -> 5900.7191 | BD15: =BC15-BA15-Z15 -> 1411.7217 | BE15: =BD15/BC15 -> 0.2392457 | BG15: 新P陆续到货，老P毛利环比减少$631.19
A16: 0127~0202 | B16: 2025W05 | C16: 344 | D16: 324 | E16: 7634.97 | J16: 30 | K16: =J16/C16 -> 0.087209302 | L16: 583.82 | M16: =(C16-C15)/C15 -> 0.23741007 | N16: =(D16-D15)/D15 -> 0.20446097 | O16: =(E16-E15)/E15 -> 0.18618796 | P16: =C16/D16 -> 1.0617284 | Q16: =E16/D16 -> 23.564722 | R16: =E16/C16 -> 22.19468 | S16: =C16/7 -> 49.142857 | T16: =D16-Y16 -> 305 | U16: =T16/D16 -> 0.94135802 | V16: =Z16/(E16-I16) -> 0.29573397 | W16: 201438 | X16: 2316 | Y16: 19 | Z16: 2257.92 | AA16: 4659.38 | AB16: 0.97 | AC16: =Z16/AA16 -> 0.48459666 | AD16: =X16/W16 -> 0.011497334 | AE16: =Y16/X16 -> 0.0082037997 | AF16: =Z16/Y16 -> 118.83789 | AG16: 84 | AH16: 211 | AI16: 49 | AJ16: =AG16*产品成本!$D$2+AH16*产品成本!$D$3+AI16*产品成本!$D$4 -> 785.42254 | AK16: =AG16*产品成本!$E$2+AH16*产品成本!$E$3+AI16*产品成本!$E$4 -> 65.551711 | AL16: =AG16*产品成本!$F$2+AH16*产品成本!$F$3+AI16*产品成本!$F$4 -> 116.96 | AM16: =AG16*产品成本!$G$2+AH16*产品成本!$G$3+AI16*产品成本!$G$4 -> 1323.96 | AN16: =(E16-I16)*0.15 -> 1145.2455 | AO16: =SUM(AJ16:AN16) -> 3437.1397 | AP16: 13 | AQ16: 16 | AR16: 1 | AS16: =L16/(1-0.15+0.15*0.2) -> 663.43182 | AT16: =AP16*产品成本!$D$2+AQ16*产品成本!$D$3+AR16*产品成本!$D$4 -> 64.577465 | AU16: =AP16*产品成本!$E$2+AQ16*产品成本!$E$3+AR16*产品成本!$E$4 -> 5.5515338 | AV16: =AP16*产品成本!$F$2+AQ16*产品成本!$F$3+AR16*产品成本!$F$4 -> 10.2 | AW16: 0 | AX16: =AS16*0.15 -> 99.514773 | AY16: =-AX16*0.2 -> -19.902955 | AZ16: =SUM(AT16:AY16) -> 159.94082 | BA16: =AO16-AZ16 -> 3277.1989 | BB16: =E16-I16 -> 7634.97 | BC16: =E16-AS16-I16 -> 6971.5382 | BD16: =BC16-BA16-Z16 -> 1436.4193 | BE16: =BD16/BC16 -> 0.20604051 | BG16: 减少广告预算
A17: 0203~0209 | B17: 2025W06 | C17: 351 | D17: 339 | E17: 7769.22 | J17: 23 | K17: =J17/C17 -> 0.065527066 | L17: 440.93 | M17: =(C17-C16)/C16 -> 0.020348837 | N17: =(D17-D16)/D16 -> 0.046296296 | O17: =(E17-E16)/E16 -> 0.017583566 | P17: =C17/D17 -> 1.0353982 | Q17: =E17/D17 -> 22.918053 | R17: =E17/C17 -> 22.13453 | S17: =C17/7 -> 50.142857 | T17: =D17-Y17 -> 118 | U17: =T17/D17 -> 0.3480826 | V17: =Z17/(E17-I17) -> 0.29884853 | W17: 243295 | X17: 2349 | Y17: 221 | Z17: 2321.82 | AA17: 5024.08 | AB17: 0.99 | AC17: =Z17/AA17 -> 0.46213834 | AD17: =X17/W17 -> 0.0096549456 | AE17: =Y17/X17 -> 0.094082588 | AF17: =Z17/Y17 -> 10.505973 | AG17: 105 | AH17: 173 | AI17: 73 | AJ17: =AG17*产品成本!$D$2+AH17*产品成本!$D$3+AI17*产品成本!$D$4 -> 828.94366 | AK17: =AG17*产品成本!$E$2+AH17*产品成本!$E$3+AI17*产品成本!$E$4 -> 66.911434 | AL17: =AG17*产品成本!$F$2+AH17*产品成本!$F$3+AI17*产品成本!$F$4 -> 119.34 | AM17: =AG17*产品成本!$G$2+AH17*产品成本!$G$3+AI17*产品成本!$G$4 -> 1346.85 | AN17: =(E17-I17)*0.15 -> 1165.383 | AO17: =SUM(AJ17:AN17) -> 3527.4281 | AP17: 7 | AQ17: 8 | AR17: 8 | AS17: =L17/(1-0.15+0.15*0.2) -> 501.05682 | AT17: =AP17*产品成本!$D$2+AQ17*产品成本!$D$3+AR17*产品成本!$D$4 -> 58.169014 | AU17: =AP17*产品成本!$E$2+AQ17*产品成本!$E$3+AR17*产品成本!$E$4 -> 4.4375704 | AV17: =AP17*产品成本!$F$2+AQ17*产品成本!$F$3+AR17*产品成本!$F$4 -> 7.82 | AX17: =AS17*0.15 -> 75.158523 | AY17: =-AX17*0.2 -> -15.031705 | AZ17: =SUM(AT17:AY17) -> 130.5534 | BA17: =AO17-AZ17 -> 3396.8747 | BB17: =E17-I17 -> 7769.22 | BC17: =E17-AS17-I17 -> 7268.1632 | BD17: =BC17-BA17-Z17 -> 1549.4685 | BE17: =BD17/BC17 -> 0.2131857 | BG17: 销量5.5FT↑,5FT↓ | BH17: 原价
A18: 0210~0216 | B18: 2025W07 | C18: 399 | D18: 357 | E18: 9260.61 | J18: 29 | K18: =J18/C18 -> 0.072681704 | L18: 585.8 | M18: =(C18-C17)/C17 -> 0.13675214 | N18: =(D18-D17)/D17 -> 0.053097345 | O18: =(E18-E17)/E17 -> 0.19196136 | P18: =C18/D18 -> 1.1176471 | Q18: =E18/D18 -> 25.940084 | R18: =E18/C18 -> 23.209549 | S18: =C18/7 -> 57 | T18: =D18-Y18 -> 138 | U18: =T18/D18 -> 0.38655462 | V18: =Z18/(E18-I18) -> 0.22524866 | W18: 205810 | X18: 2124 | Y18: 219 | Z18: 2085.94 | AA18: 5804.27 | AB18: 0.98 | AC18: =Z18/AA18 -> 0.35938025 | AD18: =X18/W18 -> 0.010320198 | AE18: =Y18/X18 -> 0.10310734 | AF18: =Z18/Y18 -> 9.5248402 | AG18: 139 | AH18: 178 | AI18: 82 | AJ18: =AG18*产品成本!$D$2+AH18*产品成本!$D$3+AI18*产品成本!$D$4 -> 941.12676 | AK18: =AG18*产品成本!$E$2+AH18*产品成本!$E$3+AI18*产品成本!$E$4 -> 75.668024 | AL18: =AG18*产品成本!$F$2+AH18*产品成本!$F$3+AI18*产品成本!$F$4 -> 135.66 | AM18: =AG18*产品成本!$G$2+AH18*产品成本!$G$3+AI18*产品成本!$G$4 -> 1526.91 | AN18: =(E18-I18)*0.15 -> 1389.0915 | AO18: =SUM(AJ18:AN18) -> 4068.4563 | AP18: 6 | AQ18: 14 | AR18: 9 | AS18: =L18/(1-0.15+0.15*0.2) -> 665.68182 | AT18: =AP18*产品成本!$D$2+AQ18*产品成本!$D$3+AR18*产品成本!$D$4 -> 72.042254 | AU18: =AP18*产品成本!$E$2+AQ18*产品成本!$E$3+AR18*产品成本!$E$4 -> 5.6307042 | AV18: =AP18*产品成本!$F$2+AQ18*产品成本!$F$3+AR18*产品成本!$F$4 -> 9.86 | AX18: =AS18*0.15 -> 99.852273 | AY18: =-AX18*0.2 -> -19.970455 | AZ18: =SUM(AT18:AY18) -> 167.41478 | BA18: =AO18-AZ18 -> 3901.0415 | BB18: =E18-I18 -> 9260.61 | BC18: =E18-AS18-I18 -> 8594.9282 | BD18: =BC18-BA18-Z18 -> 2607.9467 | BE18: =BD18/BC18 -> 0.30342856 | BG18: 销量5.5FT↑ | BH18: 原价
A19: 0217~0223 | B19: 2025W08 | C19: 379 | D19: 357 | E19: 9167.51 | J19: 19 | K19: =J19/C19 -> 0.050131926 | L19: 378.87 | M19: =(C19-C18)/C18 -> -0.050125313 | N19: =(D19-D18)/D18 -> 0 | O19: =(E19-E18)/E18 -> -0.010053333 | P19: =C19/D19 -> 1.0616246 | Q19: =E19/D19 -> 25.6793 | R19: =E19/C19 -> 24.188681 | S19: =C19/7 -> 54.142857 | T19: =D19-Y19 -> 119 | U19: =T19/D19 -> 0.33333333 | V19: =Z19/(E19-I19) -> 0.26074256 | W19: 237785 | X19: 2470 | Y19: 238 | Z19: 2390.36 | AA19: 6061.78 | AB19: 0.97 | AC19: =Z19/AA19 -> 0.39433302 | AD19: =X19/W19 -> 0.010387535 | AE19: =Y19/X19 -> 0.096356275 | AF19: =Z19/Y19 -> 10.043529 | AG19: 111 | AH19: 182 | AI19: 86 | AJ19: =AG19*产品成本!$D$2+AH19*产品成本!$D$3+AI19*产品成本!$D$4 -> 903.66197 | AK19: =AG19*产品成本!$E$2+AH19*产品成本!$E$3+AI19*产品成本!$E$4 -> 72.418187 | AL19: =AG19*产品成本!$F$2+AH19*产品成本!$F$3+AI19*产品成本!$F$4 -> 128.86 | AM19: =AG19*产品成本!$G$2+AH19*产品成本!$G$3+AI19*产品成本!$G$4 -> 1454.79 | AN19: =(E19-I19)*0.15 -> 1375.1265 | AO19: =SUM(AJ19:AN19) -> 3934.8567 | AP19: 8 | AQ19: 9 | AR19: 2 | AS19: =L19/(1-0.15+0.15*0.2) -> 430.53409 | AT19: =AP19*产品成本!$D$2+AQ19*产品成本!$D$3+AR19*产品成本!$D$4 -> 42.535211 | AU19: =AP19*产品成本!$E$2+AQ19*产品成本!$E$3+AR19*产品成本!$E$4 -> 3.5439676 | AV19: =AP19*产品成本!$F$2+AQ19*产品成本!$F$3+AR19*产品成本!$F$4 -> 6.46 | AX19: =AS19*0.15 -> 64.580114 | AY19: =-AX19*0.2 -> -12.916023 | AZ19: =SUM(AT19:AY19) -> 104.20327 | BA19: =AO19-AZ19 -> 3830.6534 | BB19: =E19-I19 -> 9167.51 | BC19: =E19-AS19-I19 -> 8736.9759 | BD19: =BC19-BA19-Z19 -> 2515.9625 | BE19: =BD19/BC19 -> 0.2879672 | BG19: 基本保持 | BH19: 原价
A20: 0224~0302 | B20: 2025W09 | C20: 477 | D20: 448 | E20: 11520.55 | J20: 28 | K20: =J20/C20 -> 0.05870021 | L20: 581.9 | M20: =(C20-C19)/C19 -> 0.2585752 | N20: =(D20-D19)/D19 -> 0.25490196 | O20: =(E20-E19)/E19 -> 0.25667166 | P20: =C20/D20 -> 1.0647321 | Q20: =E20/D20 -> 25.715513 | R20: =E20/C20 -> 24.152096 | S20: =C20/7 -> 68.142857 | T20: =D20-Y20 -> 203 | U20: =T20/D20 -> 0.453125 | V20: =Z20/(E20-I20) -> 0.21871091 | W20: 255819 | X20: 2600 | Y20: 245 | Z20: 2519.67 | AA20: 6351.18 | AB20: 0.97 | AC20: =Z20/AA20 -> 0.3967247 | AD20: =X20/W20 -> 0.010163436 | AE20: =Y20/X20 -> 0.094230769 | AF20: =Z20/Y20 -> 10.284367 | AG20: 139 | AH20: 239 | AI20: 99 | AJ20: =AG20*产品成本!$D$2+AH20*产品成本!$D$3+AI20*产品成本!$D$4 -> 1126.2676 | AK20: =AG20*产品成本!$E$2+AH20*产品成本!$E$3+AI20*产品成本!$E$4 -> 90.998223 | AL20: =AG20*产品成本!$F$2+AH20*产品成本!$F$3+AI20*产品成本!$F$4 -> 162.18 | AM20: =AG20*产品成本!$G$2+AH20*产品成本!$G$3+AI20*产品成本!$G$4 -> 1831.11 | AN20: =(E20-I20)*0.15 -> 1728.0825 | AO20: =SUM(AJ20:AN20) -> 4938.6383 | AP20: 8 | AQ20: 15 | AR20: 5 | AS20: =L20/(1-0.15+0.15*0.2) -> 661.25 | AT20: =AP20*产品成本!$D$2+AQ20*产品成本!$D$3+AR20*产品成本!$D$4 -> 65.140845 | AU20: =AP20*产品成本!$E$2+AQ20*产品成本!$E$3+AR20*产品成本!$E$4 -> 5.3307085 | AV20: =AP20*产品成本!$F$2+AQ20*产品成本!$F$3+AR20*产品成本!$F$4 -> 9.52 | AX20: =AS20*0.15 -> 99.1875 | AY20: =-AX20*0.2 -> -19.8375 | AZ20: =SUM(AT20:AY20) -> 159.34155 | BA20: =AO20-AZ20 -> 4779.2968 | BB20: =E20-I20 -> 11520.55 | BC20: =E20-AS20-I20 -> 10859.3 | BD20: =BC20-BA20-Z20 -> 3560.3332 | BE20: =BD20/BC20 -> 0.32786029 | BH20: 原价
A21: 0303~0309 | B21: 2025W10 | C21: 350 | D21: 338 | E21: 8390.83 | J21: 29 | K21: =J21/C21 -> 0.082857143 | L21: 604.6 | M21: =(C21-C20)/C20 -> -0.26624738 | N21: =(D21-D20)/D20 -> -0.24553571 | O21: =(E21-E20)/E20 -> -0.27166411 | P21: =C21/D21 -> 1.035503 | Q21: =E21/D21 -> 24.824941 | R21: =E21/C21 -> 23.9738 | S21: =C21/7 -> 50 | T21: =D21-Y21 -> 123 | U21: =T21/D21 -> 0.36390533 | V21: =Z21/(E21-I21) -> 0.30769662 | W21: 261831 | X21: 2520 | Y21: 215 | Z21: 2581.83 | AA21: 5283.21 | AB21: 1.02 | AC21: =Z21/AA21 -> 0.48868586 | AD21: =X21/W21 -> 0.0096245288 | AE21: =Y21/X21 -> 0.08531746 | AF21: =Z21/Y21 -> 12.008512 | AG21: 99 | AH21: 207 | AI21: 44 | AJ21: =AG21*产品成本!$D$2+AH21*产品成本!$D$3+AI21*产品成本!$D$4 -> 792.11268 | AK21: =AG21*产品成本!$E$2+AH21*产品成本!$E$3+AI21*产品成本!$E$4 -> 66.334656 | AL21: =AG21*产品成本!$F$2+AH21*产品成本!$F$3+AI21*产品成本!$F$4 -> 119 | AM21: =AG21*产品成本!$G$2+AH21*产品成本!$G$3+AI21*产品成本!$G$4 -> 1344.21 | AN21: =(E21-I21)*0.15 -> 1258.6245 | AO21: =SUM(AJ21:AN21) -> 3580.2818 | AP21: 9 | AQ21: 15 | AR21: 5 | AS21: =L21/(1-0.15+0.15*0.2) -> 687.04545 | AT21: =AP21*产品成本!$D$2+AQ21*产品成本!$D$3+AR21*产品成本!$D$4 -> 67.253521 | AU21: =AP21*产品成本!$E$2+AQ21*产品成本!$E$3+AR21*产品成本!$E$4 -> 5.5043155 | AV21: =AP21*产品成本!$F$2+AQ21*产品成本!$F$3+AR21*产品成本!$F$4 -> 9.86 | AX21: =AS21*0.15 -> 103.05682 | AY21: =-AX21*0.2 -> -20.611364 | AZ21: =SUM(AT21:AY21) -> 165.06329 | BA21: =AO21-AZ21 -> 3415.2185 | BB21: =E21-I21 -> 8390.83 | BC21: =E21-AS21-I21 -> 7703.7845 | BD21: =BC21-BA21-Z21 -> 1706.736 | BE21: =BD21/BC21 -> 0.22154514 | BG21: 销量5.5FT黑绿橙断货,其他5.5FT库存28个; CPC↑：断货的5.5FT的平均CPC=0.75 | BH21: 原价
A22: 0310~0316 | B22: 2025W11 | C22: 390 | D22: 376 | E22: 9380.31 | J22: 24 | K22: =J22/C22 -> 0.061538462 | L22: 496.01 | M22: =(C22-C21)/C21 -> 0.11428571 | N22: =(D22-D21)/D21 -> 0.11242604 | O22: =(E22-E21)/E21 -> 0.11792397 | P22: =C22/D22 -> 1.037234 | Q22: =E22/D22 -> 24.947633 | R22: =E22/C22 -> 24.052077 | S22: =C22/7 -> 55.714286 | T22: =D22-Y22 -> 111 | U22: =T22/D22 -> 0.29521277 | V22: =Z22/(E22-I22) -> 0.31517508 | W22: 263574 | X22: 2836 | Y22: 265 | Z22: 2956.44 | AA22: 6504.79 | AB22: 1.04 | AC22: =Z22/AA22 -> 0.45450199 | AD22: =X22/W22 -> 0.010759787 | AE22: =Y22/X22 -> 0.093441467 | AF22: =Z22/Y22 -> 11.156377 | AG22: 121 | AH22: 220 | AI22: 49 | AJ22: =AG22*产品成本!$D$2+AH22*产品成本!$D$3+AI22*产品成本!$D$4 -> 882.60563 | AK22: =AG22*产品成本!$E$2+AH22*产品成本!$E$3+AI22*产品成本!$E$4 -> 73.710283 | AL22: =AG22*产品成本!$F$2+AH22*产品成本!$F$3+AI22*产品成本!$F$4 -> 132.6 | AM22: =AG22*产品成本!$G$2+AH22*产品成本!$G$3+AI22*产品成本!$G$4 -> 1495.59 | AN22: =(E22-I22)*0.15 -> 1407.0465 | AO22: =SUM(AJ22:AN22) -> 3991.5524 | AP22: 9 | AQ22: 12 | AR22: 3 | AS22: =L22/(1-0.15+0.15*0.2) -> 563.64773 | AT22: =AP22*产品成本!$D$2+AQ22*产品成本!$D$3+AR22*产品成本!$D$4 -> 54.295775 | AU22: =AP22*产品成本!$E$2+AQ22*产品成本!$E$3+AR22*产品成本!$E$4 -> 4.5059451 | AV22: =AP22*产品成本!$F$2+AQ22*产品成本!$F$3+AR22*产品成本!$F$4 -> 8.16 | AX22: =AS22*0.15 -> 84.547159 | AY22: =-AX22*0.2 -> -16.909432 | AZ22: =SUM(AT22:AY22) -> 134.59945 | BA22: =AO22-AZ22 -> 3856.953 | BB22: =E22-I22 -> 9380.31 | BC22: =E22-AS22-I22 -> 8816.6623 | BD22: =BC22-BA22-Z22 -> 2003.2693 | BE22: =BD22/BC22 -> 0.22721402 | BG22: 调整广告重心为老款P； 5.5FT短暂有货又马上断货。黑/薄绿/粉共库存26个 | BH22: 原价
A23: 0317~0323 | B23: 2025W12 | C23: 401 | D23: 382 | E23: 9704.49 | J23: 28 | K23: =J23/C23 -> 0.069825436 | L23: 594.58 | M23: =(C23-C22)/C22 -> 0.028205128 | N23: =(D23-D22)/D22 -> 0.015957447 | O23: =(E23-E22)/E22 -> 0.034559625 | P23: =C23/D23 -> 1.0497382 | Q23: =E23/D23 -> 25.404424 | R23: =E23/C23 -> 24.200723 | S23: =C23/7 -> 57.285714 | T23: =D23-Y23 -> 128 | U23: =T23/D23 -> 0.33507853 | V23: =Z23/(E23-I23) -> 0.28675902 | W23: 278481 | X23: 2758 | Y23: 254 | Z23: 2782.85 | AA23: 6199.12 | AB23: 1.01 | AC23: =Z23/AA23 -> 0.44891049 | AD23: =X23/W23 -> 0.0099037277 | AE23: =Y23/X23 -> 0.092095722 | AF23: =Z23/Y23 -> 10.956102 | AG23: 106 | AH23: 264 | AI23: 31 | AJ23: =AG23*产品成本!$D$2+AH23*产品成本!$D$3+AI23*产品成本!$D$4 -> 884.29577 | AK23: =AG23*产品成本!$E$2+AH23*产品成本!$E$3+AI23*产品成本!$E$4 -> 75.808944 | AL23: =AG23*产品成本!$F$2+AH23*产品成本!$F$3+AI23*产品成本!$F$4 -> 136.34 | AM23: =AG23*产品成本!$G$2+AH23*产品成本!$G$3+AI23*产品成本!$G$4 -> 1541.64 | AN23: =(E23-I23)*0.15 -> 1455.6735 | AO23: =SUM(AJ23:AN23) -> 4093.7582 | AP23: 8 | AQ23: 16 | AR23: 4 | AS23: =L23/(1-0.15+0.15*0.2) -> 675.65909 | AT23: =AP23*产品成本!$D$2+AQ23*产品成本!$D$3+AR23*产品成本!$D$4 -> 63.943662 | AU23: =AP23*产品成本!$E$2+AQ23*产品成本!$E$3+AR23*产品成本!$E$4 -> 5.3134986 | AV23: =AP23*产品成本!$F$2+AQ23*产品成本!$F$3+AR23*产品成本!$F$4 -> 9.52 | AX23: =AS23*0.15 -> 101.34886 | AY23: =-AX23*0.2 -> -20.269773 | AZ23: =SUM(AT23:AY23) -> 159.85625 | BA23: =AO23-AZ23 -> 3933.902 | BB23: =E23-I23 -> 9704.49 | BC23: =E23-AS23-I23 -> 9028.8309 | BD23: =BC23-BA23-Z23 -> 2312.0789 | BE23: =BD23/BC23 -> 0.25607733 | BG23: 调整广告重心为老款P； 5.5FT依旧有货 | BH23: 原价
A24: 0324~0330 | B24: 2025W13 | C24: 464 | D24: 441 | E24: 9746.86 | J24: 24 | K24: =J24/C24 -> 0.051724138 | L24: 493.76 | M24: =(C24-C23)/C23 -> 0.15710723 | N24: =(D24-D23)/D23 -> 0.15445026 | O24: =(E24-E23)/E23 -> 0.0043660203 | P24: =C24/D24 -> 1.0521542 | Q24: =E24/D24 -> 22.101723 | R24: =E24/C24 -> 21.006164 | S24: =C24/7 -> 66.285714 | T24: =D24-Y24 -> 164 | U24: =T24/D24 -> 0.37188209 | V24: =Z24/(E24-I24) -> 0.30536809 | W24: 236690 | X24: 2806 | Y24: 277 | Z24: 2976.38 | AA24: 6103.54 | AB24: 1.06 | AC24: =Z24/AA24 -> 0.48764815 | AD24: =X24/W24 -> 0.011855169 | AE24: =Y24/X24 -> 0.098717035 | AF24: =Z24/Y24 -> 10.745054 | AG24: 151 | AH24: 257 | AI24: 56 | AJ24: =AG24*产品成本!$D$2+AH24*产品成本!$D$3+AI24*产品成本!$D$4 -> 1047.3239 | AK24: =AG24*产品成本!$E$2+AH24*产品成本!$E$3+AI24*产品成本!$E$4 -> 87.52173 | AL24: =AG24*产品成本!$F$2+AH24*产品成本!$F$3+AI24*产品成本!$F$4 -> 157.76 | AM24: =AG24*产品成本!$G$2+AH24*产品成本!$G$3+AI24*产品成本!$G$4 -> 1777.89 | AN24: =(E24-I24)*0.15 -> 1462.029 | AO24: =SUM(AJ24:AN24) -> 4532.5247 | AP24: 8 | AQ24: 14 | AR24: 2 | AS24: =L24/(1-0.15+0.15*0.2) -> 561.09091 | AT24: =AP24*产品成本!$D$2+AQ24*产品成本!$D$3+AR24*产品成本!$D$4 -> 53.098592 | AU24: =AP24*产品成本!$E$2+AQ24*产品成本!$E$3+AR24*产品成本!$E$4 -> 4.5079183 | AV24: =AP24*产品成本!$F$2+AQ24*产品成本!$F$3+AR24*产品成本!$F$4 -> 8.16 | AX24: =AS24*0.15 -> 84.163636 | AY24: =-AX24*0.2 -> -16.832727 | AZ24: =SUM(AT24:AY24) -> 133.09742 | BA24: =AO24-AZ24 -> 4399.4273 | BB24: =E24-I24 -> 9746.86 | BC24: =E24-AS24-I24 -> 9185.7691 | BD24: =BC24-BA24-Z24 -> 1809.9618 | BE24: =BD24/BC24 -> 0.19703977 | BG24: 春促15%off折扣，销量提升，但是客单价降低 | BH24: 85折
A25: 0331~0406 | B25: 2025W14 | C25: 486 | D25: 465 | E25: 11015.19 | J25: 31 | K25: =J25/C25 -> 0.063786008 | L25: 630.36 | M25: =(C25-C24)/C24 -> 0.047413793 | N25: =(D25-D24)/D24 -> 0.054421769 | O25: =(E25-E24)/E24 -> 0.13012704 | P25: =C25/D25 -> 1.0451613 | Q25: =E25/D25 -> 23.688581 | R25: =E25/C25 -> 22.665 | S25: =C25/7 -> 69.428571 | T25: =D25-Y25 -> 154 | U25: =T25/D25 -> 0.3311828 | V25: =Z25/(E25-I25) -> 0.28374545 | W25: 303852 | X25: 2994 | Y25: 311 | Z25: 3125.51 | AA25: 7326.12 | AB25: 1.04 | AC25: =Z25/AA25 -> 0.42662555 | AD25: =X25/W25 -> 0.0098534813 | AE25: =Y25/X25 -> 0.10387442 | AF25: =Z25/Y25 -> 10.049871 | AG25: 164 | AH25: 249 | AI25: 73 | AJ25: =AG25*产品成本!$D$2+AH25*产品成本!$D$3+AI25*产品成本!$D$4 -> 1114.1549 | AK25: =AG25*产品成本!$E$2+AH25*产品成本!$E$3+AI25*产品成本!$E$4 -> 91.8063 | AL25: =AG25*产品成本!$F$2+AH25*产品成本!$F$3+AI25*产品成本!$F$4 -> 165.24 | AM25: =AG25*产品成本!$G$2+AH25*产品成本!$G$3+AI25*产品成本!$G$4 -> 1860.96 | AN25: =(E25-I25)*0.15 -> 1652.2785 | AO25: =SUM(AJ25:AN25) -> 4884.4397 | AP25: 9 | AQ25: 19 | AR25: 3 | AS25: =L25/(1-0.15+0.15*0.2) -> 716.31818 | AT25: =AP25*产品成本!$D$2+AQ25*产品成本!$D$3+AR25*产品成本!$D$4 -> 69.084507 | AU25: =AP25*产品成本!$E$2+AQ25*产品成本!$E$3+AR25*产品成本!$E$4 -> 5.8554761 | AV25: =AP25*产品成本!$F$2+AQ25*产品成本!$F$3+AR25*产品成本!$F$4 -> 10.54 | AX25: =AS25*0.15 -> 107.44773 | AY25: =-AX25*0.2 -> -21.489545 | AZ25: =SUM(AT25:AY25) -> 171.43816 | BA25: =AO25-AZ25 -> 4713.0016 | BB25: =E25-I25 -> 11015.19 | BC25: =E25-AS25-I25 -> 10298.872 | BD25: =BC25-BA25-Z25 -> 2460.3603 | BE25: =BD25/BC25 -> 0.23889609 | BH25: 原价
A26: 0407~0413 | B26: 2025W15 | C26: 416 | D26: 391 | E26: 10020.4 | J26: 23 | K26: =J26/C26 -> 0.055288462 | L26: 472.65 | M26: =(C26-C25)/C25 -> -0.14403292 | N26: =(D26-D25)/D25 -> -0.15913978 | O26: =(E26-E25)/E25 -> -0.090310744 | P26: =C26/D26 -> 1.0639386 | Q26: =E26/D26 -> 25.627621 | R26: =E26/C26 -> 24.0875 | S26: =C26/7 -> 59.428571 | T26: =D26-Y26 -> 153 | U26: =T26/D26 -> 0.39130435 | V26: =Z26/(E26-I26) -> 0.27636721 | W26: 258909 | X26: 2637 | Y26: 238 | Z26: 2769.31 | AA26: 5998.55 | AB26: 1.05 | AC26: =Z26/AA26 -> 0.46166324 | AD26: =X26/W26 -> 0.010185046 | AE26: =Y26/X26 -> 0.090254077 | AF26: =Z26/Y26 -> 11.635756 | AG26: 95 | AH26: 228 | AI26: 93 | AJ26: =AG26*产品成本!$D$2+AH26*产品成本!$D$3+AI26*产品成本!$D$4 -> 990.21127 | AK26: =AG26*产品成本!$E$2+AH26*产品成本!$E$3+AI26*产品成本!$E$4 -> 79.978821 | AL26: =AG26*产品成本!$F$2+AH26*产品成本!$F$3+AI26*产品成本!$F$4 -> 141.44 | AM26: =AG26*产品成本!$G$2+AH26*产品成本!$G$3+AI26*产品成本!$G$4 -> 1602.45 | AN26: =(E26-I26)*0.15 -> 1503.06 | AO26: =SUM(AJ26:AN26) -> 4317.1401 | AP26: 7 | AQ26: 14 | AR26: 2 | AS26: =L26/(1-0.15+0.15*0.2) -> 537.10227 | AT26: =AP26*产品成本!$D$2+AQ26*产品成本!$D$3+AR26*产品成本!$D$4 -> 50.985915 | AU26: =AP26*产品成本!$E$2+AQ26*产品成本!$E$3+AR26*产品成本!$E$4 -> 4.3343113 | AV26: =AP26*产品成本!$F$2+AQ26*产品成本!$F$3+AR26*产品成本!$F$4 -> 7.82 | AX26: =AS26*0.15 -> 80.565341 | AY26: =-AX26*0.2 -> -16.113068 | AZ26: =SUM(AT26:AY26) -> 127.5925 | BA26: =AO26-AZ26 -> 4189.5476 | BB26: =E26-I26 -> 10020.4 | BC26: =E26-AS26-I26 -> 9483.2977 | BD26: =BC26-BA26-Z26 -> 2524.4401 | BE26: =BD26/BC26 -> 0.26619855 | BG26: 主力Black出现断货 | BH26: 原价
A27: 0414~0420 | B27: 2025W16 | C27: 348 | D27: 338 | E27: 8556.44 | J27: 28 | K27: =J27/C27 -> 0.08045977 | L27: 570.05 | M27: =(C27-C26)/C26 -> -0.16346154 | N27: =(D27-D26)/D26 -> -0.13554987 | O27: =(E27-E26)/E26 -> -0.14609796 | P27: =C27/D27 -> 1.0295858 | Q27: =E27/D27 -> 25.314911 | R27: =E27/C27 -> 24.587471 | S27: =C27/7 -> 49.714286 | T27: =D27-Y27 -> 152 | U27: =T27/D27 -> 0.44970414 | V27: =Z27/(E27-I27) -> 0.27541594 | W27: 235160 | X27: 2259 | Y27: 186 | Z27: 2356.58 | AA27: 4686.72 | AB27: 1.04 | AC27: =Z27/AA27 -> 0.50282074 | AD27: =X27/W27 -> 0.0096062255 | AE27: =Y27/X27 -> 0.082337317 | AF27: =Z27/Y27 -> 12.669785 | AG27: 56 | AH27: 188 | AI27: 104 | AJ27: =AG27*产品成本!$D$2+AH27*产品成本!$D$3+AI27*产品成本!$D$4 -> 859.71831 | AK27: =AG27*产品成本!$E$2+AH27*产品成本!$E$3+AI27*产品成本!$E$4 -> 67.806541 | AL27: =AG27*产品成本!$F$2+AH27*产品成本!$F$3+AI27*产品成本!$F$4 -> 118.32 | AM27: =AG27*产品成本!$G$2+AH27*产品成本!$G$3+AI27*产品成本!$G$4 -> 1345.44 | AN27: =(E27-I27)*0.15 -> 1283.466 | AO27: =SUM(AJ27:AN27) -> 3674.7509 | AP27: 9 | AQ27: 13 | AR27: 6 | AS27: =L27/(1-0.15+0.15*0.2) -> 647.78409 | AT27: =AP27*产品成本!$D$2+AQ27*产品成本!$D$3+AR27*产品成本!$D$4 -> 66.338028 | AU27: =AP27*产品成本!$E$2+AQ27*产品成本!$E$3+AR27*产品成本!$E$4 -> 5.3287352 | AV27: =AP27*产品成本!$F$2+AQ27*产品成本!$F$3+AR27*产品成本!$F$4 -> 9.52 | AX27: =AS27*0.15 -> 97.167614 | AY27: =-AX27*0.2 -> -19.433523 | AZ27: =SUM(AT27:AY27) -> 158.92085 | BA27: =AO27-AZ27 -> 3515.83 | BB27: =E27-I27 -> 8556.44 | BC27: =E27-AS27-I27 -> 7908.6559 | BD27: =BC27-BA27-Z27 -> 2036.2459 | BE27: =BD27/BC27 -> 0.25747054 | BG27: 主力Black 3.6FT断货数天 | BH27: 原价
A28: 0421~0427 | B28: 2025W17 | C28: 390 | D28: 356 | E28: 8924.45 | J28: 29 | K28: =J28/C28 -> 0.074358974 | L28: 602.16 | M28: =(C28-C27)/C27 -> 0.12068966 | N28: =(D28-D27)/D27 -> 0.053254438 | O28: =(E28-E27)/E27 -> 0.04300971 | P28: =C28/D28 -> 1.0955056 | Q28: =E28/D28 -> 25.06868 | R28: =E28/C28 -> 22.883205 | S28: =C28/7 -> 55.714286 | T28: =D28-Y28 -> 156 | U28: =T28/D28 -> 0.43820225 | V28: =Z28/(E28-I28) -> 0.28585291 | W28: 246122 | X28: 2473 | Y28: 200 | Z28: 2551.08 | AA28: 4818.21 | AB28: 1.03 | AC28: =Z28/AA28 -> 0.52946634 | AD28: =X28/W28 -> 0.010047862 | AE28: =Y28/X28 -> 0.080873433 | AF28: =Z28/Y28 -> 12.7554 | AG28: 102 | AH28: 186 | AI28: 102 | AJ28: =AG28*产品成本!$D$2+AH28*产品成本!$D$3+AI28*产品成本!$D$4 -> 946.05634 | AK28: =AG28*产品成本!$E$2+AH28*产品成本!$E$3+AI28*产品成本!$E$4 -> 74.986885 | AL28: =AG28*产品成本!$F$2+AH28*产品成本!$F$3+AI28*产品成本!$F$4 -> 132.6 | AM28: =AG28*产品成本!$G$2+AH28*产品成本!$G$3+AI28*产品成本!$G$4 -> 1499.58 | AN28: =(E28-I28)*0.15 -> 1338.6675 | AO28: =SUM(AJ28:AN28) -> 3991.8907 | AP28: 12 | AQ28: 9 | AR28: 8 | AS28: =L28/(1-0.15+0.15*0.2) -> 684.27273 | AT28: =AP28*产品成本!$D$2+AQ28*产品成本!$D$3+AR28*产品成本!$D$4 -> 70.84507 | AU28: =AP28*产品成本!$E$2+AQ28*产品成本!$E$3+AR28*产品成本!$E$4 -> 5.4983958 | AV28: =AP28*产品成本!$F$2+AQ28*产品成本!$F$3+AR28*产品成本!$F$4 -> 9.86 | AX28: =AS28*0.15 -> 102.64091 | AY28: =-AX28*0.2 -> -20.528182 | AZ28: =SUM(AT28:AY28) -> 168.31619 | BA28: =AO28-AZ28 -> 3823.5745 | BB28: =E28-I28 -> 8924.45 | BC28: =E28-AS28-I28 -> 8240.1773 | BD28: =BC28-BA28-Z28 -> 1865.5227 | BE28: =BD28/BC28 -> 0.22639352 | BH28: 后面三天9折
A29: 0428~0504 | B29: 2025W18 | C29: 414 | D29: 390 | E29: 9670.56 | J29: 34 | K29: =J29/C29 -> 0.082125604 | L29: 698.13 | M29: =(C29-C28)/C28 -> 0.061538462 | N29: =(D29-D28)/D28 -> 0.095505618 | O29: =(E29-E28)/E28 -> 0.083602911 | P29: =C29/D29 -> 1.0615385 | Q29: =E29/D29 -> 24.796308 | R29: =E29/C29 -> 23.358841 | S29: =C29/7 -> 59.142857 | T29: =D29-Y29 -> 154 | U29: =T29/D29 -> 0.39487179 | V29: =Z29/(E29-I29) -> 0.25833974 | W29: 224859 | X29: 2444 | Y29: 236 | Z29: 2498.29 | AA29: 5740.71 | AB29: 1.02 | AC29: =Z29/AA29 -> 0.43518833 | AD29: =X29/W29 -> 0.010869033 | AE29: =Y29/X29 -> 0.096563011 | AF29: =Z29/Y29 -> 10.585975 | AG29: 110 | AH29: 217 | AI29: 87 | AJ29: =AG29*产品成本!$D$2+AH29*产品成本!$D$3+AI29*产品成本!$D$4 -> 978.80282 | AK29: =AG29*产品成本!$E$2+AH29*产品成本!$E$3+AI29*产品成本!$E$4 -> 79.202235 | AL29: =AG29*产品成本!$F$2+AH29*产品成本!$F$3+AI29*产品成本!$F$4 -> 140.76 | AM29: =AG29*产品成本!$G$2+AH29*产品成本!$G$3+AI29*产品成本!$G$4 -> 1591.5 | AN29: =(E29-I29)*0.15 -> 1450.584 | AO29: =SUM(AJ29:AN29) -> 4240.8491 | AP29: 8 | AQ29: 17 | AR29: 9 | AS29: =L29/(1-0.15+0.15*0.2) -> 793.32955 | AT29: =AP29*产品成本!$D$2+AQ29*产品成本!$D$3+AR29*产品成本!$D$4 -> 82.605634 | AU29: =AP29*产品成本!$E$2+AQ29*产品成本!$E$3+AR29*产品成本!$E$4 -> 6.5562887 | AV29: =AP29*产品成本!$F$2+AQ29*产品成本!$F$3+AR29*产品成本!$F$4 -> 11.56 | AX29: =AS29*0.15 -> 118.99943 | AY29: =-AX29*0.2 -> -23.799886 | AZ29: =SUM(AT29:AY29) -> 195.92147 | BA29: =AO29-AZ29 -> 4044.9276 | BB29: =E29-I29 -> 9670.56 | BC29: =E29-AS29-I29 -> 8877.2305 | BD29: =BC29-BA29-Z29 -> 2334.0129 | BE29: =BD29/BC29 -> 0.26292129 | BG29: 5.5FT多巴胺出现断货 | BH29: 后面三天9折
A30: 0505~0511 | B30: 2025W19 | C30: 463 | D30: 435 | E30: 11347.24 | J30: 33 | K30: =J30/C30 -> 0.071274298 | L30: 661.95 | M30: =(C30-C29)/C29 -> 0.11835749 | N30: =(D30-D29)/D29 -> 0.11538462 | O30: =(E30-E29)/E29 -> 0.17337982 | P30: =C30/D30 -> 1.0643678 | Q30: =E30/D30 -> 26.085609 | R30: =E30/C30 -> 24.508078 | S30: =C30/7 -> 66.142857 | T30: =D30-Y30 -> 151 | U30: =T30/D30 -> 0.34712644 | V30: =Z30/(E30-I30) -> 0.24144373 | W30: 250034 | X30: 2650 | Y30: 284 | Z30: 2739.72 | AA30: 7513.18 | AB30: 1.03 | AC30: =Z30/AA30 -> 0.36465518 | AD30: =X30/W30 -> 0.010598559 | AE30: =Y30/X30 -> 0.10716981 | AF30: =Z30/Y30 -> 9.6469014 | AG30: 125 | AH30: 229 | AI30: 109 | AJ30: =AG30*产品成本!$D$2+AH30*产品成本!$D$3+AI30*产品成本!$D$4 -> 1108.662 | AK30: =AG30*产品成本!$E$2+AH30*产品成本!$E$3+AI30*产品成本!$E$4 -> 88.739823 | AL30: =AG30*产品成本!$F$2+AH30*产品成本!$F$3+AI30*产品成本!$F$4 -> 157.42 | AM30: =AG30*产品成本!$G$2+AH30*产品成本!$G$3+AI30*产品成本!$G$4 -> 1779.45 | AN30: =(E30-I30)*0.15 -> 1702.086 | AO30: =SUM(AJ30:AN30) -> 4836.3578 | AP30: 11 | AQ30: 17 | AR30: 5 | AS30: =L30/(1-0.15+0.15*0.2) -> 752.21591 | AT30: =AP30*产品成本!$D$2+AQ30*产品成本!$D$3+AR30*产品成本!$D$4 -> 75.704225 | AU30: =AP30*产品成本!$E$2+AQ30*产品成本!$E$3+AR30*产品成本!$E$4 -> 6.2371099 | AV30: =AP30*产品成本!$F$2+AQ30*产品成本!$F$3+AR30*产品成本!$F$4 -> 11.22 | AX30: =AS30*0.15 -> 112.83239 | AY30: =-AX30*0.2 -> -22.566477 | AZ30: =SUM(AT30:AY30) -> 183.42724 | BA30: =AO30-AZ30 -> 4652.9306 | BB30: =E30-I30 -> 11347.24 | BC30: =E30-AS30-I30 -> 10595.024 | BD30: =BC30-BA30-Z30 -> 3202.3735 | BE30: =BD30/BC30 -> 0.3022526
A31: 0512~0518 | B31: 2025W20 | C31: 373 | D31: 360 | E31: 9134.48 | F31: 29 | G31: 29 | H31: 721.31 | I31: 63.1 | J31: 23 | K31: =J31/C31 -> 0.061662198 | L31: 487.61 | M31: =(C31-C30)/C30 -> -0.19438445 | N31: =(D31-D30)/D30 -> -0.17241379 | O31: =(E31-E30)/E30 -> -0.19500425 | P31: =C31/D31 -> 1.0361111 | Q31: =E31/D31 -> 25.373556 | R31: =E31/C31 -> 24.489223 | S31: =C31/7 -> 53.285714 | T31: =D31-Y31 -> 147 | U31: =T31/D31 -> 0.40833333 | V31: =Z31/(E31-I31) -> 0.27482037 | W31: 329751 | X31: 2477 | Y31: 213 | Z31: 2493 | AA31: 5394.2 | AB31: 1.01 | AC31: =Z31/AA31 -> 0.46216306 | AD31: =X31/W31 -> 0.0075117285 | AE31: =Y31/X31 -> 0.085991118 | AF31: =Z31/Y31 -> 11.704225 | AG31: 84 | AH31: 170 | AI31: 119 | AJ31: =AG31*产品成本!$D$2+AH31*产品成本!$D$3+AI31*产品成本!$D$4 -> 930.49296 | AK31: =AG31*产品成本!$E$2+AH31*产品成本!$E$3+AI31*产品成本!$E$4 -> 72.347315 | AL31: =AG31*产品成本!$F$2+AH31*产品成本!$F$3+AI31*产品成本!$F$4 -> 126.82 | AM31: =AG31*产品成本!$G$2+AH31*产品成本!$G$3+AI31*产品成本!$G$4 -> 1437.06 | AN31: =(E31-I31)*0.15 -> 1360.707 | AO31: =SUM(AJ31:AN31) -> 3927.4273 | AP31: 5 | AQ31: 12 | AR31: 6 | AS31: =L31/(1-0.15+0.15*0.2) -> 554.10227 | AT31: =AP31*产品成本!$D$2+AQ31*产品成本!$D$3+AR31*产品成本!$D$4 -> 55.774648 | AU31: =AP31*产品成本!$E$2+AQ31*产品成本!$E$3+AR31*产品成本!$E$4 -> 4.4415169 | AV31: =AP31*产品成本!$F$2+AQ31*产品成本!$F$3+AR31*产品成本!$F$4 -> 7.82 | AX31: =AS31*0.15 -> 83.115341 | AY31: =-AX31*0.2 -> -16.623068 | AZ31: =SUM(AT31:AY31) -> 134.52844 | BA31: =AO31-AZ31 -> 3792.8988 | BB31: =E31-I31 -> 9071.38 | BC31: =E31-AS31-I31 -> 8517.2777 | BD31: =BC31-BA31-Z31 -> 2231.3789 | BE31: =BD31/BC31 -> 0.26198264 | BG31: 粉色三尺寸彻底断货上周销量20+,粉色SKU的流量切断 | BH31: 原价
A32: 0519~0525 | B32: 2025W21 | C32: 415 | D32: 392 | E32: 10098.35 | F32: 96 | G32: 90 | H32: 2303.24 | I32: 288.75 | J32: 27 | K32: =J32/C32 -> 0.065060241 | L32: 574.62 | M32: =(C32-C31)/C31 -> 0.11260054 | N32: =(D32-D31)/D31 -> 0.088888889 | O32: =(E32-E31)/E31 -> 0.10551996 | P32: =C32/D32 -> 1.0586735 | Q32: =E32/D32 -> 25.761097 | R32: =E32/C32 -> 24.333373 | S32: =C32/7 -> 59.285714 | T32: =D32-Y32 -> 150 | U32: =T32/D32 -> 0.38265306 | V32: =Z32/(E32-I32) -> 0.28468949 | W32: 550872 | X32: 2687 | Y32: 242 | Z32: 2792.69 | AA32: 6031.52 | AB32: 1.04 | AC32: =Z32/AA32 -> 0.46301596 | AD32: =X32/W32 -> 0.0048777211 | AE32: =Y32/X32 -> 0.090063268 | AF32: =Z32/Y32 -> 11.540041 | AG32: 120 | AH32: 178 | AI32: 117 | AJ32: =AG32*产品成本!$D$2+AH32*产品成本!$D$3+AI32*产品成本!$D$4 -> 1016.831 | AK32: =AG32*产品成本!$E$2+AH32*产品成本!$E$3+AI32*产品成本!$E$4 -> 79.71949 | AL32: =AG32*产品成本!$F$2+AH32*产品成本!$F$3+AI32*产品成本!$F$4 -> 141.1 | AM32: =AG32*产品成本!$G$2+AH32*产品成本!$G$3+AI32*产品成本!$G$4 -> 1593.3 | AN32: =(E32-I32)*0.15 -> 1471.44 | AO32: =SUM(AJ32:AN32) -> 4302.3905 | AP32: 5 | AQ32: 13 | AR32: 9 | AS32: =L32/(1-0.15+0.15*0.2) -> 652.97727 | AT32: =AP32*产品成本!$D$2+AQ32*产品成本!$D$3+AR32*产品成本!$D$4 -> 67.816901 | AU32: =AP32*产品成本!$E$2+AQ32*产品成本!$E$3+AR32*产品成本!$E$4 -> 5.264307 | AV32: =AP32*产品成本!$F$2+AQ32*产品成本!$F$3+AR32*产品成本!$F$4 -> 9.18 | AX32: =AS32*0.15 -> 97.946591 | AY32: =-AX32*0.2 -> -19.589318 | AZ32: =SUM(AT32:AY32) -> 160.61848 | BA32: =AO32-AZ32 -> 4141.772 | BB32: =E32-I32 -> 9809.6 | BC32: =E32-AS32-I32 -> 9156.6227 | BD32: =BC32-BA32-Z32 -> 2222.1607 | BE32: =BD32/BC32 -> 0.24268344 | BG32: 本周五促销LD,85折
A33: 0526~0601 | B33: 2025W22 | C33: 400 | D33: 382 | E33: 9152.47 | F33: 27 | G33: 26 | H33: 611.41 | I33: 57.15 | J33: 39 | K33: =J33/C33 -> 0.0975 | L33: 806.14 | M33: =(C33-C32)/C32 -> -0.036144578 | N33: =(D33-D32)/D32 -> -0.025510204 | O33: =(E33-E32)/E32 -> -0.093666787 | P33: =C33/D33 -> 1.0471204 | Q33: =E33/D33 -> 23.959346 | R33: =E33/C33 -> 22.881175 | S33: =C33/7 -> 57.142857 | T33: =D33-Y33 -> 144 | U33: =T33/D33 -> 0.37696335 | V33: =Z33/(E33-I33) -> 0.31048165 | W33: 261666 | X33: 2721 | Y33: 238 | Z33: 2823.93 | AA33: 5786.5 | AB33: 1.04 | AC33: =Z33/AA33 -> 0.48802039 | AD33: =X33/W33 -> 0.010398753 | AE33: =Y33/X33 -> 0.087467843 | AF33: =Z33/Y33 -> 11.865252 | AG33: 117 | AH33: 172 | AI33: 111 | AJ33: =AG33*产品成本!$D$2+AH33*产品成本!$D$3+AI33*产品成本!$D$4 -> 977.95775 | AK33: =AG33*产品成本!$E$2+AH33*产品成本!$E$3+AI33*产品成本!$E$4 -> 76.781928 | AL33: =AG33*产品成本!$F$2+AH33*产品成本!$F$3+AI33*产品成本!$F$4 -> 136 | AM33: =AG33*产品成本!$G$2+AH33*产品成本!$G$3+AI33*产品成本!$G$4 -> 1535.43 | AN33: =(E33-I33)*0.15 -> 1364.298 | AO33: =SUM(AJ33:AN33) -> 4090.4677 | AP33: 12 | AQ33: 16 | AR33: 11 | AS33: =L33/(1-0.15+0.15*0.2) -> 916.06818 | AT33: =AP33*产品成本!$D$2+AQ33*产品成本!$D$3+AR33*产品成本!$D$4 -> 95.56338 | AU33: =AP33*产品成本!$E$2+AQ33*产品成本!$E$3+AR33*产品成本!$E$4 -> 7.4779268 | AV33: =AP33*产品成本!$F$2+AQ33*产品成本!$F$3+AR33*产品成本!$F$4 -> 13.26 | AX33: =AS33*0.15 -> 137.41023 | AY33: =-AX33*0.2 -> -27.482045 | AZ33: =SUM(AT33:AY33) -> 226.22949 | BA33: =AO33-AZ33 -> 3864.2382 | BB33: =E33-I33 -> 9095.32 | BC33: =E33-AS33-I33 -> 8179.2518 | BD33: =BC33-BA33-Z33 -> 1491.0836 | BE33: =BD33/BC33 -> 0.18230074 | BG33: 上周测试了SB SD广告开头效果不佳，退货略高 | BH33: 9折
A34: 0602~0608 | B34: 2025W23 | C34: 429 | D34: 395 | E34: 10442.62 | F34: 49 | G34: 41 | H34: 1233.71 | I34: 75.81 | J34: 43 | K34: =J34/C34 -> 0.1002331 | L34: 911.89 | M34: =(C34-C33)/C33 -> 0.0725 | N34: =(D34-D33)/D33 -> 0.034031414 | O34: =(E34-E33)/E33 -> 0.14096195 | P34: =C34/D34 -> 1.0860759 | Q34: =E34/D34 -> 26.437013 | R34: =E34/C34 -> 24.341772 | S34: =C34/7 -> 61.285714 | T34: =D34-Y34 -> 141 | U34: =T34/D34 -> 0.35696203 | V34: =Z34/(E34-I34) -> 0.25956683 | W34: 238222 | X34: 2771 | Y34: 254 | Z34: 2690.88 | AA34: 6334.77 | AB34: 0.97 | AC34: =Z34/AA34 -> 0.42477943 | AD34: =X34/W34 -> 0.011632007 | AE34: =Y34/X34 -> 0.091663659 | AF34: =Z34/Y34 -> 10.594016 | AG34: 108 | AH34: 221 | AI34: 100 | AJ34: =AG34*产品成本!$D$2+AH34*产品成本!$D$3+AI34*产品成本!$D$4 -> 1026.0563 | AK34: =AG34*产品成本!$E$2+AH34*产品成本!$E$3+AI34*产品成本!$E$4 -> 82.356182 | AL34: =AG34*产品成本!$F$2+AH34*产品成本!$F$3+AI34*产品成本!$F$4 -> 145.86 | AM34: =AG34*产品成本!$G$2+AH34*产品成本!$G$3+AI34*产品成本!$G$4 -> 1650.42 | AN34: =(E34-I34)*0.15 -> 1555.0215 | AO34: =SUM(AJ34:AN34) -> 4459.714 | AP34: 7 | AQ34: 20 | AR34: 16 | AS34: =L34/(1-0.15+0.15*0.2) -> 1036.2386 | AT34: =AP34*产品成本!$D$2+AQ34*产品成本!$D$3+AR34*产品成本!$D$4 -> 110 | AU34: =AP34*产品成本!$E$2+AQ34*产品成本!$E$3+AR34*产品成本!$E$4 -> 8.4310521 | AV34: =AP34*产品成本!$F$2+AQ34*产品成本!$F$3+AR34*产品成本!$F$4 -> 14.62 | AX34: =AS34*0.15 -> 155.4358 | AY34: =-AX34*0.2 -> -31.087159 | AZ34: =SUM(AT34:AY34) -> 257.39969 | BA34: =AO34-AZ34 -> 4202.3143 | BB34: =E34-I34 -> 10366.81 | BC34: =E34-AS34-I34 -> 9330.5714 | BD34: =BC34-BA34-Z34 -> 2437.377 | BE34: =BD34/BC34 -> 0.26122484
A35: 0609~0615 | B35: 2025W24 | C35: 411 | D35: 383 | E35: 10097.4 | F35: 59 | G35: 59 | H35: 1913.42 | I35: 245.79 | J35: 16 | K35: =J35/C35 -> 0.03892944 | L35: 317.88 | M35: =(C35-C34)/C34 -> -0.041958042 | N35: =(D35-D34)/D34 -> -0.030379747 | O35: =(E35-E34)/E34 -> -0.033058753 | P35: =C35/D35 -> 1.073107 | Q35: =E35/D35 -> 26.363969 | R35: =E35/C35 -> 24.567883 | S35: =C35/7 -> 58.714286 | T35: =D35-Y35 -> 143 | U35: =T35/D35 -> 0.37336815 | V35: =Z35/(E35-I35) -> 0.29860398 | W35: 309763 | X35: 3025 | Y35: 240 | Z35: 2941.73 | AA35: 6135.47 | AB35: 0.97 | AC35: =Z35/AA35 -> 0.47946286 | AD35: =X35/W35 -> 0.0097655304 | AE35: =Y35/X35 -> 0.079338843 | AF35: =Z35/Y35 -> 12.257208 | AG35: 90 | AH35: 194 | AI35: 150 | AJ35: =AG35*产品成本!$D$2+AH35*产品成本!$D$3+AI35*产品成本!$D$4 -> 1096.4789 | AK35: =AG35*产品成本!$E$2+AH35*产品成本!$E$3+AI35*产品成本!$E$4 -> 84.525921 | AL35: =AG35*产品成本!$F$2+AH35*产品成本!$F$3+AI35*产品成本!$F$4 -> 147.56 | AM35: =AG35*产品成本!$G$2+AH35*产品成本!$G$3+AI35*产品成本!$G$4 -> 1673.7 | AN35: =(E35-I35)*0.15 -> 1477.7415 | AO35: =SUM(AJ35:AN35) -> 4480.0063 | AP35: 9 | AQ35: 5 | AR35: 2 | AS35: =L35/(1-0.15+0.15*0.2) -> 361.22727 | AT35: =AP35*产品成本!$D$2+AQ35*产品成本!$D$3+AR35*产品成本!$D$4 -> 36.197183 | AU35: =AP35*产品成本!$E$2+AQ35*产品成本!$E$3+AR35*产品成本!$E$4 -> 2.9464141 | AV35: =AP35*产品成本!$F$2+AQ35*产品成本!$F$3+AR35*产品成本!$F$4 -> 5.44 | AX35: =AS35*0.15 -> 54.184091 | AY35: =-AX35*0.2 -> -10.836818 | AZ35: =SUM(AT35:AY35) -> 87.93087 | BA35: =AO35-AZ35 -> 4392.0754 | BB35: =E35-I35 -> 9851.61 | BC35: =E35-AS35-I35 -> 9490.3827 | BD35: =BC35-BA35-Z35 -> 2156.5773 | BE35: =BD35/BC35 -> 0.22723818
A36: 0616~0622 | B36: 2025W25 | C36: 403 | D36: 379 | E36: 9785.09 | F36: 41 | G36: 39 | H36: 1009.39 | I36: 91.31 | J36: 29 | K36: =J36/C36 -> 0.071960298 | L36: 595.28 | M36: =(C36-C35)/C35 -> -0.01946472 | N36: =(D36-D35)/D35 -> -0.010443864 | O36: =(E36-E35)/E35 -> -0.030929744 | P36: =C36/D36 -> 1.0633245 | Q36: =E36/D36 -> 25.818179 | R36: =E36/C36 -> 24.28062 | S36: =C36/7 -> 57.571429 | T36: =D36-Y36 -> 129 | U36: =T36/D36 -> 0.34036939 | V36: =Z36/(E36-I36) -> 0.29276299 | W36: 259867 | X36: 2668 | Y36: 250 | Z36: 2837.98 | AA36: 6226.65 | AB36: 1.06 | AC36: =Z36/AA36 -> 0.45577959 | AD36: =X36/W36 -> 0.01026679 | AE36: =Y36/X36 -> 0.093703148 | AF36: =Z36/Y36 -> 11.35192 | AG36: 114 | AH36: 160 | AI36: 129 | AJ36: =AG36*产品成本!$D$2+AH36*产品成本!$D$3+AI36*产品成本!$D$4 -> 1005.8451 | AK36: =AG36*产品成本!$E$2+AH36*产品成本!$E$3+AI36*产品成本!$E$4 -> 77.727625 | AL36: =AG36*产品成本!$F$2+AH36*产品成本!$F$3+AI36*产品成本!$F$4 -> 137.02 | AM36: =AG36*产品成本!$G$2+AH36*产品成本!$G$3+AI36*产品成本!$G$4 -> 1547.76 | AN36: =(E36-I36)*0.15 -> 1454.067 | AO36: =SUM(AJ36:AN36) -> 4222.4197 | AP36: 8 | AQ36: 16 | AR36: 5 | AS36: =L36/(1-0.15+0.15*0.2) -> 676.45455 | AT36: =AP36*产品成本!$D$2+AQ36*产品成本!$D$3+AR36*产品成本!$D$4 -> 67.253521 | AU36: =AP36*产品成本!$E$2+AQ36*产品成本!$E$3+AR36*产品成本!$E$4 -> 5.5234986 | AV36: =AP36*产品成本!$F$2+AQ36*产品成本!$F$3+AR36*产品成本!$F$4 -> 9.86 | AX36: =AS36*0.15 -> 101.46818 | AY36: =-AX36*0.2 -> -20.293636 | AZ36: =SUM(AT36:AY36) -> 163.81157 | BA36: =AO36-AZ36 -> 4058.6081 | BB36: =E36-I36 -> 9693.78 | BC36: =E36-AS36-I36 -> 9017.3255 | BD36: =BC36-BA36-Z36 -> 2120.7373 | BE36: =BD36/BC36 -> 0.23518474
A37: 0623~0629 | B37: 2025W26 | C37: 419 | D37: 402 | E37: 9316.53 | F37: 56 | G37: 55 | H37: 1311.09 | I37: 158.54 | J37: 21 | K37: =J37/C37 -> 0.050119332 | L37: 426.53 | M37: =(C37-C36)/C36 -> 0.039702233 | N37: =(D37-D36)/D36 -> 0.060686016 | O37: =(E37-E36)/E36 -> -0.047885099 | P37: =C37/D37 -> 1.0422886 | Q37: =E37/D37 -> 23.175448 | R37: =E37/C37 -> 22.235155 | S37: =C37/7 -> 59.857143 | T37: =D37-Y37 -> 139 | U37: =T37/D37 -> 0.34577114 | V37: =Z37/(E37-I37) -> 0.30174853 | W37: 254466 | X37: 2593 | Y37: 263 | Z37: 2763.41 | AA37: 5980.15 | AB37: 1.07 | AC37: =Z37/AA37 -> 0.4620971 | AD37: =X37/W37 -> 0.010189966 | AE37: =Y37/X37 -> 0.10142692 | AF37: =Z37/Y37 -> 10.507262 | AG37: 119 | AH37: 144 | AI37: 156 | AJ37: =AG37*产品成本!$D$2+AH37*产品成本!$D$3+AI37*产品成本!$D$4 -> 1071.9718 | AK37: =AG37*产品成本!$E$2+AH37*产品成本!$E$3+AI37*产品成本!$E$4 -> 81.181018 | AL37: =AG37*产品成本!$F$2+AH37*产品成本!$F$3+AI37*产品成本!$F$4 -> 142.46 | AM37: =AG37*产品成本!$G$2+AH37*产品成本!$G$3+AI37*产品成本!$G$4 -> 1609.11 | AN37: =(E37-I37)*0.15 -> 1373.6985 | AO37: =SUM(AJ37:AN37) -> 4278.4213 | AP37: 7 | AQ37: 7 | AR37: 7 | AS37: =L37/(1-0.15+0.15*0.2) -> 484.69318 | AT37: =AP37*产品成本!$D$2+AQ37*产品成本!$D$3+AR37*产品成本!$D$4 -> 52.746479 | AU37: =AP37*产品成本!$E$2+AQ37*产品成本!$E$3+AR37*产品成本!$E$4 -> 4.0347803 | AV37: =AP37*产品成本!$F$2+AQ37*产品成本!$F$3+AR37*产品成本!$F$4 -> 7.14 | AX37: =AS37*0.15 -> 72.703977 | AY37: =-AX37*0.2 -> -14.540795 | AZ37: =SUM(AT37:AY37) -> 122.08444 | BA37: =AO37-AZ37 -> 4156.3369 | BB37: =E37-I37 -> 9157.99 | BC37: =E37-AS37-I37 -> 8673.2968 | BD37: =BC37-BA37-Z37 -> 1753.5499 | BE37: =BD37/BC37 -> 0.20217801
A38: 0630~0706 | B38: 2025W27 | C38: 392 | D38: 375 | E38: 8810.43 | F38: 19 | G38: 16 | H38: 425.76 | I38: 36.29 | J38: 25 | K38: =J38/C38 -> 0.06377551 | L38: 431.32 | M38: =(C38-C37)/C37 -> -0.064439141 | N38: =(D38-D37)/D37 -> -0.067164179 | O38: =(E38-E37)/E37 -> -0.0543228 | P38: =C38/D38 -> 1.0453333 | Q38: =E38/D38 -> 23.49448 | R38: =E38/C38 -> 22.475587 | S38: =C38/7 -> 56 | T38: =D38-Y38 -> 90 | U38: =T38/D38 -> 0.24 | V38: =Z38/(E38-I38) -> 0.32948756 | W38: 231377 | X38: 2629 | Y38: 285 | Z38: 2890.97 | AA38: 6529.11 | AB38: 1.1 | AC38: =Z38/AA38 -> 0.44278163 | AD38: =X38/W38 -> 0.011362409 | AE38: =Y38/X38 -> 0.10840624 | AF38: =Z38/Y38 -> 10.143754 | AG38: 106 | AH38: 129 | AI38: 157 | AJ38: =AG38*产品成本!$D$2+AH38*产品成本!$D$3+AI38*产品成本!$D$4 -> 1016.1268 | AK38: =AG38*产品成本!$E$2+AH38*产品成本!$E$3+AI38*产品成本!$E$4 -> 76.242275 | AL38: =AG38*产品成本!$F$2+AH38*产品成本!$F$3+AI38*产品成本!$F$4 -> 133.28 | AM38: =AG38*产品成本!$G$2+AH38*产品成本!$G$3+AI38*产品成本!$G$4 -> 1506.54 | AN38: =(E38-I38)*0.15 -> 1316.121 | AO38: =SUM(AJ38:AN38) -> 4048.31 | AP38: 4 | AQ38: 8 | AR38: 13 | AS38: =L38/(1-0.15+0.15*0.2) -> 490.13636 | AT38: =AP38*产品成本!$D$2+AQ38*产品成本!$D$3+AR38*产品成本!$D$4 -> 68.380282 | AU38: =AP38*产品成本!$E$2+AQ38*产品成本!$E$3+AR38*产品成本!$E$4 -> 4.9667493 | AV38: =AP38*产品成本!$F$2+AQ38*产品成本!$F$3+AR38*产品成本!$F$4 -> 8.5 | AX38: =AS38*0.15 -> 73.520455 | AY38: =-AX38*0.2 -> -14.704091 | AZ38: =SUM(AT38:AY38) -> 140.66339 | BA38: =AO38-AZ38 -> 3907.6466 | BB38: =E38-I38 -> 8774.14 | BC38: =E38-AS38-I38 -> 8284.0036 | BD38: =BC38-BA38-Z38 -> 1485.387 | BE38: =BD38/BC38 -> 0.17930786 | BG38: 7.4独立日，销量37，ACOAS=39.28%
A39: 0708~0711 | B39: PD2025 4 Days | C39: 542 | D39: 508 | E39: 10601.36 | F39: 0 | G39: 0 | H39: 0 | I39: 0 | J39: 30 | K39: =J39/C39 -> 0.055350554 | L39: 594.68 | M39: =(C39-C38)/C38 -> 0.38265306 | N39: =(D39-D38)/D38 -> 0.35466667 | O39: =(E39-E38)/E38 -> 0.20327385 | P39: =C39/D39 -> 1.0669291 | Q39: =E39/D39 -> 20.868819 | R39: =E39/C39 -> 19.559705 | S39: =C39/4 -> 135.5 | T39: =D39-Y39 -> 211 | U39: =T39/D39 -> 0.41535433 | V39: =Z39/(E39-I39) -> 0.25819517 | W39: 226717 | X39: 2425 | Y39: 297 | Z39: 2737.22 | AA39: 6015.47 | AB39: 1.13 | AC39: =Z39/AA39 -> 0.45503011 | AD39: =X39/W39 -> 0.010696154 | AE39: =Y39/X39 -> 0.12247423 | AF39: =Z39/Y39 -> 9.216229 | AG39: 143 | AH39: 187 | AI39: 212 | AJ39: =AG39*产品成本!$D$2+AH39*产品成本!$D$3+AI39*产品成本!$D$4 -> 1398.8732 | AK39: =AG39*产品成本!$E$2+AH39*产品成本!$E$3+AI39*产品成本!$E$4 -> 105.39756 | AL39: =AG39*产品成本!$F$2+AH39*产品成本!$F$3+AI39*产品成本!$F$4 -> 184.28 | AM39: =AG39*产品成本!$G$2+AH39*产品成本!$G$3+AI39*产品成本!$G$4 -> 2083.77 | AN39: =(E39-I39)*0.15 -> 1590.204 | AO39: =SUM(AJ39:AN39) -> 5362.5248 | AP39: 6 | AQ39: 13 | AR39: 4 | AS39: =L39/(1-0.15+0.15*0.2) -> 675.77273 | AT39: =AP39*产品成本!$D$2+AQ39*产品成本!$D$3+AR39*产品成本!$D$4 -> 53.380282 | AU39: =AP39*产品成本!$E$2+AQ39*产品成本!$E$3+AR39*产品成本!$E$4 -> 4.3879141 | AV39: =AP39*产品成本!$F$2+AQ39*产品成本!$F$3+AR39*产品成本!$F$4 -> 7.82 | AX39: =AS39*0.15 -> 101.36591 | AY39: =-AX39*0.2 -> -20.273182 | AZ39: =SUM(AT39:AY39) -> 146.68092 | BA39: =AO39-AZ39 -> 5215.8439 | BB39: =E39-I39 -> 10601.36 | BC39: =E39-AS39-I39 -> 9925.5873 | BD39: =BC39-BA39-Z39 -> 1972.5234 | BE39: =BD39/BC39 -> 0.19873115
A40: 0707~0713 | B40: 2025W28 | C40: 735 | D40: 694 | E40: 14720.75 | F40: 0 | G40: 0 | H40: 0 | I40: 0 | J40: 43 | K40: =J40/C40 -> 0.058503401 | L40: 855.49 | M40: =(C40-C39)/C39 -> 0.35608856 | N40: =(D40-D39)/D39 -> 0.36614173 | O40: =(E40-E39)/E39 -> 0.38857184 | P40: =C40/D40 -> 1.0590778 | Q40: =E40/D40 -> 21.211455 | R40: =E40/C40 -> 20.028231 | S40: =C40/7 -> 105 | T40: =D40-Y40 -> 229 | U40: =T40/D40 -> 0.32997118 | V40: =Z40/(E40-I40) -> 0.2748936 | W40: 331218 | X40: 3643 | Y40: 465 | Z40: 4046.64 | AA40: 9606.34 | AB40: 1.11 | AC40: =Z40/AA40 -> 0.4212468 | AD40: =X40/W40 -> 0.010998798 | AE40: =Y40/X40 -> 0.12764205 | AF40: =Z40/Y40 -> 8.7024516 | AG40: 197 | AH40: 261 | AI40: 277 | AJ40: =AG40*产品成本!$D$2+AH40*产品成本!$D$3+AI40*产品成本!$D$4 -> 1884.4366 | AK40: =AG40*产品成本!$E$2+AH40*产品成本!$E$3+AI40*产品成本!$E$4 -> 142.68881 | AL40: =AG40*产品成本!$F$2+AH40*产品成本!$F$3+AI40*产品成本!$F$4 -> 249.9 | AM40: =AG40*产品成本!$G$2+AH40*产品成本!$G$3+AI40*产品成本!$G$4 -> 2825.13 | AN40: =(E40-I40)*0.15 -> 2208.1125 | AO40: =SUM(AJ40:AN40) -> 7310.2679 | AP40: 10 | AQ40: 17 | AR40: 16 | AS40: =L40/(1-0.15+0.15*0.2) -> 972.14773 | AT40: =AP40*产品成本!$D$2+AQ40*产品成本!$D$3+AR40*产品成本!$D$4 -> 110 | AU40: =AP40*产品成本!$E$2+AQ40*产品成本!$E$3+AR40*产品成本!$E$4 -> 8.3735028 | AV40: =AP40*产品成本!$F$2+AQ40*产品成本!$F$3+AR40*产品成本!$F$4 -> 14.62 | AX40: =AS40*0.15 -> 145.82216 | AY40: =-AX40*0.2 -> -29.164432 | AZ40: =SUM(AT40:AY40) -> 249.65123 | BA40: =AO40-AZ40 -> 7060.6167 | BB40: =E40-I40 -> 14720.75 | BC40: =E40-AS40-I40 -> 13748.602 | BD40: =BC40-BA40-Z40 -> 2641.3456 | BE40: =BD40/BC40 -> 0.19211739
A41: 0714~0720 | B41: 2025W29 | C41: 425 | D41: 403 | E41: 10003.3 | F41: 31 | G41: 30 | H41: 768.09 | I41: 69.56 | J41: 41 | K41: =J41/C41 -> 0.096470588 | L41: 753.49 | M41: =(C41-C40)/C40 -> -0.42176871 | N41: =(D41-D40)/D40 -> -0.41930836 | O41: =(E41-E40)/E40 -> -0.32046261 | P41: =C41/D41 -> 1.0545906 | Q41: =E41/D41 -> 24.822084 | R41: =E41/C41 -> 23.537176 | S41: =C41/7 -> 60.714286 | T41: =D41-Y41 -> 152 | U41: =T41/D41 -> 0.37717122 | V41: =Z41/(E41-I41) -> 0.2435256 | W41: 199964 | X41: 2365 | Y41: 251 | Z41: 2419.12 | AA41: 6289.86 | AB41: ‎1.02 | AC41: =Z41/AA41 -> 0.38460633 | AD41: =X41/W41 -> 0.011827129 | AE41: =Y41/X41 -> 0.10613108 | AF41: =Z41/Y41 -> 9.6379283 | AG41: 112 | AH41: 184 | AI41: 129 | AJ41: =AG41*产品成本!$D$2+AH41*产品成本!$D$3+AI41*产品成本!$D$4 -> 1052.3239 | AK41: =AG41*产品成本!$E$2+AH41*产品成本!$E$3+AI41*产品成本!$E$4 -> 82.007375 | AL41: =AG41*产品成本!$F$2+AH41*产品成本!$F$3+AI41*产品成本!$F$4 -> 144.5 | AM41: =AG41*产品成本!$G$2+AH41*产品成本!$G$3+AI41*产品成本!$G$4 -> 1633.98 | AN41: =(E41-I41)*0.15 -> 1490.061 | AO41: =SUM(AJ41:AN41) -> 4402.8723 | AP41: 15 | AQ41: 10 | AR41: 16 | AS41: =L41/(1-0.15+0.15*0.2) -> 856.23864 | AT41: =AP41*产品成本!$D$2+AQ41*产品成本!$D$3+AR41*产品成本!$D$4 -> 105.77465 | AU41: =AP41*产品成本!$E$2+AQ41*产品成本!$E$3+AR41*产品成本!$E$4 -> 7.892007 | AV41: =AP41*产品成本!$F$2+AQ41*产品成本!$F$3+AR41*产品成本!$F$4 -> 13.94 | AX41: =AS41*0.15 -> 128.4358 | AY41: =-AX41*0.2 -> -25.687159 | AZ41: =SUM(AT41:AY41) -> 230.35529 | BA41: =AO41-AZ41 -> 4172.517 | BB41: =E41-I41 -> 9933.74 | BC41: =E41-AS41-I41 -> 9077.5014 | BD41: =BC41-BA41-Z41 -> 2485.8643 | BE41: =BD41/BC41 -> 0.27384896
A42: 0721~0727 | B42: 2025W30 | C42: 383 | D42: 366 | E42: 9301.87 | F42: 44 | G42: 38 | H42: 1056.86 | I42: 87.45 | J42: 40 | K42: =J42/C42 -> 0.10443864 | L42: 720.26 | M42: =(C42-C41)/C41 -> -0.098823529 | N42: =(D42-D41)/D41 -> -0.091811414 | O42: =(E42-E41)/E41 -> -0.07011986 | P42: =C42/D42 -> 1.0464481 | Q42: =E42/D42 -> 25.414945 | R42: =E42/C42 -> 24.286867 | S42: =C42/7 -> 54.714286 | T42: =D42-Y42 -> 135 | U42: =T42/D42 -> 0.36885246 | V42: =Z42/(E42-I42) -> 0.25285694 | W42: 200165 | X42: 2315 | Y42: 231 | Z42: 2329.93 | AA42: 5705.61 | AB42: 1.01 | AC42: =Z42/AA42 -> 0.40835774 | AD42: =X42/W42 -> 0.011565458 | AE42: =Y42/X42 -> 0.099784017 | AF42: =Z42/Y42 -> 10.086277 | AG42: 110 | AH42: 185 | AI42: 88 | AJ42: =AG42*产品成本!$D$2+AH42*产品成本!$D$3+AI42*产品成本!$D$4 -> 914.50704 | AK42: =AG42*产品成本!$E$2+AH42*产品成本!$E$3+AI42*产品成本!$E$4 -> 73.242951 | AL42: =AG42*产品成本!$F$2+AH42*产品成本!$F$3+AI42*产品成本!$F$4 -> 130.22 | AM42: =AG42*产品成本!$G$2+AH42*产品成本!$G$3+AI42*产品成本!$G$4 -> 1470.6 | AN42: =(E42-I42)*0.15 -> 1382.163 | AO42: =SUM(AJ42:AN42) -> 3970.733 | AP42: 10 | AQ42: 11 | AR42: 19 | AS42: =L42/(1-0.15+0.15*0.2) -> 818.47727 | AT42: =AP42*产品成本!$D$2+AQ42*产品成本!$D$3+AR42*产品成本!$D$4 -> 107.25352 | AU42: =AP42*产品成本!$E$2+AQ42*产品成本!$E$3+AR42*产品成本!$E$4 -> 7.846762 | AV42: =AP42*产品成本!$F$2+AQ42*产品成本!$F$3+AR42*产品成本!$F$4 -> 13.6 | AX42: =AS42*0.15 -> 122.77159 | AY42: =-AX42*0.2 -> -24.554318 | AZ42: =SUM(AT42:AY42) -> 226.91756 | BA42: =AO42-AZ42 -> 3743.8154 | BB42: =E42-I42 -> 9214.42 | BC42: =E42-AS42-I42 -> 8395.9427 | BD42: =BC42-BA42-Z42 -> 2322.1973 | BE42: =BD42/BC42 -> 0.27658565 | BG42: 上周黑5.5FT断货
A43: 0728~0803 | B43: 2025W31 | C43: 434 | D43: 403 | E43: 10601.18 | F43: 44 | G43: 43 | H43: 1076.26 | I43: 98.94 | J43: 40 | K43: =J43/C43 -> 0.092165899 | L43: 675.08 | M43: =(C43-C42)/C42 -> 0.13315927 | N43: =(D43-D42)/D42 -> 0.1010929 | O43: =(E43-E42)/E42 -> 0.13968267 | P43: =C43/D43 -> 1.0769231 | Q43: =E43/D43 -> 26.305658 | R43: =E43/C43 -> 24.426682 | S43: =C43/7 -> 62 | T43: =D43-Y43 -> 177 | U43: =T43/D43 -> 0.43920596 | V43: =Z43/(E43-I43) -> 0.24354138 | W43: 212393 | X43: 2508 | Y43: 226 | Z43: 2557.73 | AA43: 5663.04 | AB43: 1.02 | AC43: =Z43/AA43 -> 0.45165318 | AD43: =X43/W43 -> 0.011808299 | AE43: =Y43/X43 -> 0.090111643 | AF43: =Z43/Y43 -> 11.317389 | AG43: 95 | AH43: 196 | AI43: 141 | AJ43: =AG43*产品成本!$D$2+AH43*产品成本!$D$3+AI43*产品成本!$D$4 -> 1081.4789 | AK43: =AG43*产品成本!$E$2+AH43*产品成本!$E$3+AI43*产品成本!$E$4 -> 83.889537 | AL43: =AG43*产品成本!$F$2+AH43*产品成本!$F$3+AI43*产品成本!$F$4 -> 146.88 | AM43: =AG43*产品成本!$G$2+AH43*产品成本!$G$3+AI43*产品成本!$G$4 -> 1664.85 | AN43: =(E43-I43)*0.15 -> 1575.336 | AO43: =SUM(AJ43:AN43) -> 4552.4344 | AP43: 10 | AQ43: 15 | AR43: 15 | AS43: =L43/(1-0.15+0.15*0.2) -> 767.13636 | AT43: =AP43*产品成本!$D$2+AQ43*产品成本!$D$3+AR43*产品成本!$D$4 -> 102.46479 | AU43: =AP43*产品成本!$E$2+AQ43*产品成本!$E$3+AR43*产品成本!$E$4 -> 7.7779225 | AV43: =AP43*产品成本!$F$2+AQ43*产品成本!$F$3+AR43*产品成本!$F$4 -> 13.6 | AX43: =AS43*0.15 -> 115.07045 | AY43: =-AX43*0.2 -> -23.014091 | AZ43: =SUM(AT43:AY43) -> 215.89907 | BA43: =AO43-AZ43 -> 4336.5353 | BB43: =E43-I43 -> 10502.24 | BC43: =E43-AS43-I43 -> 9735.1036 | BD43: =BC43-BA43-Z43 -> 2840.8383 | BE43: =BD43/BC43 -> 0.29181387
A44: 0804~0810 | B44: 2025W32 | C44: 446 | D44: 414 | E44: 10895.07 | F44: 49 | G44: 48 | H44: 1221.31 | I44: 111.02 | J44: 34 | K44: =J44/C44 -> 0.076233184 | L44: 684.03 | M44: =(C44-C43)/C43 -> 0.02764977 | N44: =(D44-D43)/D43 -> 0.027295285 | O44: =(E44-E43)/E43 -> 0.027722386 | P44: =C44/D44 -> 1.0772947 | Q44: =E44/D44 -> 26.316594 | R44: =E44/C44 -> 24.428408 | S44: =C44/7 -> 63.714286 | T44: =D44-Y44 -> 142 | U44: =T44/D44 -> 0.34299517 | V44: =Z44/(E44-I44) -> 0.24896212 | W44: 224947 | X44: 2644 | Y44: 272 | Z44: 2684.82 | AA44: 7063.61 | AB44: 1.02 | AC44: =Z44/AA44 -> 0.38009177 | AD44: =X44/W44 -> 0.01175388 | AE44: =Y44/X44 -> 0.10287443 | AF44: =Z44/Y44 -> 9.8706618 | AG44: 87 | AH44: 151 | AI44: 183 | AJ44: =AG44*产品成本!$D$2+AH44*产品成本!$D$3+AI44*产品成本!$D$4 -> 1108.5211 | AK44: =AG44*产品成本!$E$2+AH44*产品成本!$E$3+AI44*产品成本!$E$4 -> 82.645124 | AL44: =AG44*产品成本!$F$2+AH44*产品成本!$F$3+AI44*产品成本!$F$4 -> 143.14 | AM44: =AG44*产品成本!$G$2+AH44*产品成本!$G$3+AI44*产品成本!$G$4 -> 1623.63 | AN44: =(E44-I44)*0.15 -> 1617.6075 | AO44: =SUM(AJ44:AN44) -> 4575.5438 | AP44: 7 | AQ44: 17 | AR44: 10 | AS44: =L44/(1-0.15+0.15*0.2) -> 777.30682 | AT44: =AP44*产品成本!$D$2+AQ44*产品成本!$D$3+AR44*产品成本!$D$4 -> 83.802817 | AU44: =AP44*产品成本!$E$2+AQ44*产品成本!$E$3+AR44*产品成本!$E$4 -> 6.5926817 | AV44: =AP44*产品成本!$F$2+AQ44*产品成本!$F$3+AR44*产品成本!$F$4 -> 11.56 | AX44: =AS44*0.15 -> 116.59602 | AY44: =-AX44*0.2 -> -23.319205 | AZ44: =SUM(AT44:AY44) -> 195.23232 | BA44: =AO44-AZ44 -> 4380.3114 | BB44: =E44-I44 -> 10784.05 | BC44: =E44-AS44-I44 -> 10006.743 | BD44: =BC44-BA44-Z44 -> 2941.6117 | BE44: =BD44/BC44 -> 0.29396295
A45: 0811~0817 | B45: 2025W33 | C45: 495 | D45: 453 | E45: 12053.79 | F45: 42 | G45: 41 | H45: 1030.48 | I45: 24.54 | J45: 35 | K45: =J45/C45 -> 0.070707071 | L45: 718.29 | M45: =(C45-C44)/C44 -> 0.10986547 | N45: =(D45-D44)/D44 -> 0.094202899 | O45: =(E45-E44)/E44 -> 0.10635269 | P45: =C45/D45 -> 1.0927152 | Q45: =E45/D45 -> 26.608808 | R45: =E45/C45 -> 24.351091 | S45: =C45/7 -> 70.714286 | T45: =D45-Y45 -> 160 | U45: =T45/D45 -> 0.35320088 | V45: =Z45/(E45-I45) -> 0.22464327 | W45: 237482 | X45: 2677 | Y45: 293 | Z45: 2702.29 | AA45: 7963.35 | AB45: 1.01 | AC45: =Z45/AA45 -> 0.33934086 | AD45: =X45/W45 -> 0.011272433 | AE45: =Y45/X45 -> 0.10945088 | AF45: =Z45/Y45 -> 9.2228328 | AG45: 120 | AH45: 199 | AI45: 176 | AJ45: =AG45*产品成本!$D$2+AH45*产品成本!$D$3+AI45*产品成本!$D$4 -> 1256.4789 | AK45: =AG45*产品成本!$E$2+AH45*产品成本!$E$3+AI45*产品成本!$E$4 -> 96.158083 | AL45: =AG45*产品成本!$F$2+AH45*产品成本!$F$3+AI45*产品成本!$F$4 -> 168.3 | AM45: =AG45*产品成本!$G$2+AH45*产品成本!$G$3+AI45*产品成本!$G$4 -> 1905.3 | AN45: =(E45-I45)*0.15 -> 1804.3875 | AO45: =SUM(AJ45:AN45) -> 5230.6245 | AP45: 11 | AQ45: 10 | AR45: 14 | AS45: =L45/(1-0.15+0.15*0.2) -> 816.23864 | AT45: =AP45*产品成本!$D$2+AQ45*产品成本!$D$3+AR45*产品成本!$D$4 -> 90.704225 | AU45: =AP45*产品成本!$E$2+AQ45*产品成本!$E$3+AR45*产品成本!$E$4 -> 6.7775789 | AV45: =AP45*产品成本!$F$2+AQ45*产品成本!$F$3+AR45*产品成本!$F$4 -> 11.9 | AX45: =AS45*0.15 -> 122.4358 | AY45: =-AX45*0.2 -> -24.487159 | AZ45: =SUM(AT45:AY45) -> 207.33044 | BA45: =AO45-AZ45 -> 5023.294 | BB45: =E45-I45 -> 12029.25 | BC45: =E45-AS45-I45 -> 11213.011 | BD45: =BC45-BA45-Z45 -> 3487.4273 | BE45: =BD45/BC45 -> 0.31101613
A46: 0818~0824 | B46: 2025W34 | C46: 534 | D46: 510 | E46: 13028.96 | F46: 34 | G46: 30 | H46: 835.96 | I46: 24.59 | J46: 37 | K46: =J46/C46 -> 0.06928839 | L46: 770.91 | M46: =(C46-C45)/C45 -> 0.078787879 | N46: =(D46-D45)/D45 -> 0.12582781 | O46: =(E46-E45)/E45 -> 0.080901526 | P46: =C46/D46 -> 1.0470588 | Q46: =E46/D46 -> 25.54698 | R46: =E46/C46 -> 24.398801 | S46: =C46/7 -> 76.285714 | T46: =D46-Y46 -> 206 | U46: =T46/D46 -> 0.40392157 | V46: =Z46/(E46-I46) -> 0.22342951 | W46: 259814 | X46: 3020 | Y46: 304 | Z46: 2905.56 | AA46: 7714.5 | AB46: 0.96 | AC46: =Z46/AA46 -> 0.3766362 | AD46: =X46/W46 -> 0.0116237 | AE46: =Y46/X46 -> 0.10066225 | AF46: =Z46/Y46 -> 9.5577632 | AG46: 136 | AH46: 183 | AI46: 215 | AJ46: =AG46*产品成本!$D$2+AH46*产品成本!$D$3+AI46*产品成本!$D$4 -> 1385.5634 | AK46: =AG46*产品成本!$E$2+AH46*产品成本!$E$3+AI46*产品成本!$E$4 -> 104.04115 | AL46: =AG46*产品成本!$F$2+AH46*产品成本!$F$3+AI46*产品成本!$F$4 -> 181.56 | AM46: =AG46*产品成本!$G$2+AH46*产品成本!$G$3+AI46*产品成本!$G$4 -> 2054.04 | AN46: =(E46-I46)*0.15 -> 1950.6555 | AO46: =SUM(AJ46:AN46) -> 5675.86 | AP46: 10 | AQ46: 10 | AR46: 17 | AS46: =L46/(1-0.15+0.15*0.2) -> 876.03409 | AT46: =AP46*产品成本!$D$2+AQ46*产品成本!$D$3+AR46*产品成本!$D$4 -> 98.521127 | AU46: =AP46*产品成本!$E$2+AQ46*产品成本!$E$3+AR46*产品成本!$E$4 -> 7.2339718 | AV46: =AP46*产品成本!$F$2+AQ46*产品成本!$F$3+AR46*产品成本!$F$4 -> 12.58 | AX46: =AS46*0.15 -> 131.40511 | AY46: =-AX46*0.2 -> -26.281023 | AZ46: =SUM(AT46:AY46) -> 223.45919 | BA46: =AO46-AZ46 -> 5452.4008 | BB46: =E46-I46 -> 13004.37 | BC46: =E46-AS46-I46 -> 12128.336 | BD46: =BC46-BA46-Z46 -> 3770.3751 | BE46: =BD46/BC46 -> 0.31087324
A47: 0825~0831 | B47: 2025W35 | C47: 450 | D47: 433 | E47: 10903.7 | F47: 58 | G47: 54 | H47: 1418.42 | I47: 120.8 | J47: 38 | K47: =J47/C47 -> 0.084444444 | L47: 821.92 | M47: =(C47-C46)/C46 -> -0.15730337 | N47: =(D47-D46)/D46 -> -0.15098039 | O47: =(E47-E46)/E46 -> -0.16311816 | P47: =C47/D47 -> 1.039261 | Q47: =E47/D47 -> 25.181755 | R47: =E47/C47 -> 24.230444 | S47: =C47/7 -> 64.285714 | T47: =D47-Y47 -> 189 | U47: =T47/D47 -> 0.43648961 | V47: =Z47/(E47-I47) -> 0.25213347 | W47: 229696 | X47: 2721 | Y47: 244 | Z47: 2718.73 | AA47: 6153.29 | AB47: 1 | AC47: =Z47/AA47 -> 0.44183356 | AD47: =X47/W47 -> 0.011846092 | AE47: =Y47/X47 -> 0.089672914 | AF47: =Z47/Y47 -> 11.142336 | AG47: 112 | AH47: 175 | AI47: 163 | AJ47: =AG47*产品成本!$D$2+AH47*产品成本!$D$3+AI47*产品成本!$D$4 -> 1145.8451 | AK47: =AG47*产品成本!$E$2+AH47*产品成本!$E$3+AI47*产品成本!$E$4 -> 87.412263 | AL47: =AG47*产品成本!$F$2+AH47*产品成本!$F$3+AI47*产品成本!$F$4 -> 153 | AM47: =AG47*产品成本!$G$2+AH47*产品成本!$G$3+AI47*产品成本!$G$4 -> 1731.48 | AN47: =(E47-I47)*0.15 -> 1617.435 | AO47: =SUM(AJ47:AN47) -> 4735.1723 | AP47: 3 | AQ47: 19 | AR47: 16 | AS47: =L47/(1-0.15+0.15*0.2) -> 934 | AT47: =AP47*产品成本!$D$2+AQ47*产品成本!$D$3+AR47*产品成本!$D$4 -> 99.43662 | AU47: =AP47*产品成本!$E$2+AQ47*产品成本!$E$3+AR47*产品成本!$E$4 -> 7.5438338 | AV47: =AP47*产品成本!$F$2+AQ47*产品成本!$F$3+AR47*产品成本!$F$4 -> 12.92 | AX47: =AS47*0.15 -> 140.1 | AY47: =-AX47*0.2 -> -28.02 | AZ47: =SUM(AT47:AY47) -> 231.98045 | BA47: =AO47-AZ47 -> 4503.1919 | BB47: =E47-I47 -> 10782.9 | BC47: =E47-AS47-I47 -> 9848.9 | BD47: =BC47-BA47-Z47 -> 2626.9781 | BE47: =BD47/BC47 -> 0.26672807
A48: 0901~0907 | B48: 2025W36 | C48: 445 | D48: 430 | E48: 10693.07 | F48: 26 | G48: 26 | H48: 626.64 | I48: 24.1 | J48: 36 | K48: =J48/C48 -> 0.080898876 | L48: 754.65 | M48: =(C48-C47)/C47 -> -0.011111111 | N48: =(D48-D47)/D47 -> -0.0069284065 | O48: =(E48-E47)/E47 -> -0.019317296 | P48: =C48/D48 -> 1.0348837 | Q48: =E48/D48 -> 24.867605 | R48: =E48/C48 -> 24.029371 | S48: =C48/7 -> 63.571429 | T48: =D48-Y48 -> 176 | U48: =T48/D48 -> 0.40930233 | V48: =Z48/(E48-I48) -> 0.25087989 | W48: 216007 | X48: 2646 | Y48: 254 | Z48: 2676.63 | AA48: 6219.58 | AB48: 1.01 | AC48: =Z48/AA48 -> 0.43035543 | AD48: =X48/W48 -> 0.012249603 | AE48: =Y48/X48 -> 0.095993953 | AF48: =Z48/Y48 -> 10.537913 | AG48: 108 | AH48: 173 | AI48: 164 | AJ48: =AG48*产品成本!$D$2+AH48*产品成本!$D$3+AI48*产品成本!$D$4 -> 1136.4789 | AK48: =AG48*产品成本!$E$2+AH48*产品成本!$E$3+AI48*产品成本!$E$4 -> 86.542255 | AL48: =AG48*产品成本!$F$2+AH48*产品成本!$F$3+AI48*产品成本!$F$4 -> 151.3 | AM48: =AG48*产品成本!$G$2+AH48*产品成本!$G$3+AI48*产品成本!$G$4 -> 1712.82 | AN48: =(E48-I48)*0.15 -> 1600.3455 | AO48: =SUM(AJ48:AN48) -> 4687.4866 | AP48: 12 | AQ48: 11 | AR48: 13 | AS48: =L48/(1-0.15+0.15*0.2) -> 857.55682 | AT48: =AP48*产品成本!$D$2+AQ48*产品成本!$D$3+AR48*产品成本!$D$4 -> 91.619718 | AU48: =AP48*产品成本!$E$2+AQ48*产品成本!$E$3+AR48*产品成本!$E$4 -> 6.9339761 | AV48: =AP48*产品成本!$F$2+AQ48*产品成本!$F$3+AR48*产品成本!$F$4 -> 12.24 | AX48: =AS48*0.15 -> 128.63352 | AY48: =-AX48*0.2 -> -25.726705 | AZ48: =SUM(AT48:AY48) -> 213.70051 | BA48: =AO48-AZ48 -> 4473.7861 | BB48: =E48-I48 -> 10668.97 | BC48: =E48-AS48-I48 -> 9811.4132 | BD48: =BC48-BA48-Z48 -> 2660.9971 | BE48: =BD48/BC48 -> 0.27121445
A49: 0908~0914 | B49: 2025W37 | C49: 483 | D49: 451 | E49: 11272.09 | F49: 57 | G49: 53 | H49: 1364.33 | I49: 23.94 | J49: 31 | K49: =J49/C49 -> 0.064182195 | L49: 668.4 | M49: =(C49-C48)/C48 -> 0.085393258 | N49: =(D49-D48)/D48 -> 0.048837209 | O49: =(E49-E48)/E48 -> 0.054149089 | P49: =C49/D49 -> 1.0709534 | Q49: =E49/D49 -> 24.993548 | R49: =E49/C49 -> 23.33766 | S49: =C49/7 -> 69 | T49: =D49-Y49 -> 178 | U49: =T49/D49 -> 0.39467849 | V49: =Z49/(E49-I49) -> 0.23735014 | W49: 219327 | X49: 2570 | Y49: 273 | Z49: 2669.75 | AA49: 6719.65 | AB49: 1.04 | AC49: =Z49/AA49 -> 0.39730492 | AD49: =X49/W49 -> 0.011717664 | AE49: =Y49/X49 -> 0.10622568 | AF49: =Z49/Y49 -> 9.779304 | AG49: 120 | AH49: 178 | AI49: 185 | AJ49: =AG49*产品成本!$D$2+AH49*产品成本!$D$3+AI49*产品成本!$D$4 -> 1241.9014 | AK49: =AG49*产品成本!$E$2+AH49*产品成本!$E$3+AI49*产品成本!$E$4 -> 93.99949 | AL49: =AG49*产品成本!$F$2+AH49*产品成本!$F$3+AI49*产品成本!$F$4 -> 164.22 | AM49: =AG49*产品成本!$G$2+AH49*产品成本!$G$3+AI49*产品成本!$G$4 -> 1858.5 | AN49: =(E49-I49)*0.15 -> 1687.2225 | AO49: =SUM(AJ49:AN49) -> 5045.8434 | AP49: 5 | AQ49: 11 | AR49: 15 | AS49: =L49/(1-0.15+0.15*0.2) -> 759.54545 | AT49: =AP49*产品成本!$D$2+AQ49*产品成本!$D$3+AR49*产品成本!$D$4 -> 83.450704 | AU49: =AP49*产品成本!$E$2+AQ49*产品成本!$E$3+AR49*产品成本!$E$4 -> 6.1387268 | AV49: =AP49*产品成本!$F$2+AQ49*产品成本!$F$3+AR49*产品成本!$F$4 -> 10.54 | AX49: =AS49*0.15 -> 113.93182 | AY49: =-AX49*0.2 -> -22.786364 | AZ49: =SUM(AT49:AY49) -> 191.27489 | BA49: =AO49-AZ49 -> 4854.5685 | BB49: =E49-I49 -> 11248.15 | BC49: =E49-AS49-I49 -> 10488.605 | BD49: =BC49-BA49-Z49 -> 2964.286 | BE49: =BD49/BC49 -> 0.28261968
A50: 0915~0921 | B50: 2025W38 | C50: 493 | D50: 465 | E50: 11222.27 | F50: 46 | G50: 40 | H50: 1046.94 | I50: 22.76 | J50: 36 | K50: =J50/C50 -> 0.073022312 | L50: 740.66 | M50: =(C50-C49)/C49 -> 0.020703934 | N50: =(D50-D49)/D49 -> 0.031042129 | O50: =(E50-E49)/E49 -> -0.004419766 | P50: =C50/D50 -> 1.0602151 | Q50: =E50/D50 -> 24.133914 | R50: =E50/C50 -> 22.763225 | S50: =C50/7 -> 70.428571 | T50: =D50-Y50 -> 187 | U50: =T50/D50 -> 0.40215054 | V50: =Z50/(E50-I50) -> 0.25394057 | W50: 231757 | X50: 2741 | Y50: 278 | Z50: 2844.01 | AA50: 6674.3 | AB50: 1.04 | AC50: =Z50/AA50 -> 0.4261136 | AD50: =X50/W50 -> 0.011827043 | AE50: =Y50/X50 -> 0.10142284 | AF50: =Z50/Y50 -> 10.230252 | AG50: 108 | AH50: 196 | AI50: 189 | AJ50: =AG50*产品成本!$D$2+AH50*产品成本!$D$3+AI50*产品成本!$D$4 -> 1267.8169 | AK50: =AG50*产品成本!$E$2+AH50*产品成本!$E$3+AI50*产品成本!$E$4 -> 96.226428 | AL50: =AG50*产品成本!$F$2+AH50*产品成本!$F$3+AI50*产品成本!$F$4 -> 167.62 | AM50: =AG50*产品成本!$G$2+AH50*产品成本!$G$3+AI50*产品成本!$G$4 -> 1900.02 | AN50: =(E50-I50)*0.15 -> 1679.9265 | AO50: =SUM(AJ50:AN50) -> 5111.6098 | AP50: 10 | AQ50: 11 | AR50: 15 | AS50: =L50/(1-0.15+0.15*0.2) -> 841.65909 | AT50: =AP50*产品成本!$D$2+AQ50*产品成本!$D$3+AR50*产品成本!$D$4 -> 94.014085 | AU50: =AP50*产品成本!$E$2+AQ50*产品成本!$E$3+AR50*产品成本!$E$4 -> 7.006762 | AV50: =AP50*产品成本!$F$2+AQ50*产品成本!$F$3+AR50*产品成本!$F$4 -> 12.24 | AX50: =AS50*0.15 -> 126.24886 | AY50: =-AX50*0.2 -> -25.249773 | AZ50: =SUM(AT50:AY50) -> 214.25994 | BA50: =AO50-AZ50 -> 4897.3499 | BB50: =E50-I50 -> 11199.51 | BC50: =E50-AS50-I50 -> 10357.851 | BD50: =BC50-BA50-Z50 -> 2616.491 | BE50: =BD50/BC50 -> 0.25260945 | BG50: 九折
A51: 0922~0928 | B51: 2025W39 | C51: 389 | D51: 372 | E51: 9211.49 | F51: 43 | G51: 37 | H51: 1010.09 | I51: 90.6 | J51: 39 | K51: =J51/C51 -> 0.10025707 | L51: 745.57 | M51: =(C51-C50)/C50 -> -0.21095335 | N51: =(D51-D50)/D50 -> -0.2 | O51: =(E51-E50)/E50 -> -0.17917765 | P51: =C51/D51 -> 1.0456989 | Q51: =E51/D51 -> 24.76207 | R51: =E51/C51 -> 23.679923 | S51: =C51/7 -> 55.571429 | T51: =D51-Y51 -> 156 | U51: =T51/D51 -> 0.41935484 | V51: =Z51/(E51-I51) -> 0.26663297 | W51: 205001 | X51: 2296 | Y51: 216 | Z51: 2431.93 | AA51: 5333.28 | AB51: 1.06 | AC51: =Z51/AA51 -> 0.45599143 | AD51: =X51/W51 -> 0.011199945 | AE51: =Y51/X51 -> 0.094076655 | AF51: =Z51/Y51 -> 11.258935 | AG51: 78 | AH51: 139 | AI51: 160 | AJ51: =AG51*产品成本!$D$2+AH51*产品成本!$D$3+AI51*产品成本!$D$4 -> 988.02817 | AK51: =AG51*产品成本!$E$2+AH51*产品成本!$E$3+AI51*产品成本!$E$4 -> 73.939179 | AL51: =AG51*产品成本!$F$2+AH51*产品成本!$F$3+AI51*产品成本!$F$4 -> 128.18 | AM51: =AG51*产品成本!$G$2+AH51*产品成本!$G$3+AI51*产品成本!$G$4 -> 1453.92 | AN51: =(E51-I51)*0.15 -> 1368.1335 | AO51: =SUM(AJ51:AN51) -> 4012.2008 | AP51: 11 | AQ51: 10 | AR51: 15 | AS51: =L51/(1-0.15+0.15*0.2) -> 847.23864 | AT51: =AP51*产品成本!$D$2+AQ51*产品成本!$D$3+AR51*产品成本!$D$4 -> 94.014085 | AU51: =AP51*产品成本!$E$2+AQ51*产品成本!$E$3+AR51*产品成本!$E$4 -> 6.9875789 | AV51: =AP51*产品成本!$F$2+AQ51*产品成本!$F$3+AR51*产品成本!$F$4 -> 12.24 | AX51: =AS51*0.15 -> 127.0858 | AY51: =-AX51*0.2 -> -25.417159 | AZ51: =SUM(AT51:AY51) -> 214.9103 | BA51: =AO51-AZ51 -> 3797.2905 | BB51: =E51-I51 -> 9120.89 | BC51: =E51-AS51-I51 -> 8273.6514 | BD51: =BC51-BA51-Z51 -> 2044.4308 | BE51: =BD51/BC51 -> 0.2471014
A52: 0929~1005 | B52: 2025W40 | C52: 488 | D52: 459 | E52: 10739.43 | F52: 73 | G52: 59 | H52: 1600.47 | I52: 149.07 | J52: 30 | K52: =J52/C52 -> 0.06147541 | L52: 606.91 | M52: =(C52-C51)/C51 -> 0.25449871 | N52: =(D52-D51)/D51 -> 0.23387097 | O52: =(E52-E51)/E51 -> 0.16587327 | P52: =C52/D52 -> 1.0631808 | Q52: =E52/D52 -> 23.397451 | R52: =E52/C52 -> 22.007029 | S52: =C52/7 -> 69.714286 | T52: =D52-Y52 -> 159 | U52: =T52/D52 -> 0.34640523 | V52: =Z52/(E52-I52) -> 0.2790094 | W52: 215670 | X52: 2743 | Y52: 300 | Z52: 2954.81 | AA52: 6866.78 | AB52: 1.08 | AC52: =Z52/AA52 -> 0.43030503 | AD52: =X52/W52 -> 0.012718505 | AE52: =Y52/X52 -> 0.1093693 | AF52: =Z52/Y52 -> 9.8493667 | AG52: 120 | AH52: 207 | AI52: 161 | AJ52: =AG52*产品成本!$D$2+AH52*产品成本!$D$3+AI52*产品成本!$D$4 -> 1223.7324 | AK52: =AG52*产品成本!$E$2+AH52*产品成本!$E$3+AI52*产品成本!$E$4 -> 94.550404 | AL52: =AG52*产品成本!$F$2+AH52*产品成本!$F$3+AI52*产品成本!$F$4 -> 165.92 | AM52: =AG52*产品成本!$G$2+AH52*产品成本!$G$3+AI52*产品成本!$G$4 -> 1878 | AN52: =(E52-I52)*0.15 -> 1588.554 | AO52: =SUM(AJ52:AN52) -> 4950.7568 | AP52: 8 | AQ52: 11 | AR52: 11 | AS52: =L52/(1-0.15+0.15*0.2) -> 689.67045 | AT52: =AP52*产品成本!$D$2+AQ52*产品成本!$D$3+AR52*产品成本!$D$4 -> 76.549296 | AU52: =AP52*产品成本!$E$2+AQ52*产品成本!$E$3+AR52*产品成本!$E$4 -> 5.8195479 | AV52: =AP52*产品成本!$F$2+AQ52*产品成本!$F$3+AR52*产品成本!$F$4 -> 10.2 | AX52: =AS52*0.15 -> 103.45057 | AY52: =-AX52*0.2 -> -20.690114 | AZ52: =SUM(AT52:AY52) -> 175.3293 | BA52: =AO52-AZ52 -> 4775.4275 | BB52: =E52-I52 -> 10590.36 | BC52: =E52-AS52-I52 -> 9900.6895 | BD52: =BC52-BA52-Z52 -> 2170.452 | BE52: =BD52/BC52 -> 0.21922231
A53: 1006~1012 | B53: 2025W41 | C53: 620 | D53: 584 | E53: 12681.75 | F53: 32 | G53: 21 | H53: 750.03 | I53: 55.44 | J53: 31 | K53: =J53/C53 -> 0.05 | L53: 592.98 | M53: =(C53-C52)/C52 -> 0.2704918 | N53: =(D53-D52)/D52 -> 0.27233115 | O53: =(E53-E52)/E52 -> 0.18085876 | P53: =C53/D53 -> 1.0616438 | Q53: =E53/D53 -> 21.715325 | R53: =E53/C53 -> 20.454435 | S53: =C53/7 -> 88.571429 | T53: =D53-Y53 -> 193 | U53: =T53/D53 -> 0.33047945 | V53: =Z53/(E53-I53) -> 0.25549666 | W53: 245287 | X53: 2996 | Y53: 391 | Z53: 3225.98 | AA53: 8335.08 | AB53: 1.08 | AC53: =Z53/AA53 -> 0.38703648 | AD53: =X53/W53 -> 0.012214263 | AE53: =Y53/X53 -> 0.13050734 | AF53: =Z53/Y53 -> 8.2505882 | AG53: 155 | AH53: 221 | AI53: 244 | AJ53: =AG53*产品成本!$D$2+AH53*产品成本!$D$3+AI53*产品成本!$D$4 -> 1601.9718 | AK53: =AG53*产品成本!$E$2+AH53*产品成本!$E$3+AI53*产品成本!$E$4 -> 120.75571 | AL53: =AG53*产品成本!$F$2+AH53*产品成本!$F$3+AI53*产品成本!$F$4 -> 210.8 | AM53: =AG53*产品成本!$G$2+AH53*产品成本!$G$3+AI53*产品成本!$G$4 -> 2385.45 | AN53: =(E53-I53)*0.15 -> 1893.9465 | AO53: =SUM(AJ53:AN53) -> 6212.924 | AP53: 10 | AQ53: 9 | AR53: 12 | AS53: =L53/(1-0.15+0.15*0.2) -> 673.84091 | AT53: =AP53*产品成本!$D$2+AQ53*产品成本!$D$3+AR53*产品成本!$D$4 -> 79.859155 | AU53: =AP53*产品成本!$E$2+AQ53*产品成本!$E$3+AR53*产品成本!$E$4 -> 5.9911817 | AV53: =AP53*产品成本!$F$2+AQ53*产品成本!$F$3+AR53*产品成本!$F$4 -> 10.54 | AX53: =AS53*0.15 -> 101.07614 | AY53: =-AX53*0.2 -> -20.215227 | AZ53: =SUM(AT53:AY53) -> 177.25125 | BA53: =AO53-AZ53 -> 6035.6728 | BB53: =E53-I53 -> 12626.31 | BC53: =E53-AS53-I53 -> 11952.469 | BD53: =BC53-BA53-Z53 -> 2690.8163 | BE53: =BD53/BC53 -> 0.2251264 | BG53: 1007~1008 PD秋促
A54: 1013~1019 | B54: 2025W42 | C54: 436 | D54: 415 | E54: 9798.42 | F54: 54 | G54: 47 | H54: 1197.41 | I54: 108.15 | J54: 56 | K54: =J54/C54 -> 0.12844037 | L54: 906.05 | M54: =(C54-C53)/C53 -> -0.29677419 | N54: =(D54-D53)/D53 -> -0.28938356 | O54: =(E54-E53)/E53 -> -0.22736058 | P54: =C54/D54 -> 1.0506024 | Q54: =E54/D54 -> 23.610651 | R54: =E54/C54 -> 22.47344 | S54: =C54/7 -> 62.285714 | T54: =D54-Y54 -> 146 | U54: =T54/D54 -> 0.35180723 | V54: =Z54/(E54-I54) -> 0.24867831 | W54: 221059 | X54: 2304 | Y54: 269 | Z54: 2409.76 | AA54: 6239.78 | AB54: 1.05 | AC54: =Z54/AA54 -> 0.3861931 | AD54: =X54/W54 -> 0.010422557 | AE54: =Y54/X54 -> 0.11675347 | AF54: =Z54/Y54 -> 8.9582156 | AG54: 130 | AH54: 145 | AI54: 161 | AJ54: =AG54*产品成本!$D$2+AH54*产品成本!$D$3+AI54*产品成本!$D$4 -> 1113.8732 | AK54: =AG54*产品成本!$E$2+AH54*产品成本!$E$3+AI54*产品成本!$E$4 -> 84.333486 | AL54: =AG54*产品成本!$F$2+AH54*产品成本!$F$3+AI54*产品成本!$F$4 -> 148.24 | AM54: =AG54*产品成本!$G$2+AH54*产品成本!$G$3+AI54*产品成本!$G$4 -> 1673.1 | AN54: =(E54-I54)*0.15 -> 1453.5405 | AO54: =SUM(AJ54:AN54) -> 4473.0872 | AP54: 16 | AQ54: 17 | AR54: 23 | AS54: =L54/(1-0.15+0.15*0.2) -> 1029.6023 | AT54: =AP54*产品成本!$D$2+AQ54*产品成本!$D$3+AR54*产品成本!$D$4 -> 145.84507 | AU54: =AP54*产品成本!$E$2+AQ54*产品成本!$E$3+AR54*产品成本!$E$4 -> 10.885145 | AV54: =AP54*产品成本!$F$2+AQ54*产品成本!$F$3+AR54*产品成本!$F$4 -> 19.04 | AX54: =AS54*0.15 -> 154.44034 | AY54: =-AX54*0.2 -> -30.888068 | AZ54: =SUM(AT54:AY54) -> 299.32249 | BA54: =AO54-AZ54 -> 4173.7647 | BB54: =E54-I54 -> 9690.27 | BC54: =E54-AS54-I54 -> 8660.6677 | BD54: =BC54-BA54-Z54 -> 2077.143 | BE54: =BD54/BC54 -> 0.23983636
A55: 1020~1026 | B55: 2025W43 | C55: 424 | D55: 408 | E55: 9547.58 | F55: 35 | G55: 33 | H55: 804.25 | I55: 78.54 | J55: 30 | K55: =J55/C55 -> 0.070754717 | L55: 583.25 | M55: =(C55-C54)/C54 -> -0.027522936 | N55: =(D55-D54)/D54 -> -0.01686747 | O55: =(E55-E54)/E54 -> -0.025600046 | P55: =C55/D55 -> 1.0392157 | Q55: =E55/D55 -> 23.400931 | R55: =E55/C55 -> 22.517877 | S55: =C55/7 -> 60.571429 | T55: =D55-Y55 -> 159 | U55: =T55/D55 -> 0.38970588 | V55: =Z55/(E55-I55) -> 0.26102963 | W55: 224559 | X55: 2317 | Y55: 249 | Z55: 2471.7 | AA55: 5757.73 | AB55: 1.07 | AC55: =Z55/AA55 -> 0.42928376 | AD55: =X55/W55 -> 0.010318001 | AE55: =Y55/X55 -> 0.10746655 | AF55: =Z55/Y55 -> 9.926506 | AG55: 107 | AH55: 150 | AI55: 155 | AJ55: =AG55*产品成本!$D$2+AH55*产品成本!$D$3+AI55*产品成本!$D$4 -> 1055.9859 | AK55: =AG55*产品成本!$E$2+AH55*产品成本!$E$3+AI55*产品成本!$E$4 -> 80.044475 | AL55: =AG55*产品成本!$F$2+AH55*产品成本!$F$3+AI55*产品成本!$F$4 -> 140.08 | AM55: =AG55*产品成本!$G$2+AH55*产品成本!$G$3+AI55*产品成本!$G$4 -> 1584.33 | AN55: =(E55-I55)*0.15 -> 1420.356 | AO55: =SUM(AJ55:AN55) -> 4280.7964 | AP55: 8 | AQ55: 9 | AR55: 13 | AS55: =L55/(1-0.15+0.15*0.2) -> 662.78409 | AT55: =AP55*产品成本!$D$2+AQ55*产品成本!$D$3+AR55*产品成本!$D$4 -> 78.943662 | AU55: =AP55*产品成本!$E$2+AQ55*产品成本!$E$3+AR55*产品成本!$E$4 -> 5.8539676 | AV55: =AP55*产品成本!$F$2+AQ55*产品成本!$F$3+AR55*产品成本!$F$4 -> 10.2 | AX55: =AS55*0.15 -> 99.417614 | AY55: =-AX55*0.2 -> -19.883523 | AZ55: =SUM(AT55:AY55) -> 174.53172 | BA55: =AO55-AZ55 -> 4106.2647 | BB55: =E55-I55 -> 9469.04 | BC55: =E55-AS55-I55 -> 8806.2559 | BD55: =BC55-BA55-Z55 -> 2228.2912 | BE55: =BD55/BC55 -> 0.25303503
A56: 1027~1102 | B56: 2025W44 | C56: 469 | D56: 450 | E56: 10255.03 | F56: 63 | G56: 59 | H56: 1388.87 | I56: 134.71 | J56: 39 | K56: =J56/C56 -> 0.08315565 | L56: 750.42 | M56: =(C56-C55)/C55 -> 0.10613208 | N56: =(D56-D55)/D55 -> 0.10294118 | O56: =(E56-E55)/E55 -> 0.074097311 | P56: =C56/D56 -> 1.0422222 | Q56: =E56/D56 -> 22.788956 | R56: =E56/C56 -> 21.865736 | S56: =C56/7 -> 67 | T56: =D56-Y56 -> 185 | U56: =T56/D56 -> 0.41111111 | V56: =Z56/(E56-I56) -> 0.24850202 | W56: 211588 | X56: 2321 | Y56: 265 | Z56: 2514.92 | AA56: 5934.57 | AB56: 1.08 | AC56: =Z56/AA56 -> 0.4237746 | AD56: =X56/W56 -> 0.010969431 | AE56: =Y56/X56 -> 0.11417492 | AF56: =Z56/Y56 -> 9.4902642 | AG56: 140 | AH56: 146 | AI56: 183 | AJ56: =AG56*产品成本!$D$2+AH56*产品成本!$D$3+AI56*产品成本!$D$4 -> 1209.9296 | AK56: =AG56*产品成本!$E$2+AH56*产品成本!$E$3+AI56*产品成本!$E$4 -> 90.882346 | AL56: =AG56*产品成本!$F$2+AH56*产品成本!$F$3+AI56*产品成本!$F$4 -> 159.46 | AM56: =AG56*产品成本!$G$2+AH56*产品成本!$G$3+AI56*产品成本!$G$4 -> 1799.7 | AN56: =(E56-I56)*0.15 -> 1518.048 | AO56: =SUM(AJ56:AN56) -> 4778.0199 | AP56: 11 | AQ56: 13 | AR56: 15 | AS56: =L56/(1-0.15+0.15*0.2) -> 852.75 | AT56: =AP56*产品成本!$D$2+AQ56*产品成本!$D$3+AR56*产品成本!$D$4 -> 100.35211 | AU56: =AP56*产品成本!$E$2+AQ56*产品成本!$E$3+AR56*产品成本!$E$4 -> 7.5659493 | AV56: =AP56*产品成本!$F$2+AQ56*产品成本!$F$3+AR56*产品成本!$F$4 -> 13.26 | AX56: =AS56*0.15 -> 127.9125 | AY56: =-AX56*0.2 -> -25.5825 | AZ56: =SUM(AT56:AY56) -> 223.50806 | BA56: =AO56-AZ56 -> 4554.5119 | BB56: =E56-I56 -> 10120.32 | BC56: =E56-AS56-I56 -> 9267.57 | BD56: =BC56-BA56-Z56 -> 2198.1381 | BE56: =BD56/BC56 -> 0.23718603 | BG56: 30号万圣节
A57: 1103~1109 | B57: 2025W45 | C57: 427 | D57: 397 | E57: 9395.43 | F57: 63 | G57: 44 | H57: 1363.57 | I57: 137.14 | J57: 41 | K57: =J57/C57 -> 0.096018735 | L57: 781.55 | M57: =(C57-C56)/C56 -> -0.089552239 | N57: =(D57-D56)/D56 -> -0.11777778 | O57: =(E57-E56)/E56 -> -0.08382228 | P57: =C57/D57 -> 1.0755668 | Q57: =E57/D57 -> 23.666071 | R57: =E57/C57 -> 22.003349 | S57: =C57/7 -> 61 | T57: =D57-Y57 -> 92 | U57: =T57/D57 -> 0.23173804 | V57: =Z57/(E57-I57) -> 0.32092427 | W57: 247317 | X57: 2759 | Y57: 305 | Z57: 2971.21 | AA57: 6972.09 | AB57: 1.08 | AC57: =Z57/AA57 -> 0.42615772 | AD57: =X57/W57 -> 0.011155723 | AE57: =Y57/X57 -> 0.1105473 | AF57: =Z57/Y57 -> 9.7416721 | AG57: 117 | AH57: 107 | AI57: 203 | AJ57: =AG57*产品成本!$D$2+AH57*产品成本!$D$3+AI57*产品成本!$D$4 -> 1145.1408 | AK57: =AG57*产品成本!$E$2+AH57*产品成本!$E$3+AI57*产品成本!$E$4 -> 83.570569 | AL57: =AG57*产品成本!$F$2+AH57*产品成本!$F$3+AI57*产品成本!$F$4 -> 145.18 | AM57: =AG57*产品成本!$G$2+AH57*产品成本!$G$3+AI57*产品成本!$G$4 -> 1640.73 | AN57: =(E57-I57)*0.15 -> 1388.7435 | AO57: =SUM(AJ57:AN57) -> 4403.3649 | AP57: 11 | AQ57: 14 | AR57: 16 | AS57: =L57/(1-0.15+0.15*0.2) -> 888.125 | AT57: =AP57*产品成本!$D$2+AQ57*产品成本!$D$3+AR57*产品成本!$D$4 -> 105.77465 | AU57: =AP57*产品成本!$E$2+AQ57*产品成本!$E$3+AR57*产品成本!$E$4 -> 7.9687394 | AV57: =AP57*产品成本!$F$2+AQ57*产品成本!$F$3+AR57*产品成本!$F$4 -> 13.94 | AX57: =AS57*0.15 -> 133.21875 | AY57: =-AX57*0.2 -> -26.64375 | AZ57: =SUM(AT57:AY57) -> 234.25839 | BA57: =AO57-AZ57 -> 4169.1065 | BB57: =E57-I57 -> 9258.29 | BC57: =E57-AS57-I57 -> 8370.165 | BD57: =BC57-BA57-Z57 -> 1229.8485 | BE57: =BD57/BC57 -> 0.1469324 | BG57: 断货 黑色一天
A58: 1110~1116 | B58: 2025W46 | C58: 446 | D58: 427 | E58: 9900.95 | F58: 54 | G58: 47 | H58: 1202.06 | I58: 107.8 | J58: 35 | K58: =J58/C58 -> 0.078475336 | L58: 672.99 | M58: =(C58-C57)/C57 -> 0.044496487 | N58: =(D58-D57)/D57 -> 0.075566751 | O58: =(E58-E57)/E57 -> 0.053804882 | P58: =C58/D58 -> 1.0444965 | Q58: =E58/D58 -> 23.187237 | R58: =E58/C58 -> 22.199439 | S58: =C58/7 -> 63.714286 | T58: =D58-Y58 -> 158 | U58: =T58/D58 -> 0.37002342 | V58: =Z58/(E58-I58) -> 0.27954948 | W58: 199927 | X58: 2528 | Y58: 269 | Z58: 2737.67 | AA58: 6107.72 | AB58: 1.08 | AC58: =Z58/AA58 -> 0.44823109 | AD58: =X58/W58 -> 0.012644615 | AE58: =Y58/X58 -> 0.10640823 | AF58: =Z58/Y58 -> 10.177212 | AG58: 103 | AH58: 115 | AI58: 228 | AJ58: =AG58*产品成本!$D$2+AH58*产品成本!$D$3+AI58*产品成本!$D$4 -> 1215.2113 | AK58: =AG58*产品成本!$E$2+AH58*产品成本!$E$3+AI58*产品成本!$E$4 -> 87.932392 | AL58: =AG58*产品成本!$F$2+AH58*产品成本!$F$3+AI58*产品成本!$F$4 -> 151.64 | AM58: =AG58*产品成本!$G$2+AH58*产品成本!$G$3+AI58*产品成本!$G$4 -> 1717.77 | AN58: =(E58-I58)*0.15 -> 1468.9725 | AO58: =SUM(AJ58:AN58) -> 4641.5262 | AP58: 11 | AQ58: 12 | AR58: 12 | AS58: =L58/(1-0.15+0.15*0.2) -> 764.76136 | AT58: =AP58*产品成本!$D$2+AQ58*产品成本!$D$3+AR58*产品成本!$D$4 -> 88.309859 | AU58: =AP58*产品成本!$E$2+AQ58*产品成本!$E$3+AR58*产品成本!$E$4 -> 6.7431592 | AV58: =AP58*产品成本!$F$2+AQ58*产品成本!$F$3+AR58*产品成本!$F$4 -> 11.9 | AX58: =AS58*0.15 -> 114.7142 | AY58: =-AX58*0.2 -> -22.942841 | AZ58: =SUM(AT58:AY58) -> 198.72438 | BA58: =AO58-AZ58 -> 4442.8018 | BB58: =E58-I58 -> 9793.15 | BC58: =E58-AS58-I58 -> 9028.3886 | BD58: =BC58-BA58-Z58 -> 1847.9169 | BE58: =BD58/BC58 -> 0.20467848
A59: 1117~1123 | B59: 2025W47 | C59: 513 | D59: 470 | E59: 9750.77 | F59: 86 | G59: 63 | H59: 1649.66 | I59: 170.13 | J59: 33 | K59: =J59/C59 -> 0.064327485 | L59: 620.88 | M59: =(C59-C58)/C58 -> 0.15022422 | N59: =(D59-D58)/D58 -> 0.10070258 | O59: =(E59-E58)/E58 -> -0.015168241 | P59: =C59/D59 -> 1.0914894 | Q59: =E59/D59 -> 20.746319 | R59: =E59/C59 -> 19.007349 | S59: =C59/7 -> 73.285714 | T59: =D59-Y59 -> 182 | U59: =T59/D59 -> 0.38723404 | V59: =Z59/(E59-I59) -> 0.28510621 | W59: 204331 | X59: 2582 | Y59: 288 | Z59: 2731.5 | AA59: 6068.95 | AB59: 1.06 | AC59: =Z59/AA59 -> 0.45007786 | AD59: =X59/W59 -> 0.01263636 | AE59: =Y59/X59 -> 0.11154144 | AF59: =Z59/Y59 -> 9.484375 | AG59: 131 | AH59: 171 | AI59: 211 | AJ59: =AG59*产品成本!$D$2+AH59*产品成本!$D$3+AI59*产品成本!$D$4 -> 1336.4085 | AK59: =AG59*产品成本!$E$2+AH59*产品成本!$E$3+AI59*产品成本!$E$4 -> 100.01964 | AL59: =AG59*产品成本!$F$2+AH59*产品成本!$F$3+AI59*产品成本!$F$4 -> 174.42 | AM59: =AG59*产品成本!$G$2+AH59*产品成本!$G$3+AI59*产品成本!$G$4 -> 1973.19 | AN59: =(E59-I59)*0.15 -> 1437.096 | AO59: =SUM(AJ59:AN59) -> 5021.1341 | AP59: 11 | AQ59: 5 | AR59: 17 | AS59: =L59/(1-0.15+0.15*0.2) -> 705.54545 | AT59: =AP59*产品成本!$D$2+AQ59*产品成本!$D$3+AR59*产品成本!$D$4 -> 90.070423 | AU59: =AP59*产品成本!$E$2+AQ59*产品成本!$E$3+AR59*产品成本!$E$4 -> 6.4436282 | AV59: =AP59*产品成本!$F$2+AQ59*产品成本!$F$3+AR59*产品成本!$F$4 -> 11.22 | AX59: =AS59*0.15 -> 105.83182 | AY59: =-AX59*0.2 -> -21.166364 | AZ59: =SUM(AT59:AY59) -> 192.39951 | BA59: =AO59-AZ59 -> 4828.7346 | BB59: =E59-I59 -> 9580.64 | BC59: =E59-AS59-I59 -> 8875.0945 | BD59: =BC59-BA59-Z59 -> 1314.86 | BE59: =BD59/BC59 -> 0.14815166 | BG59: 断货 (周二粉色3.6/绿色5.0/绿色5.5/粉色5.5)，1120开始8天
A60: 1124~1130 | B60: 2025W48 | C60: 657 | D60: 602 | E60: 11504.01 | F60: 112 | G60: 86 | H60: 1976.52 | I60: 167.86 | J60: 23 | K60: =J60/C60 -> 0.03500761 | L60: 422.16 | M60: =(C60-C59)/C59 -> 0.28070175 | N60: =(D60-D59)/D59 -> 0.28085106 | O60: =(E60-E59)/E59 -> 0.17980529 | P60: =C60/D60 -> 1.0913621 | Q60: =E60/D60 -> 19.109651 | R60: =E60/C60 -> 17.509909 | S60: =C60/7 -> 93.857143 | T60: =D60-Y60 -> 252 | U60: =T60/D60 -> 0.41860465 | V60: =Z60/(E60-I60) -> 0.25151484 | W60: 282183 | X60: 2800 | Y60: 350 | Z60: 2851.21 | AA60: 6592.86 | AB60: 1.02 | AC60: =Z60/AA60 -> 0.43246937 | AD60: =X60/W60 -> 0.0099226389 | AE60: =Y60/X60 -> 0.125 | AF60: =Z60/Y60 -> 8.1463143 | AG60: 204 | AH60: 201 | AI60: 252 | AJ60: =AG60*产品成本!$D$2+AH60*产品成本!$D$3+AI60*产品成本!$D$4 -> 1689.7183 | AK60: =AG60*产品成本!$E$2+AH60*产品成本!$E$3+AI60*产品成本!$E$4 -> 127.08665 | AL60: =AG60*产品成本!$F$2+AH60*产品成本!$F$3+AI60*产品成本!$F$4 -> 223.38 | AM60: =AG60*产品成本!$G$2+AH60*产品成本!$G$3+AI60*产品成本!$G$4 -> 2519.46 | AN60: =(E60-I60)*0.15 -> 1700.4225 | AO60: =SUM(AJ60:AN60) -> 6260.0675 | AP60: 7 | AQ60: 5 | AR60: 11 | AS60: =L60/(1-0.15+0.15*0.2) -> 479.72727 | AT60: =AP60*产品成本!$D$2+AQ60*产品成本!$D$3+AR60*产品成本!$D$4 -> 61.760563 | AU60: =AP60*产品成本!$E$2+AQ60*产品成本!$E$3+AR60*产品成本!$E$4 -> 4.4892 | AV60: =AP60*产品成本!$F$2+AQ60*产品成本!$F$3+AR60*产品成本!$F$4 -> 7.82 | AX60: =AS60*0.15 -> 71.959091 | AY60: =-AX60*0.2 -> -14.391818 | AZ60: =SUM(AT60:AY60) -> 131.63704 | BA60: =AO60-AZ60 -> 6128.4304 | BB60: =E60-I60 -> 11336.15 | BC60: =E60-AS60-I60 -> 10856.423 | BD60: =BC60-BA60-Z60 -> 1876.7823 | BE60: =BD60/BC60 -> 0.17287299 | BG60: 黑五（周五周六周日，28 29 30）
A61: 1201~1207 | B61: 2025W49 | C61: 465 | D61: 434 | E61: 9735.19 | F61: 43 | G61: 32 | H61: 940.85 | I61: 119.3 | J61: 31 | K61: =J61/C61 -> 0.066666667 | L61: 508.78 | M61: =(C61-C60)/C60 -> -0.29223744 | N61: =(D61-D60)/D60 -> -0.27906977 | O61: =(E61-E60)/E60 -> -0.15375682 | P61: =C61/D61 -> 1.0714286 | Q61: =E61/D61 -> 22.431313 | R61: =E61/C61 -> 20.935892 | S61: =C61/7 -> 66.428571 | T61: =D61-Y61 -> 176 | U61: =T61/D61 -> 0.40552995 | V61: =Z61/(E61-I61) -> 0.23691827 | W61: 256847 | X61: 2300 | Y61: 258 | Z61: 2278.18 | AA61: 5682.17 | AB61: 0.99 | AC61: =Z61/AA61 -> 0.40093485 | AD61: =X61/W61 -> 0.0089547474 | AE61: =Y61/X61 -> 0.11217391 | AF61: =Z61/Y61 -> 8.830155 | AG61: 120 | AH61: 166 | AI61: 179 | AJ61: =AG61*产品成本!$D$2+AH61*产品成本!$D$3+AI61*产品成本!$D$4 -> 1196.6901 | AK61: =AG61*产品成本!$E$2+AH61*产品成本!$E$3+AI61*产品成本!$E$4 -> 90.426008 | AL61: =AG61*产品成本!$F$2+AH61*产品成本!$F$3+AI61*产品成本!$F$4 -> 158.1 | AM61: =AG61*产品成本!$G$2+AH61*产品成本!$G$3+AI61*产品成本!$G$4 -> 1788.3 | AN61: =(E61-I61)*0.15 -> 1442.3835 | AO61: =SUM(AJ61:AN61) -> 4675.8996 | AP61: 13 | AQ61: 7 | AR61: 11 | AS61: =L61/(1-0.15+0.15*0.2) -> 578.15909 | AT61: =AP61*产品成本!$D$2+AQ61*产品成本!$D$3+AR61*产品成本!$D$4 -> 78.661972 | AU61: =AP61*产品成本!$E$2+AQ61*产品成本!$E$3+AR61*产品成本!$E$4 -> 5.9164225 | AV61: =AP61*产品成本!$F$2+AQ61*产品成本!$F$3+AR61*产品成本!$F$4 -> 10.54 | AX61: =AS61*0.15 -> 86.723864 | AY61: =-AX61*0.2 -> -17.344773 | AZ61: =SUM(AT61:AY61) -> 164.49749 | BA61: =AO61-AZ61 -> 4511.4022 | BB61: =E61-I61 -> 9615.89 | BC61: =E61-AS61-I61 -> 9037.7309 | BD61: =BC61-BA61-Z61 -> 2248.1487 | BE61: =BD61/BC61 -> 0.24875146 | BG61: 网络星期一 1201; 之后保持九折
A62: 1208~1214 | B62: 2025W50 | C62: 424 | D62: 407 | E62: 9207.37 | F62: 181 | G62: 168 | H62: 3981.19 | I62: 226.22 | J62: 29 | K62: =J62/C62 -> 0.068396226 | L62: 512.41 | M62: =(C62-C61)/C61 -> -0.088172043 | N62: =(D62-D61)/D61 -> -0.062211982 | O62: =(E62-E61)/E61 -> -0.05421774 | P62: =C62/D62 -> 1.041769 | Q62: =E62/D62 -> 22.622531 | R62: =E62/C62 -> 21.715495 | S62: =C62/7 -> 60.571429 | T62: =D62-Y62 -> 183 | U62: =T62/D62 -> 0.44963145 | V62: =Z62/(E62-I62) -> 0.23408472 | W62: 220903 | X62: 2078 | Y62: 224 | Z62: 2102.35 | AA62: 5024.18 | AB62: 1.01 | AC62: =Z62/AA62 -> 0.41844639 | AD62: =X62/W62 -> 0.0094068437 | AE62: =Y62/X62 -> 0.10779596 | AF62: =Z62/Y62 -> 9.3854911 | AG62: 118 | AH62: 139 | AI62: 167 | AJ62: =AG62*产品成本!$D$2+AH62*产品成本!$D$3+AI62*产品成本!$D$4 -> 1095.7042 | AK62: =AG62*产品成本!$E$2+AH62*产品成本!$E$3+AI62*产品成本!$E$4 -> 82.353461 | AL62: =AG62*产品成本!$F$2+AH62*产品成本!$F$3+AI62*产品成本!$F$4 -> 144.16 | AM62: =AG62*产品成本!$G$2+AH62*产品成本!$G$3+AI62*产品成本!$G$4 -> 1628.82 | AN62: =(E62-I62)*0.15 -> 1347.1725 | AO62: =SUM(AJ62:AN62) -> 4298.2102 | AP62: 7 | AQ62: 10 | AR62: 12 | AS62: =L62/(1-0.15+0.15*0.2) -> 582.28409 | AT62: =AP62*产品成本!$D$2+AQ62*产品成本!$D$3+AR62*产品成本!$D$4 -> 75.633803 | AU62: =AP62*产品成本!$E$2+AQ62*产品成本!$E$3+AR62*产品成本!$E$4 -> 5.6631507 | AV62: =AP62*产品成本!$F$2+AQ62*产品成本!$F$3+AR62*产品成本!$F$4 -> 9.86 | AX62: =AS62*0.15 -> 87.342614 | AY62: =-AX62*0.2 -> -17.468523 | AZ62: =SUM(AT62:AY62) -> 161.03104 | BA62: =AO62-AZ62 -> 4137.1791 | BB62: =E62-I62 -> 8981.15 | BC62: =E62-AS62-I62 -> 8398.8659 | BD62: =BC62-BA62-Z62 -> 2159.3368 | BE62: =BD62/BC62 -> 0.25709861
A63: 1215~1221 | B63: 2025W51 | C63: 436 | D63: 423 | E63: 9711.06 | F63: 228 | G63: 219 | H63: 5094.12 | I63: 260.04 | J63: 26 | K63: =J63/C63 -> 0.059633028 | L63: 512.4 | M63: =(C63-C62)/C62 -> 0.028301887 | N63: =(D63-D62)/D62 -> 0.039312039 | O63: =(E63-E62)/E62 -> 0.05470509 | P63: =C63/D63 -> 1.0307329 | Q63: =E63/D63 -> 22.957589 | R63: =E63/C63 -> 22.273073 | S63: =C63/7 -> 62.285714 | T63: =D63-Y63 -> 192 | U63: =T63/D63 -> 0.45390071 | V63: =Z63/(E63-I63) -> 0.20859336 | W63: 216381 | X63: 1885 | Y63: 231 | Z63: 1971.42 | AA63: 5377.07 | AB63: 1.05 | AC63: =Z63/AA63 -> 0.36663462 | AD63: =X63/W63 -> 0.0087114858 | AE63: =Y63/X63 -> 0.12254642 | AF63: =Z63/Y63 -> 8.5342857 | AG63: 105 | AH63: 183 | AI63: 148 | AJ63: =AG63*产品成本!$D$2+AH63*产品成本!$D$3+AI63*产品成本!$D$4 -> 1098.3099 | AK63: =AG63*产品成本!$E$2+AH63*产品成本!$E$3+AI63*产品成本!$E$4 -> 84.589335 | AL63: =AG63*产品成本!$F$2+AH63*产品成本!$F$3+AI63*产品成本!$F$4 -> 148.24 | AM63: =AG63*产品成本!$G$2+AH63*产品成本!$G$3+AI63*产品成本!$G$4 -> 1678.35 | AN63: =(E63-I63)*0.15 -> 1417.653 | AO63: =SUM(AJ63:AN63) -> 4427.1422 | AP63: 7 | AQ63: 10 | AR63: 9 | AS63: =L63/(1-0.15+0.15*0.2) -> 582.27273 | AT63: =AP63*产品成本!$D$2+AQ63*产品成本!$D$3+AR63*产品成本!$D$4 -> 65.704225 | AU63: =AP63*产品成本!$E$2+AQ63*产品成本!$E$3+AR63*产品成本!$E$4 -> 5.0331507 | AV63: =AP63*产品成本!$F$2+AQ63*产品成本!$F$3+AR63*产品成本!$F$4 -> 8.84 | AX63: =AS63*0.15 -> 87.340909 | AY63: =-AX63*0.2 -> -17.468182 | AZ63: =SUM(AT63:AY63) -> 149.4501 | BA63: =AO63-AZ63 -> 4277.6921 | BB63: =E63-I63 -> 9451.02 | BC63: =E63-AS63-I63 -> 8868.7473 | BD63: =BC63-BA63-Z63 -> 2619.6352 | BE63: =BD63/BC63 -> 0.29537826
A64: 1222~1228 | B64: 2025W52 | C64: 323 | D64: 303 | E64: 7223.97 | F64: 102 | G64: 93 | H64: 2283.88 | I64: 139.89 | J64: 19 | K64: =J64/C64 -> 0.058823529 | L64: 350.68 | M64: =(C64-C63)/C63 -> -0.25917431 | N64: =(D64-D63)/D63 -> -0.28368794 | O64: =(E64-E63)/E63 -> -0.25610901 | P64: =C64/D64 -> 1.0660066 | Q64: =E64/D64 -> 23.841485 | R64: =E64/C64 -> 22.365232 | S64: =C64/7 -> 46.142857 | T64: =D64-Y64 -> 143 | U64: =T64/D64 -> 0.47194719 | V64: =Z64/(E64-I64) -> 0.23570457 | W64: 180451 | X64: 1670 | Y64: 160 | Z64: 1669.75 | AA64: 3746.85 | AB64: 1 | AC64: =Z64/AA64 -> 0.44564101 | AD64: =X64/W64 -> 0.0092545899 | AE64: =Y64/X64 -> 0.095808383 | AF64: =Z64/Y64 -> 10.435937 | AG64: 89 | AH64: 102 | AI64: 132 | AJ64: =AG64*产品成本!$D$2+AH64*产品成本!$D$3+AI64*产品成本!$D$4 -> 840.42254 | AK64: =AG64*产品成本!$E$2+AH64*产品成本!$E$3+AI64*产品成本!$E$4 -> 62.835621 | AL64: =AG64*产品成本!$F$2+AH64*产品成本!$F$3+AI64*产品成本!$F$4 -> 109.82 | AM64: =AG64*产品成本!$G$2+AH64*产品成本!$G$3+AI64*产品成本!$G$4 -> 1241.01 | AN64: =(E64-I64)*0.15 -> 1062.612 | AO64: =SUM(AJ64:AN64) -> 3316.7002 | AP64: 4 | AQ64: 4 | AR64: 11 | AS64: =L64/(1-0.15+0.15*0.2) -> 398.5 | AT64: =AP64*产品成本!$D$2+AQ64*产品成本!$D$3+AR64*产品成本!$D$4 -> 53.309859 | AU64: =AP64*产品成本!$E$2+AQ64*产品成本!$E$3+AR64*产品成本!$E$4 -> 3.7755887 | AV64: =AP64*产品成本!$F$2+AQ64*产品成本!$F$3+AR64*产品成本!$F$4 -> 6.46 | AX64: =AS64*0.15 -> 59.775 | AY64: =-AX64*0.2 -> -11.955 | AZ64: =SUM(AT64:AY64) -> 111.36545 | BA64: =AO64-AZ64 -> 3205.3347 | BB64: =E64-I64 -> 7084.08 | BC64: =E64-AS64-I64 -> 6685.58 | BD64: =BC64-BA64-Z64 -> 1810.4953 | BE64: =BD64/BC64 -> 0.27080602 | BG64: 平安夜 圣诞节
A65: 1229~0104 | B65: 2026W01 | C65: 434 | D65: 393 | E65: 10244.5 | F65: 114 | G65: 94 | H65: 2600.36 | I65: 161.25 | J65: 29 | K65: =J65/C65 -> 0.066820276 | L65: 477.59 | M65: =(C65-C64)/C64 -> 0.34365325 | N65: =(D65-D64)/D64 -> 0.2970297 | O65: =(E65-E64)/E64 -> 0.41812604 | P65: =C65/D65 -> 1.1043257 | Q65: =E65/D65 -> 26.06743 | R65: =E65/C65 -> 23.604839 | S65: =C65/7 -> 62 | T65: =D65-Y65 -> 165 | U65: =T65/D65 -> 0.41984733 | V65: =Z65/(E65-I65) -> 0.20220365 | W65: 229389 | X65: 2108 | Y65: 228 | Z65: 2038.87 | AA65: 5774.96 | AB65: 0.97 | AC65: =Z65/AA65 -> 0.35305353 | AD65: =X65/W65 -> 0.0091896298 | AE65: =Y65/X65 -> 0.10815939 | AF65: =Z65/Y65 -> 8.9424123 | AG65: 123 | AH65: 112 | AI65: 199 | AJ65: =AG65*产品成本!$D$2+AH65*产品成本!$D$3+AI65*产品成本!$D$4 -> 1155.1408 | AK65: =AG65*产品成本!$E$2+AH65*产品成本!$E$3+AI65*产品成本!$E$4 -> 84.736162 | AL65: =AG65*产品成本!$F$2+AH65*产品成本!$F$3+AI65*产品成本!$F$4 -> 147.56 | AM65: =AG65*产品成本!$G$2+AH65*产品成本!$G$3+AI65*产品成本!$G$4 -> 1666.77 | AN65: =(E65-I65)*0.15 -> 1512.4875 | AO65: =SUM(AJ65:AN65) -> 4566.6945 | AP65: 8 | AQ65: 11 | AR65: 10 | AS65: =L65/(1-0.15+0.15*0.2) -> 542.71591 | AT65: =AP65*产品成本!$D$2+AQ65*产品成本!$D$3+AR65*产品成本!$D$4 -> 73.239437 | AU65: =AP65*产品成本!$E$2+AQ65*产品成本!$E$3+AR65*产品成本!$E$4 -> 5.6095479 | AV65: =AP65*产品成本!$F$2+AQ65*产品成本!$F$3+AR65*产品成本!$F$4 -> 9.86 | AX65: =AS65*0.15 -> 81.407386 | AY65: =-AX65*0.2 -> -16.281477 | AZ65: =SUM(AT65:AY65) -> 153.83489 | BA65: =AO65-AZ65 -> 4412.8596 | BB65: =E65-I65 -> 10083.25 | BC65: =E65-AS65-I65 -> 9540.5341 | BD65: =BC65-BA65-Z65 -> 3088.8045 | BE65: =BD65/BC65 -> 0.32375593 | BG65: 原价
A66: 0105~0111 | B66: 2026W02 | C66: 444 | D66: 417 | E66: 10786.89 | F66: 58 | G66: 47 | H66: 1403.82 | I66: 152.15 | J66: 39 | K66: =J66/C66 -> 0.087837838 | L66: 764.9 | M66: =(C66-C65)/C65 -> 0.023041475 | N66: =(D66-D65)/D65 -> 0.061068702 | O66: =(E66-E65)/E65 -> 0.052944507 | P66: =C66/D66 -> 1.0647482 | Q66: =E66/D66 -> 25.867842 | R66: =E66/C66 -> 24.294797 | S66: =C66/7 -> 63.428571 | T66: =D66-Y66 -> 164 | U66: =T66/D66 -> 0.39328537 | V66: =Z66/(E66-I66) -> 0.21657229 | W66: 215591 | X66: 2375 | Y66: 253 | Z66: 2303.19 | AA66: 6318.58 | AB66: 0.97 | AC66: =Z66/AA66 -> 0.3645107 | AD66: =X66/W66 -> 0.01101623 | AE66: =Y66/X66 -> 0.10652632 | AF66: =Z66/Y66 -> 9.1035178 | AG66: 135 | AH66: 108 | AI66: 201 | AJ66: =AG66*产品成本!$D$2+AH66*产品成本!$D$3+AI66*产品成本!$D$4 -> 1178.662 | AK66: =AG66*产品成本!$E$2+AH66*产品成本!$E$3+AI66*产品成本!$E$4 -> 86.468286 | AL66: =AG66*产品成本!$F$2+AH66*产品成本!$F$3+AI66*产品成本!$F$4 -> 150.96 | AM66: =AG66*产品成本!$G$2+AH66*产品成本!$G$3+AI66*产品成本!$G$4 -> 1703.25 | AN66: =(E66-I66)*0.15 -> 1595.211 | AO66: =SUM(AJ66:AN66) -> 4714.5513 | AP66: 14 | AQ66: 8 | AR66: 17 | AS66: =L66/(1-0.15+0.15*0.2) -> 869.20455 | AT66: =AP66*产品成本!$D$2+AQ66*产品成本!$D$3+AR66*产品成本!$D$4 -> 102.74648 | AU66: =AP66*产品成本!$E$2+AQ66*产品成本!$E$3+AR66*产品成本!$E$4 -> 7.5428197 | AV66: =AP66*产品成本!$F$2+AQ66*产品成本!$F$3+AR66*产品成本!$F$4 -> 13.26 | AX66: =AS66*0.15 -> 130.38068 | AY66: =-AX66*0.2 -> -26.076136 | AZ66: =SUM(AT66:AY66) -> 227.85384 | BA66: =AO66-AZ66 -> 4486.6974 | BB66: =E66-I66 -> 10634.74 | BC66: =E66-AS66-I66 -> 9765.5355 | BD66: =BC66-BA66-Z66 -> 2975.648 | BE66: =BD66/BC66 -> 0.30470915 | BG66: 原价
A67: 0112~0118 | B67: 2026W03 | C67: 429 | D67: 419 | E67: 10511.13 | F67: 51 | G67: 48 | H67: 1261.59 | I67: 138.23 | J67: 43 | K67: =J67/C67 -> 0.1002331 | L67: 860.16 | M67: =(C67-C66)/C66 -> -0.033783784 | N67: =(D67-D66)/D66 -> 0.0047961631 | O67: =(E67-E66)/E66 -> -0.025564366 | P67: =C67/D67 -> 1.0238663 | Q67: =E67/D67 -> 25.086229 | R67: =E67/C67 -> 24.501469 | S67: =C67/7 -> 61.285714 | T67: =D67-Y67 -> 142 | U67: =T67/D67 -> 0.33890215 | V67: =Z67/(E67-I67) -> 0.2076401 | W67: 185443 | X67: 2245 | Y67: 277 | Z67: 2153.83 | AA67: 6835.68 | AB67: 0.96 | AC67: =Z67/AA67 -> 0.31508643 | AD67: =X67/W67 -> 0.012106146 | AE67: =Y67/X67 -> 0.1233853 | AF67: =Z67/Y67 -> 7.7755596 | AG67: 111 | AH67: 113 | AI67: 205 | AJ67: =AG67*产品成本!$D$2+AH67*产品成本!$D$3+AI67*产品成本!$D$4 -> 1151.7606 | AK67: =AG67*产品成本!$E$2+AH67*产品成本!$E$3+AI67*产品成本!$E$4 -> 84.105668 | AL67: =AG67*产品成本!$F$2+AH67*产品成本!$F$3+AI67*产品成本!$F$4 -> 145.86 | AM67: =AG67*产品成本!$G$2+AH67*产品成本!$G$3+AI67*产品成本!$G$4 -> 1649.79 | AN67: =(E67-I67)*0.15 -> 1555.935 | AO67: =SUM(AJ67:AN67) -> 4587.4512 | AP67: 15 | AQ67: 5 | AR67: 23 | AS67: =L67/(1-0.15+0.15*0.2) -> 977.45455 | AT67: =AP67*产品成本!$D$2+AQ67*产品成本!$D$3+AR67*产品成本!$D$4 -> 118.38028 | AU67: =AP67*产品成本!$E$2+AQ67*产品成本!$E$3+AR67*产品成本!$E$4 -> 8.3980563 | AV67: =AP67*产品成本!$F$2+AQ67*产品成本!$F$3+AR67*产品成本!$F$4 -> 14.62 | AX67: =AS67*0.15 -> 146.61818 | AY67: =-AX67*0.2 -> -29.323636 | AZ67: =SUM(AT67:AY67) -> 258.69288 | BA67: =AO67-AZ67 -> 4328.7583 | BB67: =E67-I67 -> 10372.9 | BC67: =E67-AS67-I67 -> 9395.4455 | BD67: =BC67-BA67-Z67 -> 2912.8571 | BE67: =BD67/BC67 -> 0.31002863 | BG67: 原价
A68: 0119~0125 | B68: 2026W04 | C68: 401 | D68: 371 | E68: 8847.55 | F68: 33 | G68: 31 | H68: 742.44 | I68: 87.77 | J68: 43 | K68: =J68/C68 -> 0.10723192 | L68: 854.28 | M68: =(C68-C67)/C67 -> -0.065268065 | N68: =(D68-D67)/D67 -> -0.11455847 | O68: =(E68-E67)/E67 -> -0.15826843 | P68: =C68/D68 -> 1.0808625 | Q68: =E68/D68 -> 23.847844 | R68: =E68/C68 -> 22.063716 | S68: =C68/7 -> 57.285714 | T68: =D68-Y68 -> 161 | U68: =T68/D68 -> 0.43396226 | V68: =Z68/(E68-I68) -> 0.22967358 | W68: 281209 | X68: 2093 | Y68: 210 | Z68: 2011.89 | AA68: 5176.69 | AB68: 0.96 | AC68: =Z68/AA68 -> 0.38864409 | AD68: =X68/W68 -> 0.0074428628 | AE68: =Y68/X68 -> 0.10033445 | AF68: =Z68/Y68 -> 9.5804286 | AG68: 88 | AH68: 118 | AI68: 195 | AJ68: =AG68*产品成本!$D$2+AH68*产品成本!$D$3+AI68*产品成本!$D$4 -> 1080.6338 | AK68: =AG68*产品成本!$E$2+AH68*产品成本!$E$3+AI68*产品成本!$E$4 -> 78.976656 | AL68: =AG68*产品成本!$F$2+AH68*产品成本!$F$3+AI68*产品成本!$F$4 -> 136.34 | AM68: =AG68*产品成本!$G$2+AH68*产品成本!$G$3+AI68*产品成本!$G$4 -> 1545.42 | AN68: =(E68-I68)*0.15 -> 1313.967 | AO68: =SUM(AJ68:AN68) -> 4155.3375 | AP68: 15 | AQ68: 10 | AR68: 18 | AS68: =L68/(1-0.15+0.15*0.2) -> 970.77273 | AT68: =AP68*产品成本!$D$2+AQ68*产品成本!$D$3+AR68*产品成本!$D$4 -> 112.39437 | AU68: =AP68*产品成本!$E$2+AQ68*产品成本!$E$3+AR68*产品成本!$E$4 -> 8.312007 | AV68: =AP68*产品成本!$F$2+AQ68*产品成本!$F$3+AR68*产品成本!$F$4 -> 14.62 | AX68: =AS68*0.15 -> 145.61591 | AY68: =-AX68*0.2 -> -29.123182 | AZ68: =SUM(AT68:AY68) -> 251.8191 | BA68: =AO68-AZ68 -> 3903.5184 | BB68: =E68-I68 -> 8759.78 | BC68: =E68-AS68-I68 -> 7789.0073 | BD68: =BC68-BA68-Z68 -> 1873.5989 | BE68: =BD68/BC68 -> 0.24054399 | BF68: 5338,31 | BG68: 1-21开始Z划算，整体15%off；美国大雪1月23开始持续，一半的州受到影响，整体流量严重下滑
A69: 0126~0201 | B69: 2026W05 | C69: 524 | D69: 498 | E69: 11077.72 | F69: 54 | G69: 41 | H69: 1165.01 | I69: 96.42 | J69: 33 | K69: =J69/C69 -> 0.062977099 | L69: 645.56 | M69: =(C69-C68)/C68 -> 0.30673317 | N69: =(D69-D68)/D68 -> 0.34231806 | O69: =(E69-E68)/E68 -> 0.25206639 | P69: =C69/D69 -> 1.0522088 | Q69: =E69/D69 -> 22.244418 | R69: =E69/C69 -> 21.140687 | S69: =C69/7 -> 74.857143 | T69: =D69-Y69 -> 198 | U69: =T69/D69 -> 0.39759036 | V69: =Z69/(E69-I69) -> 0.20394853 | W69: 320616 | X69: 2314 | Y69: 300 | Z69: 2239.62 | AA69: 6515.16 | AB69: 0.97 | AC69: =Z69/AA69 -> 0.34375518 | AD69: =X69/W69 -> 0.0072173566 | AE69: =Y69/X69 -> 0.12964564 | AF69: =Z69/Y69 -> 7.4654 | AG69: 148 | AH69: 136 | AI69: 240 | AJ69: =AG69*产品成本!$D$2+AH69*产品成本!$D$3+AI69*产品成本!$D$4 -> 1394.3662 | AK69: =AG69*产品成本!$E$2+AH69*产品成本!$E$3+AI69*产品成本!$E$4 -> 102.3133 | AL69: =AG69*产品成本!$F$2+AH69*产品成本!$F$3+AI69*产品成本!$F$4 -> 178.16 | AM69: =AG69*产品成本!$G$2+AH69*产品成本!$G$3+AI69*产品成本!$G$4 -> 2012.52 | AN69: =(E69-I69)*0.15 -> 1647.195 | AO69: =SUM(AJ69:AN69) -> 5334.5545 | AP69: 7 | AQ69: 8 | AR69: 18 | AS69: =L69/(1-0.15+0.15*0.2) -> 733.59091 | AT69: =AP69*产品成本!$D$2+AQ69*产品成本!$D$3+AR69*产品成本!$D$4 -> 91.267606 | AU69: =AP69*产品成本!$E$2+AQ69*产品成本!$E$3+AR69*产品成本!$E$4 -> 6.5375704 | AV69: =AP69*产品成本!$F$2+AQ69*产品成本!$F$3+AR69*产品成本!$F$4 -> 11.22 | AX69: =AS69*0.15 -> 110.03864 | AY69: =-AX69*0.2 -> -22.007727 | AZ69: =SUM(AT69:AY69) -> 197.05609 | BA69: =AO69-AZ69 -> 5137.4984 | BB69: =E69-I69 -> 10981.3 | BC69: =E69-AS69-I69 -> 10247.709 | BD69: =BC69-BA69-Z69 -> 2870.5907 | BE69: =BD69/BC69 -> 0.28012023 | BF69: 4790,24 | BG69: 1-21开始Z划算，整体15%off,2-3结束；
A70: 0202~0208 | B70: 2026W06 | C70: 486 | D70: 450 | E70: 10769.75 | F70: 50 | G70: 30 | H70: 1102.63 | I70: 119.81 | J70: 34 | K70: =J70/C70 -> 0.069958848 | L70: 647.63 | M70: =(C70-C69)/C69 -> -0.072519084 | N70: =(D70-D69)/D69 -> -0.096385542 | O70: =(E70-E69)/E69 -> -0.027800847 | P70: =C70/D70 -> 1.08 | Q70: =E70/D70 -> 23.932778 | R70: =E70/C70 -> 22.159979 | S70: =C70/7 -> 69.428571 | T70: =D70-Y70 -> 189 | U70: =T70/D70 -> 0.42 | V70: =Z70/(E70-I70) -> 0.22871396 | W70: 224056 | X70: 2432 | Y70: 261 | Z70: 2435.79 | AA70: 6049.84 | AB70: 1 | AC70: =Z70/AA70 -> 0.40262057 | AD70: =X70/W70 -> 0.010854429 | AE70: =Y70/X70 -> 0.10731908 | AF70: =Z70/Y70 -> 9.3325287 | AG70: 110 | AH70: 141 | AI70: 235 | AJ70: =AG70*产品成本!$D$2+AH70*产品成本!$D$3+AI70*产品成本!$D$4 -> 1308.0986 | AK70: =AG70*产品成本!$E$2+AH70*产品成本!$E$3+AI70*产品成本!$E$4 -> 95.630185 | AL70: =AG70*产品成本!$F$2+AH70*产品成本!$F$3+AI70*产品成本!$F$4 -> 165.24 | AM70: =AG70*产品成本!$G$2+AH70*产品成本!$G$3+AI70*产品成本!$G$4 -> 1872.3 | AN70: =(E70-I70)*0.15 -> 1597.491 | AO70: =SUM(AJ70:AN70) -> 5038.7598 | AP70: 8 | AQ70: 15 | AR70: 11 | AS70: =L70/(1-0.15+0.15*0.2) -> 735.94318 | AT70: =AP70*产品成本!$D$2+AQ70*产品成本!$D$3+AR70*产品成本!$D$4 -> 85 | AU70: =AP70*产品成本!$E$2+AQ70*产品成本!$E$3+AR70*产品成本!$E$4 -> 6.5907085 | AV70: =AP70*产品成本!$F$2+AQ70*产品成本!$F$3+AR70*产品成本!$F$4 -> 11.56 | AX70: =AS70*0.15 -> 110.39148 | AY70: =-AX70*0.2 -> -22.078295 | AZ70: =SUM(AT70:AY70) -> 191.46389 | BA70: =AO70-AZ70 -> 4847.2959 | BB70: =E70-I70 -> 10649.94 | BC70: =E70-AS70-I70 -> 9913.9968 | BD70: =BC70-BA70-Z70 -> 2630.9109 | BE70: =BD70/BC70 -> 0.26537339 | BF70: 5120,37 | BG70: 19.79/22.39/23.29,0206-0228,整体10%off 划线价
A71: 0209~0215 | B71: 2026W07 | C71: 495 | D71: 481 | E71: 10972.88 | F71: 54 | G71: 48 | H71: 1187.26 | I71: 139.54 | J71: 43 | K71: =J71/C71 -> 0.086868687 | L71: 835.32 | M71: =(C71-C70)/C70 -> 0.018518519 | N71: =(D71-D70)/D70 -> 0.068888889 | O71: =(E71-E70)/E70 -> 0.018861162 | P71: =C71/D71 -> 1.029106 | Q71: =E71/D71 -> 22.81264 | R71: =E71/C71 -> 22.167434 | S71: =C71/7 -> 70.714286 | T71: =D71-Y71 -> 148 | U71: =T71/D71 -> 0.30769231 | V71: =Z71/(E71-I71) -> 0.23087063 | W71: 192638 | X71: 2449 | Y71: 333 | Z71: 2501.1 | AA71: 7556.87 | AB71: 1.02 | AC71: =Z71/AA71 -> 0.33097036 | AD71: =X71/W71 -> 0.012712964 | AE71: =Y71/X71 -> 0.13597387 | AF71: =Z71/Y71 -> 7.5108108 | AG71: 101 | AH71: 148 | AI71: 246 | AJ71: =AG71*产品成本!$D$2+AH71*产品成本!$D$3+AI71*产品成本!$D$4 -> 1340.2817 | AK71: =AG71*产品成本!$E$2+AH71*产品成本!$E$3+AI71*产品成本!$E$4 -> 97.727252 | AL71: =AG71*产品成本!$F$2+AH71*产品成本!$F$3+AI71*产品成本!$F$4 -> 168.3 | AM71: =AG71*产品成本!$G$2+AH71*产品成本!$G$3+AI71*产品成本!$G$4 -> 1909.29 | AN71: =(E71-I71)*0.15 -> 1625.001 | AO71: =SUM(AJ71:AN71) -> 5140.5999 | AP71: 9 | AQ71: 14 | AR71: 20 | AS71: =L71/(1-0.15+0.15*0.2) -> 949.22727 | AT71: =AP71*产品成本!$D$2+AQ71*产品成本!$D$3+AR71*产品成本!$D$4 -> 114.78873 | AU71: =AP71*产品成本!$E$2+AQ71*产品成本!$E$3+AR71*产品成本!$E$4 -> 8.4615254 | AV71: =AP71*产品成本!$F$2+AQ71*产品成本!$F$3+AR71*产品成本!$F$4 -> 14.62 | AX71: =AS71*0.15 -> 142.38409 | AY71: =-AX71*0.2 -> -28.476818 | AZ71: =SUM(AT71:AY71) -> 251.77753 | BA71: =AO71-AZ71 -> 4888.8224 | BB71: =E71-I71 -> 10833.34 | BC71: =E71-AS71-I71 -> 9884.1127 | BD71: =BC71-BA71-Z71 -> 2494.1903 | BE71: =BD71/BC71 -> 0.25234337 | BF71: 4203,30 | BG71: 19.79/22.39/23.29,0206-0228,整体10%off 划线价
A72: 0216~0222 | B72: 2026W08 | C72: 580 | D72: 546 | E72: 12876 | F72: 65 | G72: 50 | H72: 1445.95 | I72: 138.16 | J72: 37 | K72: =J72/C72 -> 0.063793103 | L72: 708.67 | M72: =(C72-C71)/C71 -> 0.17171717 | N72: =(D72-D71)/D71 -> 0.13513514 | O72: =(E72-E71)/E71 -> 0.17343851 | P72: =C72/D72 -> 1.0622711 | Q72: =E72/D72 -> 23.582418 | R72: =E72/C72 -> 22.2 | S72: =C72/7 -> 82.857143 | T72: =D72-Y72 -> 204 | U72: =T72/D72 -> 0.37362637 | V72: =Z72/(E72-I72) -> 0.23482631 | W72: 222786 | X72: 2899 | Y72: 342 | Z72: 2991.18 | AA72: 7818.94 | AB72: 1.03 | AC72: =Z72/AA72 -> 0.38255569 | AD72: =X72/W72 -> 0.013012487 | AE72: =Y72/X72 -> 0.11797171 | AF72: =Z72/Y72 -> 8.7461404 | AG72: 140 | AH72: 158 | AI72: 282 | AJ72: =AG72*产品成本!$D$2+AH72*产品成本!$D$3+AI72*产品成本!$D$4 -> 1562.9577 | AK72: =AG72*产品成本!$E$2+AH72*产品成本!$E$3+AI72*产品成本!$E$4 -> 113.98583 | AL72: =AG72*产品成本!$F$2+AH72*产品成本!$F$3+AI72*产品成本!$F$4 -> 197.2 | AM72: =AG72*产品成本!$G$2+AH72*产品成本!$G$3+AI72*产品成本!$G$4 -> 2232.6 | AN72: =(E72-I72)*0.15 -> 1910.676 | AO72: =SUM(AJ72:AN72) -> 6017.4196 | AP72: 8 | AQ72: 13 | AR72: 16 | AS72: =L72/(1-0.15+0.15*0.2) -> 805.30682 | AT72: =AP72*产品成本!$D$2+AQ72*产品成本!$D$3+AR72*产品成本!$D$4 -> 97.323944 | AU72: =AP72*产品成本!$E$2+AQ72*产品成本!$E$3+AR72*产品成本!$E$4 -> 7.2551282 | AV72: =AP72*产品成本!$F$2+AQ72*产品成本!$F$3+AR72*产品成本!$F$4 -> 12.58 | AX72: =AS72*0.15 -> 120.79602 | AY72: =-AX72*0.2 -> -24.159205 | AZ72: =SUM(AT72:AY72) -> 213.79589 | BA72: =AO72-AZ72 -> 5803.6237 | BB72: =E72-I72 -> 12737.84 | BC72: =E72-AS72-I72 -> 11932.533 | BD72: =BC72-BA72-Z72 -> 3137.7295 | BE72: =BD72/BC72 -> 0.26295586 | BF72: 4557,36 | BG72: 19.79/22.39/23.29,0206-0228,整体10%off 划线价
A73: 0223~0301 | B73: 2026W09 | C73: 596 | D73: 558 | E73: 13082.03 | F73: 90 | G73: 71 | H73: 1977.05 | I73: 183.86 | J73: 43 | K73: =J73/C73 -> 0.072147651 | L73: 832.44 | M73: =(C73-C72)/C72 -> 0.027586207 | N73: =(D73-D72)/D72 -> 0.021978022 | O73: =(E73-E72)/E72 -> 0.016001087 | P73: =C73/D73 -> 1.0681004 | Q73: =E73/D73 -> 23.444498 | R73: =E73/C73 -> 21.949715 | S73: =C73/7 -> 85.142857 | T73: =D73-Y73 -> 220 | U73: =T73/D73 -> 0.39426523 | V73: =Z73/(E73-I73) -> 0.19628831 | W73: 211323 | X73: 2479 | Y73: 338 | Z73: 2531.76 | AA73: 7647 | AB73: 1.02 | AC73: =Z73/AA73 -> 0.33107885 | AD73: =X73/W73 -> 0.011730858 | AE73: =Y73/X73 -> 0.1363453 | AF73: =Z73/Y73 -> 7.4904142 | AG73: 157 | AH73: 176 | AI73: 263 | AJ73: =AG73*产品成本!$D$2+AH73*产品成本!$D$3+AI73*产品成本!$D$4 -> 1574.0141 | AK73: =AG73*产品成本!$E$2+AH73*产品成本!$E$3+AI73*产品成本!$E$4 -> 116.41737 | AL73: =AG73*产品成本!$F$2+AH73*产品成本!$F$3+AI73*产品成本!$F$4 -> 202.64 | AM73: =AG73*产品成本!$G$2+AH73*产品成本!$G$3+AI73*产品成本!$G$4 -> 2291.43 | AN73: =(E73-I73)*0.15 -> 1934.7255 | AO73: =SUM(AJ73:AN73) -> 6119.227 | AP73: 8 | AQ73: 15 | AR73: 20 | AS73: =L73/(1-0.15+0.15*0.2) -> 945.95455 | AT73: =AP73*产品成本!$D$2+AQ73*产品成本!$D$3+AR73*产品成本!$D$4 -> 114.78873 | AU73: =AP73*产品成本!$E$2+AQ73*产品成本!$E$3+AR73*产品成本!$E$4 -> 8.4807085 | AV73: =AP73*产品成本!$F$2+AQ73*产品成本!$F$3+AR73*产品成本!$F$4 -> 14.62 | AX73: =AS73*0.15 -> 141.89318 | AY73: =-AX73*0.2 -> -28.378636 | AZ73: =SUM(AT73:AY73) -> 251.40399 | BA73: =AO73-AZ73 -> 5867.823 | BB73: =E73-I73 -> 12898.17 | BC73: =E73-AS73-I73 -> 11952.215 | BD73: =BC73-BA73-Z73 -> 3552.6325 | BE73: =BD73/BC73 -> 0.29723632 | BF73: 4679,37 | BG73: 19.79/22.39/23.29,0301-0331,整体10%off 划线价 0227~0305 评论拆分 3天影响
A74: 0302~0308 | B74: 2026W10 | C74: 489 | D74: 463 | E74: 10803.14 | F74: 54 | G74: 44 | H74: 1212.76 | I74: 146.83 | J74: 42 | K74: =J74/C74 -> 0.085889571 | L74: 812.8 | M74: =(C74-C73)/C73 -> -0.1795302 | N74: =(D74-D73)/D73 -> -0.1702509 | O74: =(E74-E73)/E73 -> -0.17420003 | P74: =C74/D74 -> 1.0561555 | Q74: =E74/D74 -> 23.332916 | R74: =E74/C74 -> 22.092311 | S74: =C74/7 -> 69.857143 | T74: =D74-Y74 -> 179 | U74: =T74/D74 -> 0.38660907 | V74: =Z74/(E74-I74) -> 0.22458149 | W74: 191264 | X74: 2364 | Y74: 284 | Z74: 2393.21 | AA74: 6412.56 | AB74: 1.01 | AC74: =Z74/AA74 -> 0.37320664 | AD74: =X74/W74 -> 0.01235988 | AE74: =Y74/X74 -> 0.12013536 | AF74: =Z74/Y74 -> 8.4267958 | AG74: 107 | AH74: 158 | AI74: 224 | AJ74: =AG74*产品成本!$D$2+AH74*产品成本!$D$3+AI74*产品成本!$D$4 -> 1301.2676 | AK74: =AG74*产品成本!$E$2+AH74*产品成本!$E$3+AI74*产品成本!$E$4 -> 96.076796 | AL74: =AG74*产品成本!$F$2+AH74*产品成本!$F$3+AI74*产品成本!$F$4 -> 166.26 | AM74: =AG74*产品成本!$G$2+AH74*产品成本!$G$3+AI74*产品成本!$G$4 -> 1884.63 | AN74: =(E74-I74)*0.15 -> 1598.4465 | AO74: =SUM(AJ74:AN74) -> 5046.6809 | AP74: 8 | AQ74: 13 | AR74: 21 | AS74: =L74/(1-0.15+0.15*0.2) -> 923.63636 | AT74: =AP74*产品成本!$D$2+AQ74*产品成本!$D$3+AR74*产品成本!$D$4 -> 113.87324 | AU74: =AP74*产品成本!$E$2+AQ74*产品成本!$E$3+AR74*产品成本!$E$4 -> 8.3051282 | AV74: =AP74*产品成本!$F$2+AQ74*产品成本!$F$3+AR74*产品成本!$F$4 -> 14.28 | AX74: =AS74*0.15 -> 138.54545 | AY74: =-AX74*0.2 -> -27.709091 | AZ74: =SUM(AT74:AY74) -> 247.29473 | BA74: =AO74-AZ74 -> 4799.3862 | BB74: =E74-I74 -> 10656.31 | BC74: =E74-AS74-I74 -> 9732.6736 | BD74: =BC74-BA74-Z74 -> 2540.0775 | BE74: =BD74/BC74 -> 0.26098455 | BF74: 4803,36 | BG74: 19.79/22.39/23.29,0301-0331,整体10%off 划线价 0227~0305 评论拆分 4天影响
A75: 0309~0315 | B75: 2026W11 | C75: 516 | D75: 494 | E75: 11340.07 | F75: 59 | G75: 50 | H75: 1294.81 | I75: 21.95 | J75: 28 | K75: =J75/C75 -> 0.054263566 | L75: 557.36 | M75: =(C75-C74)/C74 -> 0.055214724 | N75: =(D75-D74)/D74 -> 0.066954644 | O75: =(E75-E74)/E74 -> 0.049701291 | P75: =C75/D75 -> 1.0445344 | Q75: =E75/D75 -> 22.955607 | R75: =E75/C75 -> 21.97688 | S75: =C75/7 -> 73.714286 | T75: =D75-Y75 -> 192 | U75: =T75/D75 -> 0.38866397 | V75: =Z75/(E75-I75) -> 0.19503681 | W75: 176307 | X75: 2202 | Y75: 302 | Z75: 2207.45 | AA75: 6324.06 | AB75: 1 | AC75: =Z75/AA75 -> 0.34905583 | AD75: =X75/W75 -> 0.012489578 | AE75: =Y75/X75 -> 0.13714805 | AF75: =Z75/Y75 -> 7.3094371 | AG75: 126 | AH75: 194 | AI75: 196 | AJ75: =AG75*产品成本!$D$2+AH75*产品成本!$D$3+AI75*产品成本!$D$4 -> 1324.7887 | AK75: =AG75*产品成本!$E$2+AH75*产品成本!$E$3+AI75*产品成本!$E$4 -> 100.43577 | AL75: =AG75*产品成本!$F$2+AH75*产品成本!$F$3+AI75*产品成本!$F$4 -> 175.44 | AM75: =AG75*产品成本!$G$2+AH75*产品成本!$G$3+AI75*产品成本!$G$4 -> 1985.94 | AN75: =(E75-I75)*0.15 -> 1697.718 | AO75: =SUM(AJ75:AN75) -> 5284.3225 | AP75: 3 | AQ75: 7 | AR75: 18 | AS75: =L75/(1-0.15+0.15*0.2) -> 633.36364 | AT75: =AP75*产品成本!$D$2+AQ75*产品成本!$D$3+AR75*产品成本!$D$4 -> 80.704225 | AU75: =AP75*产品成本!$E$2+AQ75*产品成本!$E$3+AR75*产品成本!$E$4 -> 5.6503521 | AV75: =AP75*产品成本!$F$2+AQ75*产品成本!$F$3+AR75*产品成本!$F$4 -> 9.52 | AX75: =AS75*0.15 -> 95.004545 | AY75: =-AX75*0.2 -> -19.000909 | AZ75: =SUM(AT75:AY75) -> 171.87821 | BA75: =AO75-AZ75 -> 5112.4443 | BB75: =E75-I75 -> 11318.12 | BC75: =E75-AS75-I75 -> 10684.756 | BD75: =BC75-BA75-Z75 -> 3364.8621 | BE75: =BD75/BC75 -> 0.31492174 | BF75: 4800,40 | BG75: 19.79/22.39/23.29,0301-0331,整体10%off 划线价 高退货 B0CDBV251P/B0BMQL779Q/B0BMQKFDQ7
A76: 0316~0322 | B76: 2026W12 | C76: 607 | D76: 578 | E76: 13284.45 | F76: 96 | G76: 83 | H76: 2106.88 | I76: 21.95 | J76: 42 | K76: =J76/C76 -> 0.069192751 | L76: 790.8 | M76: =(C76-C75)/C75 -> 0.17635659 | N76: =(D76-D75)/D75 -> 0.17004049 | O76: =(E76-E75)/E75 -> 0.17146102 | P76: =C76/D76 -> 1.050173 | Q76: =E76/D76 -> 22.983478 | R76: =E76/C76 -> 21.88542 | S76: =C76/7 -> 86.714286 | T76: =D76-Y76 -> 188 | U76: =T76/D76 -> 0.32525952 | V76: =Z76/(E76-I76) -> 0.22812893 | W76: 538423 | X76: 2869 | Y76: 390 | Z76: 3025.56 | AA76: 8041.88 | AB76: 1.05 | AC76: =Z76/AA76 -> 0.37622546 | AD76: =X76/W76 -> 0.0053285242 | AE76: =Y76/X76 -> 0.13593587 | AF76: =Z76/Y76 -> 7.7578462 | AG76: 173 | AH76: 180 | AI76: 254 | AJ76: =AG76*产品成本!$D$2+AH76*产品成本!$D$3+AI76*产品成本!$D$4 -> 1586.4789 | AK76: =AG76*产品成本!$E$2+AH76*产品成本!$E$3+AI76*产品成本!$E$4 -> 118.07624 | AL76: =AG76*产品成本!$F$2+AH76*产品成本!$F$3+AI76*产品成本!$F$4 -> 206.38 | AM76: =AG76*产品成本!$G$2+AH76*产品成本!$G$3+AI76*产品成本!$G$4 -> 2330.97 | AN76: =(E76-I76)*0.15 -> 1989.375 | AO76: =SUM(AJ76:AN76) -> 6231.2801 | AP76: 16 | AQ76: 11 | AR76: 15 | AS76: =L76/(1-0.15+0.15*0.2) -> 898.63636 | AT76: =AP76*产品成本!$D$2+AQ76*产品成本!$D$3+AR76*产品成本!$D$4 -> 106.69014 | AU76: =AP76*产品成本!$E$2+AQ76*产品成本!$E$3+AR76*产品成本!$E$4 -> 8.0484042 | AV76: =AP76*产品成本!$F$2+AQ76*产品成本!$F$3+AR76*产品成本!$F$4 -> 14.28 | AX76: =AS76*0.15 -> 134.79545 | AY76: =-AX76*0.2 -> -26.959091 | AZ76: =SUM(AT76:AY76) -> 236.85491 | BA76: =AO76-AZ76 -> 5994.4252 | BB76: =E76-I76 -> 13262.5 | BC76: =E76-AS76-I76 -> 12363.864 | BD76: =BC76-BA76-Z76 -> 3343.8784 | BE76: =BD76/BC76 -> 0.27045578 | BF76: 3817,29 | BG76: 19.79/22.39/23.29,0317-0324,整体10%off Z划算
A77: 0323~0329 | B77: 2026W13 | C77: 543 | D77: 510 | E77: 11886.82 | F77: 258 | G77: 234 | H77: 5716.1 | I77: 22.16 | J77: 48 | K77: =J77/C77 -> 0.08839779 | L77: 914.55 | M77: =(C77-C76)/C76 -> -0.10543657 | N77: =(D77-D76)/D76 -> -0.11764706 | O77: =(E77-E76)/E76 -> -0.10520797 | P77: =C77/D77 -> 1.0647059 | Q77: =E77/D77 -> 23.30749 | R77: =E77/C77 -> 21.891013 | S77: =C77/7 -> 77.571429 | T77: =D77-Y77 -> 156 | U77: =T77/D77 -> 0.30588235 | V77: =Z77/(E77-I77) -> 0.23895501 | W77: 315938 | X77: 2679 | Y77: 354 | Z77: 2835.12 | AA77: 7310.63 | AB77: 1.06 | AC77: =Z77/AA77 -> 0.38780789 | AD77: =X77/W77 -> 0.0084795118 | AE77: =Y77/X77 -> 0.13213886 | AF77: =Z77/Y77 -> 8.0088136 | AG77: 133 | AH77: 214 | AI77: 196 | AJ77: =AG77*产品成本!$D$2+AH77*产品成本!$D$3+AI77*产品成本!$D$4 -> 1381.831 | AK77: =AG77*产品成本!$E$2+AH77*产品成本!$E$3+AI77*产品成本!$E$4 -> 105.50683 | AL77: =AG77*产品成本!$F$2+AH77*产品成本!$F$3+AI77*产品成本!$F$4 -> 184.62 | AM77: =AG77*产品成本!$G$2+AH77*产品成本!$G$3+AI77*产品成本!$G$4 -> 2089.77 | AN77: =(E77-I77)*0.15 -> 1779.699 | AO77: =SUM(AJ77:AN77) -> 5541.4268 | AP77: 12 | AQ77: 15 | AR77: 21 | AS77: =L77/(1-0.15+0.15*0.2) -> 1039.2614 | AT77: =AP77*产品成本!$D$2+AQ77*产品成本!$D$3+AR77*产品成本!$D$4 -> 126.5493 | AU77: =AP77*产品成本!$E$2+AQ77*产品成本!$E$3+AR77*产品成本!$E$4 -> 9.3851366 | AV77: =AP77*产品成本!$F$2+AQ77*产品成本!$F$3+AR77*产品成本!$F$4 -> 16.32 | AX77: =AS77*0.15 -> 155.8892 | AY77: =-AX77*0.2 -> -31.177841 | AZ77: =SUM(AT77:AY77) -> 276.9658 | BA77: =AO77-AZ77 -> 5264.461 | BB77: =E77-I77 -> 11864.66 | BC77: =E77-AS77-I77 -> 10825.399 | BD77: =BC77-BA77-Z77 -> 2725.8176 | BE77: =BD77/BC77 -> 0.25179836 | BF77: 3817,29 | BG77: 19.79/22.39/23.29,0317-0324,整体10%off Z划算
A78: 汇总 | C78: =SUBTOTAL(109,表22[销量]) -> 31980 | D78: =SUBTOTAL(109,表22[订单量]) -> 30212 | E78: =SUBTOTAL(109,表22[销售额]) -> 720639.24 | F78: =SUBTOTAL(109,表22[促销销量]) -> 3012 | G78: =SUBTOTAL(109,表22[促销订单量]) -> 2637 | H78: =SUBTOTAL(109,表22[促销销售额]) -> 68434.25 | I78: =SUBTOTAL(109,表22[促销折扣]) -> 4999.41 | J78: =SUBTOTAL(109,表22[退款量]) -> 2290 | K78: =J78/C78 -> 0.071607255 | L78: =SUBTOTAL(109,表22[退款金额]) -> 44715.04 | P78: =C78/D78 -> 1.0585198 | Q78: =E78/D78 -> 23.852749 | R78: =E78/C78 -> 22.53406 | S78: =C78/7 -> 4568.5714 | T78: =D78-Y78 -> 11553 | U78: =T78/D78 -> 0.38239772 | V78: =Z78/(E78-I78) -> 0.25816336 | W78: =SUBTOTAL(109,表22[展示]) -> 17535500 | X78: =SUBTOTAL(109,表22[点击]) -> 180797 | Y78: =SUBTOTAL(109,表22[广告订单量]) -> 18659 | Z78: =SUBTOTAL(109,表22[广告花费]) -> 184751.98 | AA78: =SUBTOTAL(109,表22[广告销售额]) -> 440942.91 | AB78: =SUBTOTAL(101,表22[CPC]) -> 1.0242857 | AC78: =Z78/AA78 -> 0.41899297 | AD78: =X78/W78 -> 0.010310342 | AE78: =Y78/X78 -> 0.10320415 | AF78: =Z78/Y78 -> 9.9014942 | AG78: =SUBTOTAL(109,表22[3.6FT]) -> 8465 | AH78: =SUBTOTAL(109,表22[5.0FT]) -> 13412 | AI78: =SUBTOTAL(109,表22[5.5FT]) -> 10076 | AJ78: =SUBTOTAL(109,表22[产品成本]) -> 79569.155 | AK78: =SUBTOTAL(109,表22[头程]) -> 6171.245 | AL78: =SUBTOTAL(109,表22[入仓费]) -> 10864.02 | AM78: =SUBTOTAL(109,表22[FBA物流]) -> 122839.05 | AN78: =SUBTOTAL(109,表22[佣金]) -> 107345.97 | AO78: =SUBTOTAL(109,表22[成本小结]) -> 326789.44 | AP78: =SUBTOTAL(109,表22[退款3.6FT]) -> 643 | AQ78: =SUBTOTAL(109,表22[退款5.0FT]) -> 900 | AR78: =SUBTOTAL(109,表22[退款5.5FT]) -> 743 | AS78: =SUBTOTAL(109,表22[退款 销售金额]) -> 50812.545 | AT78: =SUBTOTAL(109,表22[退款 产品成本]) -> 5719.0845 | AU78: =SUBTOTAL(109,表22[退款头程]) -> 441.17045 | AV78: =SUBTOTAL(109,表22[退款 入仓费]) -> 777.24 | AX78: =SUBTOTAL(109,表22[退款佣金]) -> 7621.8818 | AY78: =SUBTOTAL(109,表22[退款 管理费用 佣金的20%]) -> -1524.3764 | AZ78: =SUBTOTAL(109,表22[退款 成本小结]) -> 13035 | BA78: =SUBTOTAL(109,表22[净成本]) -> 313754.44 | BB78: =SUBTOTAL(109,表22[净销售额]) -> 715639.83 | BC78: =SUBTOTAL(109,表22[净销售额 (-退款金额)]) -> 664827.28 | BD78: =SUBTOTAL(109,表22[毛利]) -> 166320.86 | BE78: =BD78/BC78 -> 0.25017153 | BI78: =SUBTOTAL(103,表22[备用]) -> 0

Sheet Toy
A1: 产品 | C1: 销售情况$ | W1: 广告$ | AG1: 销售成本$ | AQ1: 退款成本$ 退款部分的销售金额=系统退款金额/(1-0.15+0.2*0.15) | BC1: 汇总$
C2: 输入 | M2: 公式输出 | W2: 输入 | AC2: 公式输出 | AG2: 输入 | AK2: 公式输出 | AQ2: 输入 | AU2: 公式输出
A3: 日期 | B3: 周数 | C3: 销量 | D3: 订单量 | E3: 销售额 | F3: 促销销量 | G3: 促销订单量 | H3: 促销销售额 | I3: 促销折扣 | J3: 退款量 | K3: 退款率 | L3: 退款金额 | M3: 销量环比 | N3: 订单环比 | O3: 销售额环比 | P3: 客单 销量 | Q3: 客单 价格($) | R3: 销售 均价($) | S3: 日均 销量 | T3: 自然 订单 | U3: 自然单 占比(%) | V3: TAcos (%) | W3: 展示 | X3: 点击 | Y3: 广告订单量 | Z3: 广告花费 | AA3: 广告销售额 | AB3: CPC | AC3: Acos(%) | AD3: CTR(%) | AE3: CVR(%) | AF3: CPS(%) | AG3: Short w/oBall 1Pack | AH3: Long w/oBall 1Pack | AI3: w/Ball 1Pack | AJ3: Long w/oBall 2Pack | AK3: 产品成本 | AL3: 头程 | AM3: 入仓费 | AN3: FBA物流 | AO3: 佣金 | AP3: 成本小结 | AQ3: 退款Short w/oBall 1Pack | AR3: 退款Long w/oBall 1Pack | AS3: 退款w/Ball 1Pack | AT3: 退款Long w/oBall 2Pack | AU3: 退款 销售金额 | AV3: 退款 产品成本 | AW3: 退款头程 | AX3: 退款 入仓费 | AY3: 退款 FBA物流 | AZ3: 退款佣金 | BA3: 退款 管理费用 佣金的20% | BB3: 退款 成本小结 | BC3: 净成本 | BD3: 净销售额 | BE3: 净销售额 (-退款金额) | BF3: 毛利 | BG3: 毛利率 | BH3: BSR | BI3: 备注 | BJ3: 促销 | BK3: 列1
A4: 1104~1110 | B4: 2024W45 | C4: 40 | D4: 37 | E4: 949.6 | J4: 0 | K4: =J4/C4 -> 0 | L4: 0 | M4: =(C4-C3)/C3 -> #VALUE! | N4: =(D4-D3)/D3 -> #VALUE! | O4: =(E4-E3)/E3 -> #VALUE! | P4: =C4/D4 -> 1.0810811 | Q4: =E4/D4 -> 25.664865 | R4: =E4/C4 -> 23.74 | S4: =C4/7 -> 5.7142857 | T4: =D4-Y4 -> 8 | U4: =T4/D4 -> 0.21621622 | V4: =Z4/(E4-I4) -> 0.34419756 | W4: 54006 | X4: 248 | Y4: 29 | Z4: 326.85 | AA4: 710.7 | AB4: 1.32 | AC4: =Z4/AA4 -> 0.45989869 | AD4: =X4/W4 -> 0.0045920824 | AE4: =Y4/X4 -> 0.11693548 | AF4: =Z4/Y4 -> 11.27069 | AG4: 10 | AH4: 10 | AI4: 20 | AJ4: 0 | AK4: =AG4*产品成本!$D$5+AH4*产品成本!$D$6+AI4*产品成本!$D$7+AJ4*产品成本!$D$8 -> 128.16901 | AL4: =AG4*产品成本!$E$5+AH4*产品成本!$E$6+AI4*产品成本!$E$7+AJ4*产品成本!$E$8 -> 13.9 | AM4: =AG4*产品成本!$F$5+AH4*产品成本!$F$6+AI4*产品成本!$F$7+AJ4*产品成本!$F$8 -> 15.7 | AN4: =AG4*产品成本!$G$5+AH4*产品成本!$G$6+AI4*产品成本!$G$7+AJ4*产品成本!$G$8 -> 195.4 | AO4: =(E4-I4)*0.15 -> 142.44 | AP4: =SUM(AK4:AO4) -> 495.60901 | AQ4: 0 | AR4: 0 | AS4: 0 | AT4: 0 | AU4: =L4/(1-0.15-0.15*0.2) -> 0 | AV4: =AQ4*产品成本!$D$5+AR4*产品成本!$D$6+AS4*产品成本!$D$7+AT4*产品成本!D8 -> 0 | AW4: =AQ4*产品成本!$E$5+AR4*产品成本!$E$6+AS4*产品成本!$E$7+AT4*产品成本!E8 -> 0 | AX4: =AQ4*产品成本!$F$5+AR4*产品成本!$F$6+AS4*产品成本!$F$7+AT4*产品成本!F8 -> 0 | AY4: 0 | AZ4: =AU4*0.15 -> 0 | BA4: =-AZ4*0.2 -> 0 | BB4: =SUM(AV4:BA4) -> 0 | BC4: =AP4-BB4 -> 495.60901 | BD4: =E4-I4 -> 949.6 | BE4: =E4-AU4-I4 -> 949.6 | BF4: =BE4-BC4-Z4 -> 127.14099 | BG4: =BF4/BE4 -> 0.13388899
A5: 1111~1117 | B5: 2024W46 | C5: 58 | D5: 55 | E5: 1371.42 | J5: 1 | K5: =J5/C5 -> 0.017241379 | L5: 20.23 | M5: =(C5-C4)/C4 -> 0.45 | N5: =(D5-D4)/D4 -> 0.48648649 | O5: =(E5-E4)/E4 -> 0.44420809 | P5: =C5/D5 -> 1.0545455 | Q5: =E5/D5 -> 24.934909 | R5: =E5/C5 -> 23.645172 | S5: =C5/7 -> 8.2857143 | T5: =D5-Y5 -> 22 | U5: =T5/D5 -> 0.4 | V5: =Z5/(E5-I5) -> 0.22456286 | W5: 55780 | X5: 231 | Y5: 33 | Z5: 307.97 | AA5: 819.65 | AB5: 1.33 | AC5: =Z5/AA5 -> 0.37573354 | AD5: =X5/W5 -> 0.0041412693 | AE5: =Y5/X5 -> 0.14285714 | AF5: =Z5/Y5 -> 9.3324242 | AG5: 20 | AH5: 19 | AI5: 19 | AJ5: 0 | AK5: =AG5*产品成本!$D$5+AH5*产品成本!$D$6+AI5*产品成本!$D$7+AJ5*产品成本!$D$8 -> 176.61972 | AL5: =AG5*产品成本!$E$5+AH5*产品成本!$E$6+AI5*产品成本!$E$7+AJ5*产品成本!$E$8 -> 19.08 | AM5: =AG5*产品成本!$F$5+AH5*产品成本!$F$6+AI5*产品成本!$F$7+AJ5*产品成本!$F$8 -> 22.45 | AN5: =AG5*产品成本!$G$5+AH5*产品成本!$G$6+AI5*产品成本!$G$7+AJ5*产品成本!$G$8 -> 275.84 | AO5: =(E5-I5)*0.15 -> 205.713 | AP5: =SUM(AK5:AO5) -> 699.70272 | AQ5: 1 | AR5: 0 | AS5: 0 | AT5: 0 | AU5: =L5/(1-0.15-0.15*0.2) -> 24.670732 | AV5: =AQ5*产品成本!$D$5+AR5*产品成本!$D$6+AS5*产品成本!$D$7+AT5*产品成本!D11 -> 2.6760563 | AW5: =AQ5*产品成本!$E$5+AR5*产品成本!$E$6+AS5*产品成本!$E$7+AT5*产品成本!E11 -> 0.27 | AX5: =AQ5*产品成本!$F$5+AR5*产品成本!$F$6+AS5*产品成本!$F$7+AT5*产品成本!F11 -> 0.41 | AY5: 0 | AZ5: =AU5*0.15 -> 3.7006098 | BA5: =-AZ5*0.2 -> -0.74012195 | BB5: =SUM(AV5:BA5) -> 6.3165441 | BC5: =AP5-BB5 -> 693.38617 | BD5: =E5-I5 -> 1371.42 | BE5: =E5-AU5-I5 -> 1346.7493 | BF5: =BE5-BC5-Z5 -> 345.39309 | BG5: =BF5/BE5 -> 0.25646429
A6: 1118~1124 | B6: 2024W47 | C6: 44 | D6: 42 | E6: 1044.56 | J6: 0 | K6: =J6/C6 -> 0 | L6: 0 | M6: =(C6-C5)/C5 -> -0.24137931 | N6: =(D6-D5)/D5 -> -0.23636364 | O6: =(E6-E5)/E5 -> -0.23833691 | P6: =C6/D6 -> 1.047619 | Q6: =E6/D6 -> 24.870476 | R6: =E6/C6 -> 23.74 | S6: =C6/7 -> 6.2857143 | T6: =D6-Y6 -> 12 | U6: =T6/D6 -> 0.28571429 | V6: =Z6/(E6-I6) -> 0.44654208 | W6: 80855 | X6: 306 | Y6: 30 | Z6: 466.44 | AA6: 708.7 | AB6: 1.52 | AC6: =Z6/AA6 -> 0.65816283 | AD6: =X6/W6 -> 0.0037845526 | AE6: =Y6/X6 -> 0.098039216 | AF6: =Z6/Y6 -> 15.548 | AG6: 11 | AH6: 17 | AI6: 16 | AJ6: 0 | AK6: =AG6*产品成本!$D$5+AH6*产品成本!$D$6+AI6*产品成本!$D$7+AJ6*产品成本!$D$8 -> 135.91549 | AL6: =AG6*产品成本!$E$5+AH6*产品成本!$E$6+AI6*产品成本!$E$7+AJ6*产品成本!$E$8 -> 14.81 | AM6: =AG6*产品成本!$F$5+AH6*产品成本!$F$6+AI6*产品成本!$F$7+AJ6*产品成本!$F$8 -> 16.85 | AN6: =AG6*产品成本!$G$5+AH6*产品成本!$G$6+AI6*产品成本!$G$7+AJ6*产品成本!$G$8 -> 207.74 | AO6: =(E6-I6)*0.15 -> 156.684 | AP6: =SUM(AK6:AO6) -> 531.99949 | AQ6: 0 | AR6: 0 | AS6: 0 | AT6: 0 | AU6: =L6/(1-0.15-0.15*0.2) -> 0 | AV6: =AQ6*产品成本!$D$5+AR6*产品成本!$D$6+AS6*产品成本!$D$7+AT6*产品成本!D12 -> 0 | AW6: =AQ6*产品成本!$E$5+AR6*产品成本!$E$6+AS6*产品成本!$E$7+AT6*产品成本!E12 -> 0 | AX6: =AQ6*产品成本!$F$5+AR6*产品成本!$F$6+AS6*产品成本!$F$7+AT6*产品成本!F12 -> 0 | AY6: 0 | AZ6: =AU6*0.15 -> 0 | BA6: =-AZ6*0.2 -> 0 | BB6: =SUM(AV6:BA6) -> 0 | BC6: =AP6-BB6 -> 531.99949 | BD6: =E6-I6 -> 1044.56 | BE6: =E6-AU6-I6 -> 1044.56 | BF6: =BE6-BC6-Z6 -> 46.120507 | BG6: =BF6/BE6 -> 0.044153047
A7: 1125~1201 | B7: 2024W48 | C7: 57 | D7: 55 | E7: 1343.43 | J7: 0 | K7: =J7/C7 -> 0 | L7: 0 | M7: =(C7-C6)/C6 -> 0.29545455 | N7: =(D7-D6)/D6 -> 0.30952381 | O7: =(E7-E6)/E6 -> 0.28612047 | P7: =C7/D7 -> 1.0363636 | Q7: =E7/D7 -> 24.426 | R7: =E7/C7 -> 23.568947 | S7: =C7/7 -> 8.1428571 | T7: =D7-Y7 -> 20 | U7: =T7/D7 -> 0.36363636 | V7: =Z7/(E7-I7) -> 0.38619057 | W7: 107755 | X7: 336 | Y7: 35 | Z7: 518.82 | AA7: 815.65 | AB7: 1.54 | AC7: =Z7/AA7 -> 0.63608165 | AD7: =X7/W7 -> 0.0031181848 | AE7: =Y7/X7 -> 0.10416667 | AF7: =Z7/Y7 -> 14.823429 | AG7: 24 | AH7: 22 | AI7: 11 | AJ7: 0 | AK7: =AG7*产品成本!$D$5+AH7*产品成本!$D$6+AI7*产品成本!$D$7+AJ7*产品成本!$D$8 -> 166.47887 | AL7: =AG7*产品成本!$E$5+AH7*产品成本!$E$6+AI7*产品成本!$E$7+AJ7*产品成本!$E$8 -> 17.92 | AM7: =AG7*产品成本!$F$5+AH7*产品成本!$F$6+AI7*产品成本!$F$7+AJ7*产品成本!$F$8 -> 21.83 | AN7: =AG7*产品成本!$G$5+AH7*产品成本!$G$6+AI7*产品成本!$G$7+AJ7*产品成本!$G$8 -> 265.44 | AO7: =(E7-I7)*0.15 -> 201.5145 | AP7: =SUM(AK7:AO7) -> 673.18337 | AQ7: 0 | AR7: 0 | AS7: 0 | AT7: 0 | AU7: =L7/(1-0.15-0.15*0.2) -> 0 | AV7: =AQ7*产品成本!$D$5+AR7*产品成本!$D$6+AS7*产品成本!$D$7+AT7*产品成本!D15 -> 0 | AW7: =AQ7*产品成本!$E$5+AR7*产品成本!$E$6+AS7*产品成本!$E$7+AT7*产品成本!E15 -> 0 | AX7: =AQ7*产品成本!$F$5+AR7*产品成本!$F$6+AS7*产品成本!$F$7+AT7*产品成本!F15 -> 0 | AY7: 0 | AZ7: =AU7*0.15 -> 0 | BA7: =-AZ7*0.2 -> 0 | BB7: =SUM(AV7:BA7) -> 0 | BC7: =AP7-BB7 -> 673.18337 | BD7: =E7-I7 -> 1343.43 | BE7: =E7-AU7-I7 -> 1343.43 | BF7: =BE7-BC7-Z7 -> 151.42663 | BG7: =BF7/BE7 -> 0.11271642
A8: 1202~1208 | B8: 2024W49 | C8: 47 | D8: 46 | E8: 1107.53 | J8: 1 | K8: =J8/C8 -> 0.021276596 | L8: 21.11 | M8: =(C8-C7)/C7 -> -0.1754386 | N8: =(D8-D7)/D7 -> -0.16363636 | O8: =(E8-E7)/E7 -> -0.1755953 | P8: =C8/D8 -> 1.0217391 | Q8: =E8/D8 -> 24.076739 | R8: =E8/C8 -> 23.564468 | S8: =C8/7 -> 6.7142857 | T8: =D8-Y8 -> 21 | U8: =T8/D8 -> 0.45652174 | V8: =Z8/(E8-I8) -> 0.3454534 | W8: 70831 | X8: 276 | Y8: 25 | Z8: 382.6 | AA8: 591.75 | AB8: 1.39 | AC8: =Z8/AA8 -> 0.64655682 | AD8: =X8/W8 -> 0.0038965989 | AE8: =Y8/X8 -> 0.09057971 | AF8: =Z8/Y8 -> 15.304 | AG8: 20 | AH8: 14 | AI8: 13 | AJ8: 0 | AK8: =AG8*产品成本!$D$5+AH8*产品成本!$D$6+AI8*产品成本!$D$7+AJ8*产品成本!$D$8 -> 140.56338 | AL8: =AG8*产品成本!$E$5+AH8*产品成本!$E$6+AI8*产品成本!$E$7+AJ8*产品成本!$E$8 -> 15.08 | AM8: =AG8*产品成本!$F$5+AH8*产品成本!$F$6+AI8*产品成本!$F$7+AJ8*产品成本!$F$8 -> 18.29 | AN8: =AG8*产品成本!$G$5+AH8*产品成本!$G$6+AI8*产品成本!$G$7+AJ8*产品成本!$G$8 -> 223.76 | AO8: =(E8-I8)*0.15 -> 166.1295 | AP8: =SUM(AK8:AO8) -> 563.82288 | AQ8: 0 | AR8: 1 | AS8: 0 | AT8: 0 | AU8: =L8/(1-0.15-0.15*0.2) -> 25.743902 | AV8: =AQ8*产品成本!$D$5+AR8*产品成本!$D$6+AS8*产品成本!$D$7+AT8*产品成本!D16 -> 2.8169014 | AW8: =AQ8*产品成本!$E$5+AR8*产品成本!$E$6+AS8*产品成本!$E$7+AT8*产品成本!E16 -> 0.32 | AX8: =AQ8*产品成本!$F$5+AR8*产品成本!$F$6+AS8*产品成本!$F$7+AT8*产品成本!F16 -> 0.34 | AY8: 0 | AZ8: =AU8*0.15 -> 3.8615854 | BA8: =-AZ8*0.2 -> -0.77231707 | BB8: =SUM(AV8:BA8) -> 6.5661697 | BC8: =AP8-BB8 -> 557.25671 | BD8: =E8-I8 -> 1107.53 | BE8: =E8-AU8-I8 -> 1081.7861 | BF8: =BE8-BC8-Z8 -> 141.92939 | BG8: =BF8/BE8 -> 0.13119912
A9: 1209~1215 | B9: 2024W50 | C9: 69 | D9: 66 | E9: 1634.31 | J9: 4 | K9: =J9/C9 -> 0.057971014 | L9: 64.72 | M9: =(C9-C8)/C8 -> 0.46808511 | N9: =(D9-D8)/D8 -> 0.43478261 | O9: =(E9-E8)/E8 -> 0.47563497 | P9: =C9/D9 -> 1.0454545 | Q9: =E9/D9 -> 24.762273 | R9: =E9/C9 -> 23.685652 | S9: =C9/7 -> 9.8571429 | T9: =D9-Y9 -> 30 | U9: =T9/D9 -> 0.45454545 | V9: =Z9/(E9-I9) -> 0.24864928 | W9: 76019 | X9: 284 | Y9: 36 | Z9: 406.37 | AA9: 847.84 | AB9: 1.43 | AC9: =Z9/AA9 -> 0.47930034 | AD9: =X9/W9 -> 0.0037359081 | AE9: =Y9/X9 -> 0.12676056 | AF9: =Z9/Y9 -> 11.288056 | AG9: 21 | AH9: 24 | AI9: 24 | AJ9: 0 | AK9: =AG9*产品成本!$D$5+AH9*产品成本!$D$6+AI9*产品成本!$D$7+AJ9*产品成本!$D$8 -> 211.69014 | AL9: =AG9*产品成本!$E$5+AH9*产品成本!$E$6+AI9*产品成本!$E$7+AJ9*产品成本!$E$8 -> 22.95 | AM9: =AG9*产品成本!$F$5+AH9*产品成本!$F$6+AI9*产品成本!$F$7+AJ9*产品成本!$F$8 -> 26.61 | AN9: =AG9*产品成本!$G$5+AH9*产品成本!$G$6+AI9*产品成本!$G$7+AJ9*产品成本!$G$8 -> 327.54 | AO9: =(E9-I9)*0.15 -> 245.1465 | AP9: =SUM(AK9:AO9) -> 833.93664 | AQ9: 4 | AR9: 0 | AS9: 0 | AT9: 0 | AU9: =L9/(1-0.15-0.15*0.2) -> 78.926829 | AV9: =AQ9*产品成本!$D$5+AR9*产品成本!$D$6+AS9*产品成本!$D$7+AT9*产品成本!D17 -> 10.704225 | AW9: =AQ9*产品成本!$E$5+AR9*产品成本!$E$6+AS9*产品成本!$E$7+AT9*产品成本!E17 -> 1.08 | AX9: =AQ9*产品成本!$F$5+AR9*产品成本!$F$6+AS9*产品成本!$F$7+AT9*产品成本!F17 -> 1.64 | AY9: 0 | AZ9: =AU9*0.15 -> 11.839024 | BA9: =-AZ9*0.2 -> -2.3678049 | BB9: =SUM(AV9:BA9) -> 22.895445 | BC9: =AP9-BB9 -> 811.0412 | BD9: =E9-I9 -> 1634.31 | BE9: =E9-AU9-I9 -> 1555.3832 | BF9: =BE9-BC9-Z9 -> 337.97197 | BG9: =BF9/BE9 -> 0.21729178
A10: 1216~1222 | B10: 2024W51 | C10: 78 | D10: 76 | E10: 1727.32 | J10: 3 | K10: =J10/C10 -> 0.038461538 | L10: 57.52 | M10: =(C10-C9)/C9 -> 0.13043478 | N10: =(D10-D9)/D9 -> 0.15151515 | O10: =(E10-E9)/E9 -> 0.056910868 | P10: =C10/D10 -> 1.0263158 | Q10: =E10/D10 -> 22.727895 | R10: =E10/C10 -> 22.145128 | S10: =C10/7 -> 11.142857 | T10: =D10-Y10 -> 29 | U10: =T10/D10 -> 0.38157895 | V10: =Z10/(E10-I10) -> 0.29468772 | W10: 95228 | X10: 359 | Y10: 47 | Z10: 509.02 | AA10: 1027.73 | AB10: 1.42 | AC10: =Z10/AA10 -> 0.49528573 | AD10: =X10/W10 -> 0.0037698996 | AE10: =Y10/X10 -> 0.13091922 | AF10: =Z10/Y10 -> 10.830213 | AG10: 23 | AH10: 28 | AI10: 27 | AJ10: 0 | AK10: =AG10*产品成本!$D$5+AH10*产品成本!$D$6+AI10*产品成本!$D$7+AJ10*产品成本!$D$8 -> 239.29577 | AL10: =AG10*产品成本!$E$5+AH10*产品成本!$E$6+AI10*产品成本!$E$7+AJ10*产品成本!$E$8 -> 25.97 | AM10: =AG10*产品成本!$F$5+AH10*产品成本!$F$6+AI10*产品成本!$F$7+AJ10*产品成本!$F$8 -> 30.02 | AN10: =AG10*产品成本!$G$5+AH10*产品成本!$G$6+AI10*产品成本!$G$7+AJ10*产品成本!$G$8 -> 369.5 | AO10: =(E10-I10)*0.15 -> 259.098 | AP10: =SUM(AK10:AO10) -> 923.88377 | AQ10: 2 | AR10: 0 | AS10: 1 | AT10: 0 | AU10: =L10/(1-0.15-0.15*0.2) -> 70.146341 | AV10: =AQ10*产品成本!$D$5+AR10*产品成本!$D$6+AS10*产品成本!$D$7+AT10*产品成本!D19 -> 9.0140845 | AW10: =AQ10*产品成本!$E$5+AR10*产品成本!$E$6+AS10*产品成本!$E$7+AT10*产品成本!E19 -> 0.94 | AX10: =AQ10*产品成本!$F$5+AR10*产品成本!$F$6+AS10*产品成本!$F$7+AT10*产品成本!F19 -> 1.23 | AY10: 0 | AZ10: =AU10*0.15 -> 10.521951 | BA10: =-AZ10*0.2 -> -2.1043902 | BB10: =SUM(AV10:BA10) -> 19.601645 | BC10: =AP10-BB10 -> 904.28213 | BD10: =E10-I10 -> 1727.32 | BE10: =E10-AU10-I10 -> 1657.1737 | BF10: =BE10-BC10-Z10 -> 243.87153 | BG10: =BF10/BE10 -> 0.14716112
A11: 1223~1229 | B11: 2024W52 | C11: 44 | D11: 42 | E11: 940.06 | J11: 1 | K11: =J11/C11 -> 0.022727273 | L11: 21.59 | M11: =(C11-C10)/C10 -> -0.43589744 | N11: =(D11-D10)/D10 -> -0.44736842 | O11: =(E11-E10)/E10 -> -0.45576963 | P11: =C11/D11 -> 1.047619 | Q11: =E11/D11 -> 22.382381 | R11: =E11/C11 -> 21.365 | S11: =C11/7 -> 6.2857143 | T11: =D11-Y11 -> 22 | U11: =T11/D11 -> 0.52380952 | V11: =Z11/(E11-I11) -> 0.28838585 | W11: 38905 | X11: 205 | Y11: 20 | Z11: 271.1 | AA11: 450.69 | AB11: 1.32 | AC11: =Z11/AA11 -> 0.60152211 | AD11: =X11/W11 -> 0.0052692456 | AE11: =Y11/X11 -> 0.097560976 | AF11: =Z11/Y11 -> 13.555 | AG11: 11 | AH11: 18 | AI11: 15 | AJ11: 0 | AK11: =AG11*产品成本!$D$5+AH11*产品成本!$D$6+AI11*产品成本!$D$7+AJ11*产品成本!$D$8 -> 135.07042 | AL11: =AG11*产品成本!$E$5+AH11*产品成本!$E$6+AI11*产品成本!$E$7+AJ11*产品成本!$E$8 -> 14.73 | AM11: =AG11*产品成本!$F$5+AH11*产品成本!$F$6+AI11*产品成本!$F$7+AJ11*产品成本!$F$8 -> 16.78 | AN11: =AG11*产品成本!$G$5+AH11*产品成本!$G$6+AI11*产品成本!$G$7+AJ11*产品成本!$G$8 -> 206.54 | AO11: =(E11-I11)*0.15 -> 141.009 | AP11: =SUM(AK11:AO11) -> 514.12942 | AQ11: 0 | AR11: 1 | AS11: 0 | AT11: 0 | AU11: =L11/(1-0.15-0.15*0.2) -> 26.329268 | AV11: =AQ11*产品成本!$D$5+AR11*产品成本!$D$6+AS11*产品成本!$D$7+AT11*产品成本!D20 -> 2.8169014 | AW11: =AQ11*产品成本!$E$5+AR11*产品成本!$E$6+AS11*产品成本!$E$7+AT11*产品成本!E20 -> 0.32 | AX11: =AQ11*产品成本!$F$5+AR11*产品成本!$F$6+AS11*产品成本!$F$7+AT11*产品成本!F20 -> 0.34 | AY11: 0 | AZ11: =AU11*0.15 -> 3.9493902 | BA11: =-AZ11*0.2 -> -0.78987805 | BB11: =SUM(AV11:BA11) -> 6.6364136 | BC11: =AP11-BB11 -> 507.49301 | BD11: =E11-I11 -> 940.06 | BE11: =E11-AU11-I11 -> 913.73073 | BF11: =BE11-BC11-Z11 -> 135.13772 | BG11: =BF11/BE11 -> 0.14789666 | BI11: ADW1
A12: 1230~0105 | B12: 2025W01 | C12: 40 | D12: 40 | E12: 853.7 | J12: 1 | K12: =J12/C12 -> 0.025 | L12: 19 | M12: =(C12-C11)/C11 -> -0.090909091 | N12: =(D12-D11)/D11 -> -0.047619048 | O12: =(E12-E11)/E11 -> -0.091866477 | P12: =C12/D12 -> 1 | Q12: =E12/D12 -> 21.3425 | R12: =E12/C12 -> 21.3425 | S12: =C12/7 -> 5.7142857 | T12: =D12-Y12 -> 17 | U12: =T12/D12 -> 0.425 | V12: =Z12/(E12-I12) -> 0.29796181 | W12: 33555 | X12: 218 | Y12: 23 | Z12: 254.37 | AA12: 485.47 | AB12: 1.17 | AC12: =Z12/AA12 -> 0.52396647 | AD12: =X12/W12 -> 0.0064967963 | AE12: =Y12/X12 -> 0.10550459 | AF12: =Z12/Y12 -> 11.059565 | AG12: 11 | AH12: 17 | AI12: 12 | AJ12: 0 | AK12: =AG12*产品成本!$D$5+AH12*产品成本!$D$6+AI12*产品成本!$D$7+AJ12*产品成本!$D$8 -> 121.26761 | AL12: =AG12*产品成本!$E$5+AH12*产品成本!$E$6+AI12*产品成本!$E$7+AJ12*产品成本!$E$8 -> 13.21 | AM12: =AG12*产品成本!$F$5+AH12*产品成本!$F$6+AI12*产品成本!$F$7+AJ12*产品成本!$F$8 -> 15.21 | AN12: =AG12*产品成本!$G$5+AH12*产品成本!$G$6+AI12*产品成本!$G$7+AJ12*产品成本!$G$8 -> 186.62 | AO12: =(E12-I12)*0.15 -> 128.055 | AP12: =SUM(AK12:AO12) -> 464.36261 | AQ12: 0 | AR12: 0 | AS12: 1 | AT12: 0 | AU12: =L12/(1-0.15-0.15*0.2) -> 23.170732 | AV12: =AQ12*产品成本!$D$5+AR12*产品成本!$D$6+AS12*产品成本!$D$7+AT12*产品成本!D21 -> 3.6619718 | AW12: =AQ12*产品成本!$E$5+AR12*产品成本!$E$6+AS12*产品成本!$E$7+AT12*产品成本!E21 -> 0.4 | AX12: =AQ12*产品成本!$F$5+AR12*产品成本!$F$6+AS12*产品成本!$F$7+AT12*产品成本!F21 -> 0.41 | AY12: 0 | AZ12: =AU12*0.15 -> 3.4756098 | BA12: =-AZ12*0.2 -> -0.69512195 | BB12: =SUM(AV12:BA12) -> 7.2524596 | BC12: =AP12-BB12 -> 457.11015 | BD12: =E12-I12 -> 853.7 | BE12: =E12-AU12-I12 -> 830.52927 | BF12: =BE12-BC12-Z12 -> 119.04912 | BG12: =BF12/BE12 -> 0.14334127 | BI12: ADW2,降CPC和Acos
A13: 0106~0112 | B13: 2025W02 | C13: 32 | D13: 31 | E13: 760.68 | J13: 1 | K13: =J13/C13 -> 0.03125 | L13: 19 | M13: =(C13-C12)/C12 -> -0.2 | N13: =(D13-D12)/D12 -> -0.225 | O13: =(E13-E12)/E12 -> -0.10896099 | P13: =C13/D13 -> 1.0322581 | Q13: =E13/D13 -> 24.538065 | R13: =E13/C13 -> 23.77125 | S13: =C13/7 -> 4.5714286 | T13: =D13-Y13 -> 11 | U13: =T13/D13 -> 0.35483871 | V13: =Z13/(E13-I13) -> 0.30475364 | W13: 32697 | X13: 197 | Y13: 20 | Z13: 231.82 | AA13: 475.8 | AB13: 1.18 | AC13: =Z13/AA13 -> 0.48722152 | AD13: =X13/W13 -> 0.0060250176 | AE13: =Y13/X13 -> 0.10152284 | AF13: =Z13/Y13 -> 11.591 | AG13: 7 | AH13: 10 | AI13: 15 | AJ13: 0 | AK13: =AG13*产品成本!$D$5+AH13*产品成本!$D$6+AI13*产品成本!$D$7+AJ13*产品成本!$D$8 -> 101.83099 | AL13: =AG13*产品成本!$E$5+AH13*产品成本!$E$6+AI13*产品成本!$E$7+AJ13*产品成本!$E$8 -> 11.09 | AM13: =AG13*产品成本!$F$5+AH13*产品成本!$F$6+AI13*产品成本!$F$7+AJ13*产品成本!$F$8 -> 12.42 | AN13: =AG13*产品成本!$G$5+AH13*产品成本!$G$6+AI13*产品成本!$G$7+AJ13*产品成本!$G$8 -> 154.3 | AO13: =(E13-I13)*0.15 -> 114.102 | AP13: =SUM(AK13:AO13) -> 393.74299 | AQ13: 0 | AR13: 0 | AS13: 1 | AT13: 0 | AU13: =L13/(1-0.15-0.15*0.2) -> 23.170732 | AV13: =AQ13*产品成本!$D$5+AR13*产品成本!$D$6+AS13*产品成本!$D$7+AT13*产品成本!D22 -> 3.6619718 | AW13: =AQ13*产品成本!$E$5+AR13*产品成本!$E$6+AS13*产品成本!$E$7+AT13*产品成本!E22 -> 0.4 | AX13: =AQ13*产品成本!$F$5+AR13*产品成本!$F$6+AS13*产品成本!$F$7+AT13*产品成本!F22 -> 0.41 | AY13: 0 | AZ13: =AU13*0.15 -> 3.4756098 | BA13: =-AZ13*0.2 -> -0.69512195 | BB13: =SUM(AV13:BA13) -> 7.2524596 | BC13: =AP13-BB13 -> 386.49053 | BD13: =E13-I13 -> 760.68 | BE13: =E13-AU13-I13 -> 737.50927 | BF13: =BE13-BC13-Z13 -> 119.19874 | BG13: =BF13/BE13 -> 0.16162338 | BI13: 原价
A14: 0113~0119 | B14: 2025W03 | C14: 39 | D14: 37 | E14: 898.21 | J14: 1 | K14: =J14/C14 -> 0.025641026 | L14: 18.21 | M14: =(C14-C13)/C13 -> 0.21875 | N14: =(D14-D13)/D13 -> 0.19354839 | O14: =(E14-E13)/E13 -> 0.18079876 | P14: =C14/D14 -> 1.0540541 | Q14: =E14/D14 -> 24.275946 | R14: =E14/C14 -> 23.031026 | S14: =C14/7 -> 5.5714286 | T14: =D14-Y14 -> 17 | U14: =T14/D14 -> 0.45945946 | V14: =Z14/(E14-I14) -> 0.28279578 | W14: 46155 | X14: 217 | Y14: 20 | Z14: 254.01 | AA14: 470.99 | AB14: 1.17 | AC14: =Z14/AA14 -> 0.53931081 | AD14: =X14/W14 -> 0.0047015491 | AE14: =Y14/X14 -> 0.092165899 | AF14: =Z14/Y14 -> 12.7005 | AG14: 9 | AH14: 19 | AI14: 11 | AJ14: 0 | AK14: =AG14*产品成本!$D$5+AH14*产品成本!$D$6+AI14*产品成本!$D$7+AJ14*产品成本!$D$8 -> 117.88732 | AL14: =AG14*产品成本!$E$5+AH14*产品成本!$E$6+AI14*产品成本!$E$7+AJ14*产品成本!$E$8 -> 12.91 | AM14: =AG14*产品成本!$F$5+AH14*产品成本!$F$6+AI14*产品成本!$F$7+AJ14*产品成本!$F$8 -> 14.66 | AN14: =AG14*产品成本!$G$5+AH14*产品成本!$G$6+AI14*产品成本!$G$7+AJ14*产品成本!$G$8 -> 179.7 | AO14: =(E14-I14)*0.15 -> 134.7315 | AP14: =SUM(AK14:AO14) -> 459.88882 | AQ14: 1 | AR14: 0 | AS14: 0 | AT14: 0 | AU14: =L14/(1-0.15-0.15*0.2) -> 22.207317 | AV14: =AQ14*产品成本!$D$5+AR14*产品成本!$D$6+AS14*产品成本!$D$7+AT14*产品成本!D23 -> 2.6760563 | AW14: =AQ14*产品成本!$E$5+AR14*产品成本!$E$6+AS14*产品成本!$E$7+AT14*产品成本!E23 -> 0.27 | AX14: =AQ14*产品成本!$F$5+AR14*产品成本!$F$6+AS14*产品成本!$F$7+AT14*产品成本!F23 -> 0.41 | AZ14: =AU14*0.15 -> 3.3310976 | BA14: =-AZ14*0.2 -> -0.66621951 | BB14: =SUM(AV14:BA14) -> 6.0209344 | BC14: =AP14-BB14 -> 453.86789 | BD14: =E14-I14 -> 898.21 | BE14: =E14-AU14-I14 -> 876.00268 | BF14: =BE14-BC14-Z14 -> 168.12479 | BG14: =BF14/BE14 -> 0.19192269 | BI14: 平日原价 周末九折
A15: 0120~0126 | B15: 2025W04 | C15: 45 | D15: 42 | E15: 1008.55 | J15: 3 | K15: =J15/C15 -> 0.066666667 | L15: 62.45 | M15: =(C15-C14)/C14 -> 0.15384615 | N15: =(D15-D14)/D14 -> 0.13513514 | O15: =(E15-E14)/E14 -> 0.12284432 | P15: =C15/D15 -> 1.0714286 | Q15: =E15/D15 -> 24.013095 | R15: =E15/C15 -> 22.412222 | S15: =C15/7 -> 6.4285714 | T15: =D15-Y15 -> 17 | U15: =T15/D15 -> 0.4047619 | V15: =Z15/(E15-I15) -> 0.34793515 | W15: 76033 | X15: 299 | Y15: 25 | Z15: 350.91 | AA15: 682.89 | AB15: 1.17 | AC15: =Z15/AA15 -> 0.51386021 | AD15: =X15/W15 -> 0.003932503 | AE15: =Y15/X15 -> 0.08361204 | AF15: =Z15/Y15 -> 14.0364 | AG15: 9 | AH15: 18 | AI15: 18 | AJ15: 0 | AK15: =AG15*产品成本!$D$5+AH15*产品成本!$D$6+AI15*产品成本!$D$7+AJ15*产品成本!$D$8 -> 140.70423 | AL15: =AG15*产品成本!$E$5+AH15*产品成本!$E$6+AI15*产品成本!$E$7+AJ15*产品成本!$E$8 -> 15.39 | AM15: =AG15*产品成本!$F$5+AH15*产品成本!$F$6+AI15*产品成本!$F$7+AJ15*产品成本!$F$8 -> 17.19 | AN15: =AG15*产品成本!$G$5+AH15*产品成本!$G$6+AI15*产品成本!$G$7+AJ15*产品成本!$G$8 -> 212.58 | AO15: =(E15-I15)*0.15 -> 151.2825 | AP15: =SUM(AK15:AO15) -> 537.14673 | AQ15: 1 | AR15: 0 | AS15: 2 | AT15: 0 | AU15: =L15/(1-0.15-0.15*0.2) -> 76.158537 | AV15: =AQ15*产品成本!$D$5+AR15*产品成本!$D$6+AS15*产品成本!$D$7+AT15*产品成本!D24 -> 10 | AW15: =AQ15*产品成本!$E$5+AR15*产品成本!$E$6+AS15*产品成本!$E$7+AT15*产品成本!E24 -> 1.07 | AX15: =AQ15*产品成本!$F$5+AR15*产品成本!$F$6+AS15*产品成本!$F$7+AT15*产品成本!F24 -> 1.23 | AZ15: =AU15*0.15 -> 11.42378 | BA15: =-AZ15*0.2 -> -2.2847561 | BB15: =SUM(AV15:BA15) -> 21.439024 | BC15: =AP15-BB15 -> 515.7077 | BD15: =E15-I15 -> 1008.55 | BE15: =E15-AU15-I15 -> 932.39146 | BF15: =BE15-BC15-Z15 -> 65.773762 | BG15: =BF15/BE15 -> 0.070543077
A16: 0127~0202 | B16: 2025W05 | C16: 57 | D16: 57 | E16: 1219.83 | J16: 1 | K16: =J16/C16 -> 0.01754386 | L16: 21.11 | M16: =(C16-C15)/C15 -> 0.26666667 | N16: =(D16-D15)/D15 -> 0.35714286 | O16: =(E16-E15)/E15 -> 0.20948887 | P16: =C16/D16 -> 1 | Q16: =E16/D16 -> 21.400526 | R16: =E16/C16 -> 21.400526 | S16: =C16/7 -> 8.1428571 | T16: =D16-Y16 -> 22 | U16: =T16/D16 -> 0.38596491 | V16: =Z16/(E16-I16) -> 0.25233024 | W16: 48720 | X16: 267 | Y16: 35 | Z16: 307.8 | AA16: 754.86 | AB16: 1.15 | AC16: =Z16/AA16 -> 0.40775773 | AD16: =X16/W16 -> 0.0054802956 | AE16: =Y16/X16 -> 0.13108614 | AF16: =Z16/Y16 -> 8.7942857 | AG16: 12 | AH16: 21 | AI16: 24 | AJ16: 0 | AK16: =AG16*产品成本!$D$5+AH16*产品成本!$D$6+AI16*产品成本!$D$7+AJ16*产品成本!$D$8 -> 179.15493 | AL16: =AG16*产品成本!$E$5+AH16*产品成本!$E$6+AI16*产品成本!$E$7+AJ16*产品成本!$E$8 -> 19.56 | AM16: =AG16*产品成本!$F$5+AH16*产品成本!$F$6+AI16*产品成本!$F$7+AJ16*产品成本!$F$8 -> 21.9 | AN16: =AG16*产品成本!$G$5+AH16*产品成本!$G$6+AI16*产品成本!$G$7+AJ16*产品成本!$G$8 -> 271.2 | AO16: =(E16-I16)*0.15 -> 182.9745 | AP16: =SUM(AK16:AO16) -> 674.78943 | AQ16: 0 | AR16: 0 | AS16: 1 | AT16: 0 | AU16: =L16/(1-0.15-0.15*0.2) -> 25.743902 | AV16: =AQ16*产品成本!$D$5+AR16*产品成本!$D$6+AS16*产品成本!$D$7+AT16*产品成本!D25 -> 3.6619718 | AW16: =AQ16*产品成本!$E$5+AR16*产品成本!$E$6+AS16*产品成本!$E$7+AT16*产品成本!E25 -> 0.4 | AX16: =AQ16*产品成本!$F$5+AR16*产品成本!$F$6+AS16*产品成本!$F$7+AT16*产品成本!F25 -> 0.41 | AZ16: =AU16*0.15 -> 3.8615854 | BA16: =-AZ16*0.2 -> -0.77231707 | BB16: =SUM(AV16:BA16) -> 7.5612401 | BC16: =AP16-BB16 -> 667.22819 | BD16: =E16-I16 -> 1219.83 | BE16: =E16-AU16-I16 -> 1194.0861 | BF16: =BE16-BC16-Z16 -> 219.05791 | BG16: =BF16/BE16 -> 0.18345236
A17: 0203~0209 | B17: 2025W06 | C17: 68 | D17: 57 | E17: 1559.92 | J17: 3 | K17: =J17/C17 -> 0.044117647 | L17: 60.34 | M17: =(C17-C16)/C16 -> 0.19298246 | N17: =(D17-D16)/D16 -> 0 | O17: =(E17-E16)/E16 -> 0.27880114 | P17: =C17/D17 -> 1.1929825 | Q17: =E17/D17 -> 27.367018 | R17: =E17/C17 -> 22.94 | S17: =C17/7 -> 9.7142857 | T17: =D17-Y17 -> 18 | U17: =T17/D17 -> 0.31578947 | V17: =Z17/(E17-I17) -> 0.20599774 | W17: 47496 | X17: 291 | Y17: 39 | Z17: 321.34 | AA17: 1029.05 | AB17: 1.1 | AC17: =Z17/AA17 -> 0.3122686 | AD17: =X17/W17 -> 0.0061268317 | AE17: =Y17/X17 -> 0.13402062 | AF17: =Z17/Y17 -> 8.2394872 | AG17: 14 | AH17: 28 | AI17: 26 | AJ17: 0 | AK17: =AG17*产品成本!$D$5+AH17*产品成本!$D$6+AI17*产品成本!$D$7+AJ17*产品成本!$D$8 -> 211.5493 | AL17: =AG17*产品成本!$E$5+AH17*产品成本!$E$6+AI17*产品成本!$E$7+AJ17*产品成本!$E$8 -> 23.14 | AM17: =AG17*产品成本!$F$5+AH17*产品成本!$F$6+AI17*产品成本!$F$7+AJ17*产品成本!$F$8 -> 25.92 | AN17: =AG17*产品成本!$G$5+AH17*产品成本!$G$6+AI17*产品成本!$G$7+AJ17*产品成本!$G$8 -> 320.12 | AO17: =(E17-I17)*0.15 -> 233.988 | AP17: =SUM(AK17:AO17) -> 814.7173 | AQ17: 1 | AR17: 1 | AS17: 1 | AT17: 0 | AU17: =L17/(1-0.15-0.15*0.2) -> 73.585366 | AV17: =AQ17*产品成本!$D$5+AR17*产品成本!$D$6+AS17*产品成本!$D$7+AT17*产品成本!D26 -> 9.1549296 | AW17: =AQ17*产品成本!$E$5+AR17*产品成本!$E$6+AS17*产品成本!$E$7+AT17*产品成本!E26 -> 0.99 | AX17: =AQ17*产品成本!$F$5+AR17*产品成本!$F$6+AS17*产品成本!$F$7+AT17*产品成本!F26 -> 1.16 | AZ17: =AU17*0.15 -> 11.037805 | BA17: =-AZ17*0.2 -> -2.207561 | BB17: =SUM(AV17:BA17) -> 20.135173 | BC17: =AP17-BB17 -> 794.58212 | BD17: =E17-I17 -> 1559.92 | BE17: =E17-AU17-I17 -> 1486.3346 | BF17: =BE17-BC17-Z17 -> 370.41251 | BG17: =BF17/BE17 -> 0.24921206
A18: 0210~0216 | B18: 2025W07 | C18: 38 | D18: 36 | E18: 900.62 | J18: 2 | K18: =J18/C18 -> 0.052631579 | L18: 38 | M18: =(C18-C17)/C17 -> -0.44117647 | N18: =(D18-D17)/D17 -> -0.36842105 | O18: =(E18-E17)/E17 -> -0.42264988 | P18: =C18/D18 -> 1.0555556 | Q18: =E18/D18 -> 25.017222 | R18: =E18/C18 -> 23.700526 | S18: =C18/7 -> 5.4285714 | T18: =D18-Y18 -> 18 | U18: =T18/D18 -> 0.5 | V18: =Z18/(E18-I18) -> 0.31528281 | W18: 43873 | X18: 252 | Y18: 18 | Z18: 283.95 | AA18: 454.81 | AB18: 1.13 | AC18: =Z18/AA18 -> 0.62432664 | AD18: =X18/W18 -> 0.0057438516 | AE18: =Y18/X18 -> 0.071428571 | AF18: =Z18/Y18 -> 15.775 | AG18: 11 | AH18: 12 | AI18: 15 | AJ18: 0 | AK18: =AG18*产品成本!$D$5+AH18*产品成本!$D$6+AI18*产品成本!$D$7+AJ18*产品成本!$D$8 -> 118.16901 | AL18: =AG18*产品成本!$E$5+AH18*产品成本!$E$6+AI18*产品成本!$E$7+AJ18*产品成本!$E$8 -> 12.81 | AM18: =AG18*产品成本!$F$5+AH18*产品成本!$F$6+AI18*产品成本!$F$7+AJ18*产品成本!$F$8 -> 14.74 | AN18: =AG18*产品成本!$G$5+AH18*产品成本!$G$6+AI18*产品成本!$G$7+AJ18*产品成本!$G$8 -> 182.06 | AO18: =(E18-I18)*0.15 -> 135.093 | AP18: =SUM(AK18:AO18) -> 462.87201 | AQ18: 0 | AR18: 0 | AS18: 2 | AT18: 0 | AU18: =L18/(1-0.15-0.15*0.2) -> 46.341463 | AV18: =AQ18*产品成本!$D$5+AR18*产品成本!$D$6+AS18*产品成本!$D$7+AT18*产品成本!D27 -> 7.3239437 | AW18: =AQ18*产品成本!$E$5+AR18*产品成本!$E$6+AS18*产品成本!$E$7+AT18*产品成本!E27 -> 0.8 | AX18: =AQ18*产品成本!$F$5+AR18*产品成本!$F$6+AS18*产品成本!$F$7+AT18*产品成本!F27 -> 0.82 | AZ18: =AU18*0.15 -> 6.9512195 | BA18: =-AZ18*0.2 -> -1.3902439 | BB18: =SUM(AV18:BA18) -> 14.504919 | BC18: =AP18-BB18 -> 448.36709 | BD18: =E18-I18 -> 900.62 | BE18: =E18-AU18-I18 -> 854.27854 | BF18: =BE18-BC18-Z18 -> 121.96144 | BG18: =BF18/BE18 -> 0.14276543 | BI18: 断货w/ball只有orange
A19: 0217~0223 | B19: 2025W08 | C19: 37 | D19: 37 | E19: 855.64 | J19: 2 | K19: =J19/C19 -> 0.054054054 | L19: 41.34 | M19: =(C19-C18)/C18 -> -0.026315789 | N19: =(D19-D18)/D18 -> 0.027777778 | O19: =(E19-E18)/E18 -> -0.049943372 | P19: =C19/D19 -> 1 | Q19: =E19/D19 -> 23.125405 | R19: =E19/C19 -> 23.125405 | S19: =C19/7 -> 5.2857143 | T19: =D19-Y19 -> 12 | U19: =T19/D19 -> 0.32432432 | V19: =Z19/(E19-I19) -> 0.30954607 | W19: 49981 | X19: 235 | Y19: 25 | Z19: 264.86 | AA19: 592.75 | AB19: 1.13 | AC19: =Z19/AA19 -> 0.44683256 | AD19: =X19/W19 -> 0.0047017867 | AE19: =Y19/X19 -> 0.10638298 | AF19: =Z19/Y19 -> 10.5944 | AG19: 8 | AH19: 20 | AI19: 9 | AJ19: 0 | AK19: =AG19*产品成本!$D$5+AH19*产品成本!$D$6+AI19*产品成本!$D$7+AJ19*产品成本!$D$8 -> 110.70423 | AL19: =AG19*产品成本!$E$5+AH19*产品成本!$E$6+AI19*产品成本!$E$7+AJ19*产品成本!$E$8 -> 12.16 | AM19: =AG19*产品成本!$F$5+AH19*产品成本!$F$6+AI19*产品成本!$F$7+AJ19*产品成本!$F$8 -> 13.77 | AN19: =AG19*产品成本!$G$5+AH19*产品成本!$G$6+AI19*产品成本!$G$7+AJ19*产品成本!$G$8 -> 168.32 | AO19: =(E19-I19)*0.15 -> 128.346 | AP19: =SUM(AK19:AO19) -> 433.30023 | AQ19: 1 | AR19: 1 | AS19: 0 | AT19: 0 | AU19: =L19/(1-0.15-0.15*0.2) -> 50.414634 | AV19: =AQ19*产品成本!$D$5+AR19*产品成本!$D$6+AS19*产品成本!$D$7+AT19*产品成本!D28 -> 5.4929577 | AW19: =AQ19*产品成本!$E$5+AR19*产品成本!$E$6+AS19*产品成本!$E$7+AT19*产品成本!E28 -> 0.59 | AX19: =AQ19*产品成本!$F$5+AR19*产品成本!$F$6+AS19*产品成本!$F$7+AT19*产品成本!F28 -> 0.75 | AZ19: =AU19*0.15 -> 7.5621951 | BA19: =-AZ19*0.2 -> -1.512439 | BB19: =SUM(AV19:BA19) -> 12.882714 | BC19: =AP19-BB19 -> 420.41751 | BD19: =E19-I19 -> 855.64 | BE19: =E19-AU19-I19 -> 805.22537 | BF19: =BE19-BC19-Z19 -> 119.94785 | BG19: =BF19/BE19 -> 0.14896184 | BI19: 断货w/ball只有orange,其他陆续断货
A20: 0224~0302 | B20: 2025W09 | C20: 48 | D20: 46 | E20: 1142.52 | J20: 2 | K20: =J20/C20 -> 0.041666667 | L20: 42.22 | M20: =(C20-C19)/C19 -> 0.2972973 | N20: =(D20-D19)/D19 -> 0.24324324 | O20: =(E20-E19)/E19 -> 0.33528119 | P20: =C20/D20 -> 1.0434783 | Q20: =E20/D20 -> 24.837391 | R20: =E20/C20 -> 23.8025 | S20: =C20/7 -> 6.8571429 | T20: =D20-Y20 -> 21 | U20: =T20/D20 -> 0.45652174 | V20: =Z20/(E20-I20) -> 0.1730648 | W20: 30704 | X20: 193 | Y20: 25 | Z20: 197.73 | AA20: 620.64 | AB20: 1.02 | AC20: =Z20/AA20 -> 0.31859049 | AD20: =X20/W20 -> 0.006285826 | AE20: =Y20/X20 -> 0.12953368 | AF20: =Z20/Y20 -> 7.9092 | AG20: 9 | AH20: 26 | AI20: 13 | AJ20: 0 | AK20: =AG20*产品成本!$D$5+AH20*产品成本!$D$6+AI20*产品成本!$D$7+AJ20*产品成本!$D$8 -> 144.92958 | AL20: =AG20*产品成本!$E$5+AH20*产品成本!$E$6+AI20*产品成本!$E$7+AJ20*产品成本!$E$8 -> 15.95 | AM20: =AG20*产品成本!$F$5+AH20*产品成本!$F$6+AI20*产品成本!$F$7+AJ20*产品成本!$F$8 -> 17.86 | AN20: =AG20*产品成本!$G$5+AH20*产品成本!$G$6+AI20*产品成本!$G$7+AJ20*产品成本!$G$8 -> 218.82 | AO20: =(E20-I20)*0.15 -> 171.378 | AP20: =SUM(AK20:AO20) -> 568.93758 | AQ20: 0 | AR20: 1 | AS20: 1 | AT20: 0 | AU20: =L20/(1-0.15-0.15*0.2) -> 51.487805 | AV20: =AQ20*产品成本!$D$5+AR20*产品成本!$D$6+AS20*产品成本!$D$7+AT20*产品成本!D29 -> 6.4788732 | AW20: =AQ20*产品成本!$E$5+AR20*产品成本!$E$6+AS20*产品成本!$E$7+AT20*产品成本!E29 -> 0.72 | AX20: =AQ20*产品成本!$F$5+AR20*产品成本!$F$6+AS20*产品成本!$F$7+AT20*产品成本!F29 -> 0.75 | AZ20: =AU20*0.15 -> 7.7231707 | BA20: =-AZ20*0.2 -> -1.5446341 | BB20: =SUM(AV20:BA20) -> 14.12741 | BC20: =AP20-BB20 -> 554.81017 | BD20: =E20-I20 -> 1142.52 | BE20: =E20-AU20-I20 -> 1091.0322 | BF20: =BE20-BC20-Z20 -> 338.49203 | BG20: =BF20/BE20 -> 0.31024935
A21: 0303~0309 | B21: 2025W10 | C21: 34 | D21: 33 | E21: 806.66 | J21: 0 | K21: =J21/C21 -> 0 | L21: 0 | M21: =(C21-C20)/C20 -> -0.29166667 | N21: =(D21-D20)/D20 -> -0.2826087 | O21: =(E21-E20)/E20 -> -0.29396422 | P21: =C21/D21 -> 1.030303 | Q21: =E21/D21 -> 24.444242 | R21: =E21/C21 -> 23.725294 | S21: =C21/7 -> 4.8571429 | T21: =D21-Y21 -> 9 | U21: =T21/D21 -> 0.27272727 | V21: =Z21/(E21-I21) -> 0.28595691 | W21: 32552 | X21: 215 | Y21: 24 | Z21: 230.67 | AA21: 584.85 | AB21: 1.07 | AC21: =Z21/AA21 -> 0.39440882 | AD21: =X21/W21 -> 0.0066048169 | AE21: =Y21/X21 -> 0.11162791 | AF21: =Z21/Y21 -> 9.61125 | AG21: 9 | AH21: 18 | AI21: 7 | AJ21: 0 | AK21: =AG21*产品成本!$D$5+AH21*产品成本!$D$6+AI21*产品成本!$D$7+AJ21*产品成本!$D$8 -> 100.42254 | AL21: =AG21*产品成本!$E$5+AH21*产品成本!$E$6+AI21*产品成本!$E$7+AJ21*产品成本!$E$8 -> 10.99 | AM21: =AG21*产品成本!$F$5+AH21*产品成本!$F$6+AI21*产品成本!$F$7+AJ21*产品成本!$F$8 -> 12.68 | AN21: =AG21*产品成本!$G$5+AH21*产品成本!$G$6+AI21*产品成本!$G$7+AJ21*产品成本!$G$8 -> 154.5 | AO21: =(E21-I21)*0.15 -> 120.999 | AP21: =SUM(AK21:AO21) -> 399.59154 | AQ21: 0 | AR21: 0 | AS21: 0 | AT21: 0 | AU21: =L21/(1-0.15-0.15*0.2) -> 0 | AV21: =AQ21*产品成本!$D$5+AR21*产品成本!$D$6+AS21*产品成本!$D$7+AT21*产品成本!D30 -> 0 | AW21: =AQ21*产品成本!$E$5+AR21*产品成本!$E$6+AS21*产品成本!$E$7+AT21*产品成本!E30 -> 0 | AX21: =AQ21*产品成本!$F$5+AR21*产品成本!$F$6+AS21*产品成本!$F$7+AT21*产品成本!F30 -> 0 | AZ21: =AU21*0.15 -> 0 | BA21: =-AZ21*0.2 -> 0 | BB21: =SUM(AV21:BA21) -> 0 | BC21: =AP21-BB21 -> 399.59154 | BD21: =E21-I21 -> 806.66 | BE21: =E21-AU21-I21 -> 806.66 | BF21: =BE21-BC21-Z21 -> 176.39846 | BG21: =BF21/BE21 -> 0.21867759
A22: 0310~0316 | B22: 2025W11 | C22: 38 | D22: 36 | E22: 902.62 | J22: 1 | K22: =J22/C22 -> 0.026315789 | L22: 21.11 | M22: =(C22-C21)/C21 -> 0.11764706 | N22: =(D22-D21)/D21 -> 0.090909091 | O22: =(E22-E21)/E21 -> 0.11895966 | P22: =C22/D22 -> 1.0555556 | Q22: =E22/D22 -> 25.072778 | R22: =E22/C22 -> 23.753158 | S22: =C22/7 -> 5.4285714 | T22: =D22-Y22 -> 17 | U22: =T22/D22 -> 0.47222222 | V22: =Z22/(E22-I22) -> 0.20330815 | W22: 30728 | X22: 173 | Y22: 19 | Z22: 183.51 | AA22: 472.8 | AB22: 1.06 | AC22: =Z22/AA22 -> 0.38813452 | AD22: =X22/W22 -> 0.0056300443 | AE22: =Y22/X22 -> 0.10982659 | AF22: =Z22/Y22 -> 9.6584211 | AG22: 9 | AH22: 18 | AI22: 11 | AJ22: 0 | AK22: =AG22*产品成本!$D$5+AH22*产品成本!$D$6+AI22*产品成本!$D$7+AJ22*产品成本!$D$8 -> 115.07042 | AL22: =AG22*产品成本!$E$5+AH22*产品成本!$E$6+AI22*产品成本!$E$7+AJ22*产品成本!$E$8 -> 12.59 | AM22: =AG22*产品成本!$F$5+AH22*产品成本!$F$6+AI22*产品成本!$F$7+AJ22*产品成本!$F$8 -> 14.32 | AN22: =AG22*产品成本!$G$5+AH22*产品成本!$G$6+AI22*产品成本!$G$7+AJ22*产品成本!$G$8 -> 175.62 | AO22: =(E22-I22)*0.15 -> 135.393 | AP22: =SUM(AK22:AO22) -> 452.99342 | AQ22: 0 | AR22: 0 | AS22: 1 | AT22: 0 | AU22: =L22/(1-0.15-0.15*0.2) -> 25.743902 | AV22: =AQ22*产品成本!$D$5+AR22*产品成本!$D$6+AS22*产品成本!$D$7+AT22*产品成本!D31 -> 3.6619718 | AW22: =AQ22*产品成本!$E$5+AR22*产品成本!$E$6+AS22*产品成本!$E$7+AT22*产品成本!E31 -> 0.4 | AX22: =AQ22*产品成本!$F$5+AR22*产品成本!$F$6+AS22*产品成本!$F$7+AT22*产品成本!F31 -> 0.41 | AZ22: =AU22*0.15 -> 3.8615854 | BA22: =-AZ22*0.2 -> -0.77231707 | BB22: =SUM(AV22:BA22) -> 7.5612401 | BC22: =AP22-BB22 -> 445.43218 | BD22: =E22-I22 -> 902.62 | BE22: =E22-AU22-I22 -> 876.8761 | BF22: =BE22-BC22-Z22 -> 247.93392 | BG22: =BF22/BE22 -> 0.28274681
A23: 0317~0323 | B23: 2025W12 | C23: 41 | D23: 40 | E23: 972.59 | J23: 0 | K23: =J23/C23 -> 0 | L23: 0 | M23: =(C23-C22)/C22 -> 0.078947368 | N23: =(D23-D22)/D22 -> 0.11111111 | O23: =(E23-E22)/E22 -> 0.077518779 | P23: =C23/D23 -> 1.025 | Q23: =E23/D23 -> 24.31475 | R23: =E23/C23 -> 23.721707 | S23: =C23/7 -> 5.8571429 | T23: =D23-Y23 -> 12 | U23: =T23/D23 -> 0.3 | V23: =Z23/(E23-I23) -> 0.28038536 | W23: 35047 | X23: 253 | Y23: 28 | Z23: 272.7 | AA23: 653.71 | AB23: 1.11 | AC23: =Z23/AA23 -> 0.41715746 | AD23: =X23/W23 -> 0.0072188775 | AE23: =Y23/X23 -> 0.11067194 | AF23: =Z23/Y23 -> 9.7392857 | AG23: 11 | AH23: 16 | AI23: 14 | AJ23: 0 | AK23: =AG23*产品成本!$D$5+AH23*产品成本!$D$6+AI23*产品成本!$D$7+AJ23*产品成本!$D$8 -> 125.77465 | AL23: =AG23*产品成本!$E$5+AH23*产品成本!$E$6+AI23*产品成本!$E$7+AJ23*产品成本!$E$8 -> 13.69 | AM23: =AG23*产品成本!$F$5+AH23*产品成本!$F$6+AI23*产品成本!$F$7+AJ23*产品成本!$F$8 -> 15.69 | AN23: =AG23*产品成本!$G$5+AH23*产品成本!$G$6+AI23*产品成本!$G$7+AJ23*产品成本!$G$8 -> 193.1 | AO23: =(E23-I23)*0.15 -> 145.8885 | AP23: =SUM(AK23:AO23) -> 494.14315 | AQ23: 0 | AR23: 0 | AS23: 0 | AT23: 0 | AU23: =L23/(1-0.15-0.15*0.2) -> 0 | AV23: =AQ23*产品成本!$D$5+AR23*产品成本!$D$6+AS23*产品成本!$D$7+AT23*产品成本!D32 -> 0 | AW23: =AQ23*产品成本!$E$5+AR23*产品成本!$E$6+AS23*产品成本!$E$7+AT23*产品成本!E32 -> 0 | AX23: =AQ23*产品成本!$F$5+AR23*产品成本!$F$6+AS23*产品成本!$F$7+AT23*产品成本!F32 -> 0 | AZ23: =AU23*0.15 -> 0 | BA23: =-AZ23*0.2 -> 0 | BB23: =SUM(AV23:BA23) -> 0 | BC23: =AP23-BB23 -> 494.14315 | BD23: =E23-I23 -> 972.59 | BE23: =E23-AU23-I23 -> 972.59 | BF23: =BE23-BC23-Z23 -> 205.74685 | BG23: =BF23/BE23 -> 0.21154531 | BI23: 海运补货0323
A24: 0324~0330 | B24: 2025W13 | C24: 56 | D24: 53 | E24: 1151.05 | J24: 1 | K24: =J24/C24 -> 0.017857143 | L24: 21.11 | M24: =(C24-C23)/C23 -> 0.36585366 | N24: =(D24-D23)/D23 -> 0.325 | O24: =(E24-E23)/E23 -> 0.18348945 | P24: =C24/D24 -> 1.0566038 | Q24: =E24/D24 -> 21.717925 | R24: =E24/C24 -> 20.554464 | S24: =C24/7 -> 8 | T24: =D24-Y24 -> 21 | U24: =T24/D24 -> 0.39622642 | V24: =Z24/(E24-I24) -> 0.25741714 | W24: 41621 | X24: 248 | Y24: 32 | Z24: 296.3 | AA24: 681.37 | AB24: 1.19 | AC24: =Z24/AA24 -> 0.43485918 | AD24: =X24/W24 -> 0.0059585305 | AE24: =Y24/X24 -> 0.12903226 | AF24: =Z24/Y24 -> 9.259375 | AG24: 15 | AH24: 22 | AI24: 19 | AJ24: 0 | AK24: =AG24*产品成本!$D$5+AH24*产品成本!$D$6+AI24*产品成本!$D$7+AJ24*产品成本!$D$8 -> 171.69014 | AL24: =AG24*产品成本!$E$5+AH24*产品成本!$E$6+AI24*产品成本!$E$7+AJ24*产品成本!$E$8 -> 18.69 | AM24: =AG24*产品成本!$F$5+AH24*产品成本!$F$6+AI24*产品成本!$F$7+AJ24*产品成本!$F$8 -> 21.42 | AN24: =AG24*产品成本!$G$5+AH24*产品成本!$G$6+AI24*产品成本!$G$7+AJ24*产品成本!$G$8 -> 263.58 | AO24: =(E24-I24)*0.15 -> 172.6575 | AP24: =SUM(AK24:AO24) -> 648.03764 | AQ24: 0 | AR24: 0 | AS24: 1 | AT24: 0 | AU24: =L24/(1-0.15-0.15*0.2) -> 25.743902 | AV24: =AQ24*产品成本!$D$5+AR24*产品成本!$D$6+AS24*产品成本!$D$7+AT24*产品成本!D33 -> 3.6619718 | AW24: =AQ24*产品成本!$E$5+AR24*产品成本!$E$6+AS24*产品成本!$E$7+AT24*产品成本!E33 -> 0.4 | AX24: =AQ24*产品成本!$F$5+AR24*产品成本!$F$6+AS24*产品成本!$F$7+AT24*产品成本!F33 -> 0.41 | AZ24: =AU24*0.15 -> 3.8615854 | BA24: =-AZ24*0.2 -> -0.77231707 | BB24: =SUM(AV24:BA24) -> 7.5612401 | BC24: =AP24-BB24 -> 640.4764 | BD24: =E24-I24 -> 1151.05 | BE24: =E24-AU24-I24 -> 1125.3061 | BF24: =BE24-BC24-Z24 -> 188.5297 | BG24: =BF24/BE24 -> 0.16753637 | BI24: 春促15%off折扣
A25: 0331~0406 | B25: 2025W14 | C25: 30 | D25: 29 | E25: 686.7 | J25: 1 | K25: =J25/C25 -> 0.033333333 | L25: 21.11 | M25: =(C25-C24)/C24 -> -0.46428571 | N25: =(D25-D24)/D24 -> -0.45283019 | O25: =(E25-E24)/E24 -> -0.40341427 | P25: =C25/D25 -> 1.0344828 | Q25: =E25/D25 -> 23.67931 | R25: =E25/C25 -> 22.89 | S25: =C25/7 -> 4.2857143 | T25: =D25-Y25 -> 14 | U25: =T25/D25 -> 0.48275862 | V25: =Z25/(E25-I25) -> 0.2658803 | W25: 18306 | X25: 158 | Y25: 15 | Z25: 182.58 | AA25: 347.8 | AB25: 1.16 | AC25: =Z25/AA25 -> 0.52495687 | AD25: =X25/W25 -> 0.0086310499 | AE25: =Y25/X25 -> 0.094936709 | AF25: =Z25/Y25 -> 12.172 | AG25: 12 | AH25: 13 | AI25: 5 | AJ25: 0 | AK25: =AG25*产品成本!$D$5+AH25*产品成本!$D$6+AI25*产品成本!$D$7+AJ25*产品成本!$D$8 -> 87.042254 | AL25: =AG25*产品成本!$E$5+AH25*产品成本!$E$6+AI25*产品成本!$E$7+AJ25*产品成本!$E$8 -> 9.4 | AM25: =AG25*产品成本!$F$5+AH25*产品成本!$F$6+AI25*产品成本!$F$7+AJ25*产品成本!$F$8 -> 11.39 | AN25: =AG25*产品成本!$G$5+AH25*产品成本!$G$6+AI25*产品成本!$G$7+AJ25*产品成本!$G$8 -> 138.24 | AO25: =(E25-I25)*0.15 -> 103.005 | AP25: =SUM(AK25:AO25) -> 349.07725 | AQ25: 0 | AR25: 1 | AS25: 0 | AT25: 0 | AU25: =L25/(1-0.15-0.15*0.2) -> 25.743902 | AV25: =AQ25*产品成本!$D$5+AR25*产品成本!$D$6+AS25*产品成本!$D$7+AT25*产品成本!D34 -> 2.8169014 | AW25: =AQ25*产品成本!$E$5+AR25*产品成本!$E$6+AS25*产品成本!$E$7+AT25*产品成本!E34 -> 0.32 | AX25: =AQ25*产品成本!$F$5+AR25*产品成本!$F$6+AS25*产品成本!$F$7+AT25*产品成本!F34 -> 0.34 | AZ25: =AU25*0.15 -> 3.8615854 | BA25: =-AZ25*0.2 -> -0.77231707 | BB25: =SUM(AV25:BA25) -> 6.5661697 | BC25: =AP25-BB25 -> 342.51108 | BD25: =E25-I25 -> 686.7 | BE25: =E25-AU25-I25 -> 660.9561 | BF25: =BE25-BC25-Z25 -> 135.86501 | BG25: =BF25/BE25 -> 0.2055583
A26: 0407~0413 | B26: 2025W15 | C26: 40 | D26: 38 | E26: 956.6 | J26: 1 | K26: =J26/C26 -> 0.025 | L26: 17.1 | M26: =(C26-C25)/C25 -> 0.33333333 | N26: =(D26-D25)/D25 -> 0.31034483 | O26: =(E26-E25)/E25 -> 0.39303917 | P26: =C26/D26 -> 1.0526316 | Q26: =E26/D26 -> 25.173684 | R26: =E26/C26 -> 23.915 | S26: =C26/7 -> 5.7142857 | T26: =D26-Y26 -> 13 | U26: =T26/D26 -> 0.34210526 | V26: =Z26/(E26-I26) -> 0.17767092 | W26: 18638 | X26: 148 | Y26: 25 | Z26: 169.96 | AA26: 622.64 | AB26: 1.11 | AC26: =Z26/AA26 -> 0.27296672 | AD26: =X26/W26 -> 0.0079407662 | AE26: =Y26/X26 -> 0.16891892 | AF26: =Z26/Y26 -> 6.7984 | AG26: 3 | AH26: 26 | AI26: 11 | AJ26: 0 | AK26: =AG26*产品成本!$D$5+AH26*产品成本!$D$6+AI26*产品成本!$D$7+AJ26*产品成本!$D$8 -> 121.5493 | AL26: =AG26*产品成本!$E$5+AH26*产品成本!$E$6+AI26*产品成本!$E$7+AJ26*产品成本!$E$8 -> 13.53 | AM26: =AG26*产品成本!$F$5+AH26*产品成本!$F$6+AI26*产品成本!$F$7+AJ26*产品成本!$F$8 -> 14.58 | AN26: =AG26*产品成本!$G$5+AH26*产品成本!$G$6+AI26*产品成本!$G$7+AJ26*产品成本!$G$8 -> 178.86 | AO26: =(E26-I26)*0.15 -> 143.49 | AP26: =SUM(AK26:AO26) -> 472.0093 | AQ26: 0 | AR26: 0 | AS26: 1 | AT26: 0 | AU26: =L26/(1-0.15-0.15*0.2) -> 20.853659 | AV26: =AQ26*产品成本!$D$5+AR26*产品成本!$D$6+AS26*产品成本!$D$7+AT26*产品成本!D35 -> 3.6619718 | AW26: =AQ26*产品成本!$E$5+AR26*产品成本!$E$6+AS26*产品成本!$E$7+AT26*产品成本!E35 -> 0.4 | AX26: =AQ26*产品成本!$F$5+AR26*产品成本!$F$6+AS26*产品成本!$F$7+AT26*产品成本!F35 -> 0.41 | AZ26: =AU26*0.15 -> 3.1280488 | BA26: =-AZ26*0.2 -> -0.62560976 | BB26: =SUM(AV26:BA26) -> 6.9744109 | BC26: =AP26-BB26 -> 465.03488 | BD26: =E26-I26 -> 956.6 | BE26: =E26-AU26-I26 -> 935.74634 | BF26: =BE26-BC26-Z26 -> 300.75146 | BG26: =BF26/BE26 -> 0.32140276
A27: 0414~0420 | B27: 2025W16 | C27: 22 | D27: 22 | E27: 524.78 | J27: 1 | K27: =J27/C27 -> 0.045454545 | L27: 21.11 | M27: =(C27-C26)/C26 -> -0.45 | N27: =(D27-D26)/D26 -> -0.42105263 | O27: =(E27-E26)/E26 -> -0.45141125 | P27: =C27/D27 -> 1 | Q27: =E27/D27 -> 23.853636 | R27: =E27/C27 -> 23.853636 | S27: =C27/7 -> 3.1428571 | T27: =D27-Y27 -> 7 | U27: =T27/D27 -> 0.31818182 | V27: =Z27/(E27-I27) -> 0.31274058 | W27: 29556 | X27: 160 | Y27: 15 | Z27: 164.12 | AA27: 356.85 | AB27: 1.03 | AC27: =Z27/AA27 -> 0.45991313 | AD27: =X27/W27 -> 0.0054134524 | AE27: =Y27/X27 -> 0.09375 | AF27: =Z27/Y27 -> 10.941333 | AG27: 3 | AH27: 15 | AI27: 4 | AJ27: 0 | AK27: =AG27*产品成本!$D$5+AH27*产品成本!$D$6+AI27*产品成本!$D$7+AJ27*产品成本!$D$8 -> 64.929577 | AL27: =AG27*产品成本!$E$5+AH27*产品成本!$E$6+AI27*产品成本!$E$7+AJ27*产品成本!$E$8 -> 7.21 | AM27: =AG27*产品成本!$F$5+AH27*产品成本!$F$6+AI27*产品成本!$F$7+AJ27*产品成本!$F$8 -> 7.97 | AN27: =AG27*产品成本!$G$5+AH27*产品成本!$G$6+AI27*产品成本!$G$7+AJ27*产品成本!$G$8 -> 97.02 | AO27: =(E27-I27)*0.15 -> 78.717 | AP27: =SUM(AK27:AO27) -> 255.84658 | AQ27: 0 | AR27: 1 | AS27: 0 | AT27: 0 | AU27: =L27/(1-0.15-0.15*0.2) -> 25.743902 | AV27: =AQ27*产品成本!$D$5+AR27*产品成本!$D$6+AS27*产品成本!$D$7+AT27*产品成本!D36 -> 2.8169014 | AW27: =AQ27*产品成本!$E$5+AR27*产品成本!$E$6+AS27*产品成本!$E$7+AT27*产品成本!E36 -> 0.32 | AX27: =AQ27*产品成本!$F$5+AR27*产品成本!$F$6+AS27*产品成本!$F$7+AT27*产品成本!F36 -> 0.34 | AZ27: =AU27*0.15 -> 3.8615854 | BA27: =-AZ27*0.2 -> -0.77231707 | BB27: =SUM(AV27:BA27) -> 6.5661697 | BC27: =AP27-BB27 -> 249.28041 | BD27: =E27-I27 -> 524.78 | BE27: =E27-AU27-I27 -> 499.0361 | BF27: =BE27-BC27-Z27 -> 85.63569 | BG27: =BF27/BE27 -> 0.1716022
A28: 0421~0427 | B28: 2025W17 | C28: 22 | D28: 22 | E28: 522.78 | J28: 1 | K28: =J28/C28 -> 0.045454545 | L28: 20.23 | M28: =(C28-C27)/C27 -> 0 | N28: =(D28-D27)/D27 -> 0 | O28: =(E28-E27)/E27 -> -0.0038111209 | P28: =C28/D28 -> 1 | Q28: =E28/D28 -> 23.762727 | R28: =E28/C28 -> 23.762727 | S28: =C28/7 -> 3.1428571 | T28: =D28-Y28 -> 9 | U28: =T28/D28 -> 0.40909091 | V28: =Z28/(E28-I28) -> 0.44640193 | W28: 36296 | X28: 220 | Y28: 13 | Z28: 233.37 | AA28: 307.87 | AB28: 1.06 | AC28: =Z28/AA28 -> 0.75801475 | AD28: =X28/W28 -> 0.006061274 | AE28: =Y28/X28 -> 0.059090909 | AF28: =Z28/Y28 -> 17.951538 | AG28: 5 | AH28: 8 | AI28: 9 | AJ28: 0 | AK28: =AG28*产品成本!$D$5+AH28*产品成本!$D$6+AI28*产品成本!$D$7+AJ28*产品成本!$D$8 -> 68.873239 | AL28: =AG28*产品成本!$E$5+AH28*产品成本!$E$6+AI28*产品成本!$E$7+AJ28*产品成本!$E$8 -> 7.51 | AM28: =AG28*产品成本!$F$5+AH28*产品成本!$F$6+AI28*产品成本!$F$7+AJ28*产品成本!$F$8 -> 8.46 | AN28: =AG28*产品成本!$G$5+AH28*产品成本!$G$6+AI28*产品成本!$G$7+AJ28*产品成本!$G$8 -> 104.66 | AO28: =(E28-I28)*0.15 -> 78.417 | AP28: =SUM(AK28:AO28) -> 267.92024 | AQ28: 0 | AR28: 1 | AS28: 0 | AT28: 0 | AU28: =L28/(1-0.15-0.15*0.2) -> 24.670732 | AV28: =AQ28*产品成本!$D$5+AR28*产品成本!$D$6+AS28*产品成本!$D$7+AT28*产品成本!D37 -> 2.8169014 | AW28: =AQ28*产品成本!$E$5+AR28*产品成本!$E$6+AS28*产品成本!$E$7+AT28*产品成本!E37 -> 0.32 | AX28: =AQ28*产品成本!$F$5+AR28*产品成本!$F$6+AS28*产品成本!$F$7+AT28*产品成本!F37 -> 0.34 | AZ28: =AU28*0.15 -> 3.7006098 | BA28: =-AZ28*0.2 -> -0.74012195 | BB28: =SUM(AV28:BA28) -> 6.4373892 | BC28: =AP28-BB28 -> 261.48285 | BD28: =E28-I28 -> 522.78 | BE28: =E28-AU28-I28 -> 498.10927 | BF28: =BE28-BC28-Z28 -> 3.2564181 | BG28: =BF28/BE28 -> 0.0065375577 | BI28: 陆续到货，目前是都有货的状态，广告陆续重新打开，还有待观察调整。需要重新打排名，目前160，需要稳定到100以内
A29: 0428~0504 | B29: 2025W18 | C29: 50 | D29: 49 | E29: 1190.5 | J29: 0 | K29: =J29/C29 -> 0 | L29: 0 | M29: =(C29-C28)/C28 -> 1.2727273 | N29: =(D29-D28)/D28 -> 1.2272727 | O29: =(E29-E28)/E28 -> 1.2772486 | P29: =C29/D29 -> 1.0204082 | Q29: =E29/D29 -> 24.295918 | R29: =E29/C29 -> 23.81 | S29: =C29/7 -> 7.1428571 | T29: =D29-Y29 -> 14 | U29: =T29/D29 -> 0.28571429 | V29: =Z29/(E29-I29) -> 0.16871903 | W29: 30152 | X29: 181 | Y29: 35 | Z29: 200.86 | AA29: 831.65 | AB29: 1.11 | AC29: =Z29/AA29 -> 0.24151987 | AD29: =X29/W29 -> 0.0060029185 | AE29: =Y29/X29 -> 0.19337017 | AF29: =Z29/Y29 -> 5.7388571 | AG29: 9 | AH29: 30 | AI29: 11 | AJ29: 0 | AK29: =AG29*产品成本!$D$5+AH29*产品成本!$D$6+AI29*产品成本!$D$7+AJ29*产品成本!$D$8 -> 148.87324 | AL29: =AG29*产品成本!$E$5+AH29*产品成本!$E$6+AI29*产品成本!$E$7+AJ29*产品成本!$E$8 -> 16.43 | AM29: =AG29*产品成本!$F$5+AH29*产品成本!$F$6+AI29*产品成本!$F$7+AJ29*产品成本!$F$8 -> 18.4 | AN29: =AG29*产品成本!$G$5+AH29*产品成本!$G$6+AI29*产品成本!$G$7+AJ29*产品成本!$G$8 -> 224.58 | AO29: =(E29-I29)*0.15 -> 178.575 | AP29: =SUM(AK29:AO29) -> 586.85824 | AQ29: 0 | AR29: 0 | AS29: 0 | AT29: 0 | AU29: =L29/(1-0.15-0.15*0.2) -> 0 | AV29: =AQ29*产品成本!$D$5+AR29*产品成本!$D$6+AS29*产品成本!$D$7+AT29*产品成本!D38 -> 0 | AW29: =AQ29*产品成本!$E$5+AR29*产品成本!$E$6+AS29*产品成本!$E$7+AT29*产品成本!E38 -> 0 | AX29: =AQ29*产品成本!$F$5+AR29*产品成本!$F$6+AS29*产品成本!$F$7+AT29*产品成本!F38 -> 0 | AZ29: =AU29*0.15 -> 0 | BA29: =-AZ29*0.2 -> 0 | BB29: =SUM(AV29:BA29) -> 0 | BC29: =AP29-BB29 -> 586.85824 | BD29: =E29-I29 -> 1190.5 | BE29: =E29-AU29-I29 -> 1190.5 | BF29: =BE29-BC29-Z29 -> 402.78176 | BG29: =BF29/BE29 -> 0.33832991
A30: 0505~0511 | B30: 2025W19 | C30: 44 | D30: 44 | E30: 1067.55 | J30: 0 | K30: =J30/C30 -> 0 | L30: 0 | M30: =(C30-C29)/C29 -> -0.12 | N30: =(D30-D29)/D29 -> -0.10204082 | O30: =(E30-E29)/E29 -> -0.10327593 | P30: =C30/D30 -> 1 | Q30: =E30/D30 -> 24.2625 | R30: =E30/C30 -> 24.2625 | S30: =C30/7 -> 6.2857143 | T30: =D30-Y30 -> 20 | U30: =T30/D30 -> 0.45454545 | V30: =Z30/(E30-I30) -> 0.1810688 | W30: 27516 | X30: 177 | Y30: 24 | Z30: 193.3 | AA30: 568.76 | AB30: 1.09 | AC30: =Z30/AA30 -> 0.33986216 | AD30: =X30/W30 -> 0.006432621 | AE30: =Y30/X30 -> 0.13559322 | AF30: =Z30/Y30 -> 8.0541667 | AG30: 12 | AH30: 17 | AI30: 15 | AJ30: 0 | AK30: =AG30*产品成本!$D$5+AH30*产品成本!$D$6+AI30*产品成本!$D$7+AJ30*产品成本!$D$8 -> 134.92958 | AL30: =AG30*产品成本!$E$5+AH30*产品成本!$E$6+AI30*产品成本!$E$7+AJ30*产品成本!$E$8 -> 14.68 | AM30: =AG30*产品成本!$F$5+AH30*产品成本!$F$6+AI30*产品成本!$F$7+AJ30*产品成本!$F$8 -> 16.85 | AN30: =AG30*产品成本!$G$5+AH30*产品成本!$G$6+AI30*产品成本!$G$7+AJ30*产品成本!$G$8 -> 207.36 | AO30: =(E30-I30)*0.15 -> 160.1325 | AP30: =SUM(AK30:AO30) -> 533.95208 | AQ30: 0 | AR30: 0 | AS30: 0 | AT30: 0 | AU30: =L30/(1-0.15-0.15*0.2) -> 0 | AV30: =AQ30*产品成本!$D$5+AR30*产品成本!$D$6+AS30*产品成本!$D$7+AT30*产品成本!D39 -> 0 | AW30: =AQ30*产品成本!$E$5+AR30*产品成本!$E$6+AS30*产品成本!$E$7+AT30*产品成本!E39 -> 0 | AX30: =AQ30*产品成本!$F$5+AR30*产品成本!$F$6+AS30*产品成本!$F$7+AT30*产品成本!F39 -> 0 | AZ30: =AU30*0.15 -> 0 | BA30: =-AZ30*0.2 -> 0 | BB30: =SUM(AV30:BA30) -> 0 | BC30: =AP30-BB30 -> 533.95208 | BD30: =E30-I30 -> 1067.55 | BE30: =E30-AU30-I30 -> 1067.55 | BF30: =BE30-BC30-Z30 -> 340.29792 | BG30: =BF30/BE30 -> 0.31876532 | BI30: 无调整
A31: 0512~0518 | B31: 2025W20 | C31: 49 | D31: 47 | E31: 1169.51 | J31: 0 | K31: =J31/C31 -> 0 | L31: 0 | M31: =(C31-C30)/C30 -> 0.11363636 | N31: =(D31-D30)/D30 -> 0.068181818 | O31: =(E31-E30)/E30 -> 0.095508407 | P31: =C31/D31 -> 1.0425532 | Q31: =E31/D31 -> 24.883191 | R31: =E31/C31 -> 23.867551 | S31: =C31/7 -> 7 | T31: =D31-Y31 -> 23 | U31: =T31/D31 -> 0.4893617 | V31: =Z31/(E31-I31) -> 0.1652829 | W31: 27516 | X31: 177 | Y31: 24 | Z31: 193.3 | AA31: 568.76 | AB31: 1.09 | AC31: =Z31/AA31 -> 0.33986216 | AD31: =X31/W31 -> 0.006432621 | AE31: =Y31/X31 -> 0.13559322 | AF31: =Z31/Y31 -> 8.0541667 | AG31: 6 | AH31: 24 | AI31: 19 | AJ31: 0 | AK31: =AG31*产品成本!$D$5+AH31*产品成本!$D$6+AI31*产品成本!$D$7+AJ31*产品成本!$D$8 -> 153.23944 | AL31: =AG31*产品成本!$E$5+AH31*产品成本!$E$6+AI31*产品成本!$E$7+AJ31*产品成本!$E$8 -> 16.9 | AM31: =AG31*产品成本!$F$5+AH31*产品成本!$F$6+AI31*产品成本!$F$7+AJ31*产品成本!$F$8 -> 18.41 | AN31: =AG31*产品成本!$G$5+AH31*产品成本!$G$6+AI31*产品成本!$G$7+AJ31*产品成本!$G$8 -> 227.64 | AO31: =(E31-I31)*0.15 -> 175.4265 | AP31: =SUM(AK31:AO31) -> 591.61594 | AQ31: 0 | AR31: 0 | AS31: 0 | AT31: 0 | AU31: =L31/(1-0.15-0.15*0.2) -> 0 | AV31: =AQ31*产品成本!$D$5+AR31*产品成本!$D$6+AS31*产品成本!$D$7+AT31*产品成本!D40 -> 0 | AW31: =AQ31*产品成本!$E$5+AR31*产品成本!$E$6+AS31*产品成本!$E$7+AT31*产品成本!E40 -> 0 | AX31: =AQ31*产品成本!$F$5+AR31*产品成本!$F$6+AS31*产品成本!$F$7+AT31*产品成本!F40 -> 0 | AZ31: =AU31*0.15 -> 0 | BA31: =-AZ31*0.2 -> 0 | BB31: =SUM(AV31:BA31) -> 0 | BC31: =AP31-BB31 -> 591.61594 | BD31: =E31-I31 -> 1169.51 | BE31: =E31-AU31-I31 -> 1169.51 | BF31: =BE31-BC31-Z31 -> 384.59406 | BG31: =BF31/BE31 -> 0.3288506
A32: 0519~0525 | B32: 2025W21 | C32: 42 | D32: 42 | E32: 1002.58 | J32: 1 | K32: =J32/C32 -> 0.023809524 | L32: 21.11 | M32: =(C32-C31)/C31 -> -0.14285714 | N32: =(D32-D31)/D31 -> -0.10638298 | O32: =(E32-E31)/E31 -> -0.14273499 | P32: =C32/D32 -> 1 | Q32: =E32/D32 -> 23.870952 | R32: =E32/C32 -> 23.870952 | S32: =C32/7 -> 6 | T32: =D32-Y32 -> 17 | U32: =T32/D32 -> 0.4047619 | V32: =Z32/(E32-I32) -> 0.16185242 | W32: 25169 | X32: 167 | Y32: 25 | Z32: 162.27 | AA32: 597.86 | AB32: 0.97 | AC32: =Z32/AA32 -> 0.27141806 | AD32: =X32/W32 -> 0.0066351464 | AE32: =Y32/X32 -> 0.1497006 | AF32: =Z32/Y32 -> 6.4908 | AG32: 5 | AH32: 27 | AI32: 10 | AJ32: 0 | AK32: =AG32*产品成本!$D$5+AH32*产品成本!$D$6+AI32*产品成本!$D$7+AJ32*产品成本!$D$8 -> 126.05634 | AL32: =AG32*产品成本!$E$5+AH32*产品成本!$E$6+AI32*产品成本!$E$7+AJ32*产品成本!$E$8 -> 13.99 | AM32: =AG32*产品成本!$F$5+AH32*产品成本!$F$6+AI32*产品成本!$F$7+AJ32*产品成本!$F$8 -> 15.33 | AN32: =AG32*产品成本!$G$5+AH32*产品成本!$G$6+AI32*产品成本!$G$7+AJ32*产品成本!$G$8 -> 187.46 | AO32: =(E32-I32)*0.15 -> 150.387 | AP32: =SUM(AK32:AO32) -> 493.22334 | AQ32: 0 | AR32: 0 | AS32: 1 | AT32: 0 | AU32: =L32/(1-0.15-0.15*0.2) -> 25.743902 | AV32: =AQ32*产品成本!$D$5+AR32*产品成本!$D$6+AS32*产品成本!$D$7+AT32*产品成本!D41 -> 3.6619718 | AW32: =AQ32*产品成本!$E$5+AR32*产品成本!$E$6+AS32*产品成本!$E$7+AT32*产品成本!E41 -> 0.4 | AX32: =AQ32*产品成本!$F$5+AR32*产品成本!$F$6+AS32*产品成本!$F$7+AT32*产品成本!F41 -> 0.41 | AZ32: =AU32*0.15 -> 3.8615854 | BA32: =-AZ32*0.2 -> -0.77231707 | BB32: =SUM(AV32:BA32) -> 7.5612401 | BC32: =AP32-BB32 -> 485.6621 | BD32: =E32-I32 -> 1002.58 | BE32: =E32-AU32-I32 -> 976.8361 | BF32: =BE32-BC32-Z32 -> 328.904 | BG32: =BF32/BE32 -> 0.33670336
A33: 0526~0601 | B33: 2025W22 | C33: 56 | D33: 54 | E33: 1200.94 | J33: 2 | K33: =J33/C33 -> 0.035714286 | L33: 38.44 | M33: =(C33-C32)/C32 -> 0.33333333 | N33: =(D33-D32)/D32 -> 0.28571429 | O33: =(E33-E32)/E32 -> 0.19784955 | P33: =C33/D33 -> 1.037037 | Q33: =E33/D33 -> 22.23963 | R33: =E33/C33 -> 21.445357 | S33: =C33/7 -> 8 | T33: =D33-Y33 -> 14 | U33: =T33/D33 -> 0.25925926 | V33: =Z33/(E33-I33) -> 0.23433311 | W33: 30427 | X33: 255 | Y33: 40 | Z33: 281.42 | AA33: 845.31 | AB33: 1.1 | AC33: =Z33/AA33 -> 0.33291928 | AD33: =X33/W33 -> 0.0083807145 | AE33: =Y33/X33 -> 0.15686275 | AF33: =Z33/Y33 -> 7.0355 | AG33: 22 | AH33: 22 | AI33: 12 | AJ33: 0 | AK33: =AG33*产品成本!$D$5+AH33*产品成本!$D$6+AI33*产品成本!$D$7+AJ33*产品成本!$D$8 -> 164.78873 | AL33: =AG33*产品成本!$E$5+AH33*产品成本!$E$6+AI33*产品成本!$E$7+AJ33*产品成本!$E$8 -> 17.78 | AM33: =AG33*产品成本!$F$5+AH33*产品成本!$F$6+AI33*产品成本!$F$7+AJ33*产品成本!$F$8 -> 21.42 | AN33: =AG33*产品成本!$G$5+AH33*产品成本!$G$6+AI33*产品成本!$G$7+AJ33*产品成本!$G$8 -> 260.92 | AO33: =(E33-I33)*0.15 -> 180.141 | AP33: =SUM(AK33:AO33) -> 645.04973 | AQ33: 2 | AR33: 0 | AS33: 0 | AT33: 0 | AU33: =L33/(1-0.15-0.15*0.2) -> 46.878049 | AV33: =AQ33*产品成本!$D$5+AR33*产品成本!$D$6+AS33*产品成本!$D$7+AT33*产品成本!D42 -> 5.3521127 | AW33: =AQ33*产品成本!$E$5+AR33*产品成本!$E$6+AS33*产品成本!$E$7+AT33*产品成本!E42 -> 0.54 | AX33: =AQ33*产品成本!$F$5+AR33*产品成本!$F$6+AS33*产品成本!$F$7+AT33*产品成本!F42 -> 0.82 | AZ33: =AU33*0.15 -> 7.0317073 | BA33: =-AZ33*0.2 -> -1.4063415 | BB33: =SUM(AV33:BA33) -> 12.337479 | BC33: =AP33-BB33 -> 632.71225 | BD33: =E33-I33 -> 1200.94 | BE33: =E33-AU33-I33 -> 1154.062 | BF33: =BE33-BC33-Z33 -> 239.9297 | BG33: =BF33/BE33 -> 0.20790019 | BI33: 新开广告，广告单占比高
A34: 0602~0608 | B34: 2025W23 | C34: 80 | D34: 73 | E34: 1609.14 | F34: 4 | G34: 4 | H34: 78.58 | I34: 7.86 | J34: 2 | K34: =J34/C34 -> 0.025 | L34: 36.52 | M34: =(C34-C33)/C33 -> 0.42857143 | N34: =(D34-D33)/D33 -> 0.35185185 | O34: =(E34-E33)/E33 -> 0.33990041 | P34: =C34/D34 -> 1.0958904 | Q34: =E34/D34 -> 22.043014 | R34: =E34/C34 -> 20.11425 | S34: =C34/7 -> 11.428571 | T34: =D34-Y34 -> 31 | U34: =T34/D34 -> 0.42465753 | V34: =Z34/(E34-I34) -> 0.19688 | W34: 35717 | X34: 282 | Y34: 42 | Z34: 315.26 | AA34: 847.04 | AB34: 1.12 | AC34: =Z34/AA34 -> 0.37219022 | AD34: =X34/W34 -> 0.0078953999 | AE34: =Y34/X34 -> 0.14893617 | AF34: =Z34/Y34 -> 7.5061905 | AG34: 31 | AH34: 29 | AI34: 20 | AJ34: 0 | AK34: =AG34*产品成本!$D$5+AH34*产品成本!$D$6+AI34*产品成本!$D$7+AJ34*产品成本!$D$8 -> 237.88732 | AL34: =AG34*产品成本!$E$5+AH34*产品成本!$E$6+AI34*产品成本!$E$7+AJ34*产品成本!$E$8 -> 25.65 | AM34: =AG34*产品成本!$F$5+AH34*产品成本!$F$6+AI34*产品成本!$F$7+AJ34*产品成本!$F$8 -> 30.77 | AN34: =AG34*产品成本!$G$5+AH34*产品成本!$G$6+AI34*产品成本!$G$7+AJ34*产品成本!$G$8 -> 375.82 | AO34: =(E34-I34)*0.15 -> 240.192 | AP34: =SUM(AK34:AO34) -> 910.31932 | AQ34: 0 | AR34: 1 | AS34: 1 | AT34: 0 | AU34: =L34/(1-0.15-0.15*0.2) -> 44.536585 | AV34: =AQ34*产品成本!$D$5+AR34*产品成本!$D$6+AS34*产品成本!$D$7+AT34*产品成本!D43 -> 6.4788732 | AW34: =AQ34*产品成本!$E$5+AR34*产品成本!$E$6+AS34*产品成本!$E$7+AT34*产品成本!E43 -> 0.72 | AX34: =AQ34*产品成本!$F$5+AR34*产品成本!$F$6+AS34*产品成本!$F$7+AT34*产品成本!F43 -> 0.75 | AZ34: =AU34*0.15 -> 6.6804878 | BA34: =-AZ34*0.2 -> -1.3360976 | BB34: =SUM(AV34:BA34) -> 13.293263 | BC34: =AP34-BB34 -> 897.02606 | BD34: =E34-I34 -> 1601.28 | BE34: =E34-AU34-I34 -> 1556.7434 | BF34: =BE34-BC34-Z34 -> 344.45735 | BG34: =BF34/BE34 -> 0.22126791
A35: 0609~0615 | B35: 2025W24 | C35: 55 | D35: 52 | E35: 1205.75 | F35: 3 | G35: 3 | H35: 63.87 | I35: 6.39 | J35: 2 | K35: =J35/C35 -> 0.036363636 | L35: 35.04 | M35: =(C35-C34)/C34 -> -0.3125 | N35: =(D35-D34)/D34 -> -0.28767123 | O35: =(E35-E34)/E34 -> -0.2506867 | P35: =C35/D35 -> 1.0576923 | Q35: =E35/D35 -> 23.1875 | R35: =E35/C35 -> 21.922727 | S35: =C35/7 -> 7.8571429 | T35: =D35-Y35 -> 13 | U35: =T35/D35 -> 0.25 | V35: =Z35/(E35-I35) -> 0.2209345 | W35: 24731 | X35: 249 | Y35: 39 | Z35: 264.98 | AA35: 920.08 | AB35: 1.06 | AC35: =Z35/AA35 -> 0.2879967 | AD35: =X35/W35 -> 0.010068335 | AE35: =Y35/X35 -> 0.15662651 | AF35: =Z35/Y35 -> 6.794359 | AG35: 14 | AH35: 30 | AI35: 12 | AJ35: 0 | AK35: =AG35*产品成本!$D$5+AH35*产品成本!$D$6+AI35*产品成本!$D$7+AJ35*产品成本!$D$8 -> 165.91549 | AL35: =AG35*产品成本!$E$5+AH35*产品成本!$E$6+AI35*产品成本!$E$7+AJ35*产品成本!$E$8 -> 18.18 | AM35: =AG35*产品成本!$F$5+AH35*产品成本!$F$6+AI35*产品成本!$F$7+AJ35*产品成本!$F$8 -> 20.86 | AN35: =AG35*产品成本!$G$5+AH35*产品成本!$G$6+AI35*产品成本!$G$7+AJ35*产品成本!$G$8 -> 254.36 | AO35: =(E35-I35)*0.15 -> 179.904 | AP35: =SUM(AK35:AO35) -> 639.21949 | AQ35: 0 | AR35: 0 | AS35: 2 | AT35: 0 | AU35: =L35/(1-0.15-0.15*0.2) -> 42.731707 | AV35: =AQ35*产品成本!$D$5+AR35*产品成本!$D$6+AS35*产品成本!$D$7+AT35*产品成本!D44 -> 7.3239437 | AW35: =AQ35*产品成本!$E$5+AR35*产品成本!$E$6+AS35*产品成本!$E$7+AT35*产品成本!E44 -> 0.8 | AX35: =AQ35*产品成本!$F$5+AR35*产品成本!$F$6+AS35*产品成本!$F$7+AT35*产品成本!F44 -> 0.82 | AZ35: =AU35*0.15 -> 6.4097561 | BA35: =-AZ35*0.2 -> -1.2819512 | BB35: =SUM(AV35:BA35) -> 14.071749 | BC35: =AP35-BB35 -> 625.14774 | BD35: =E35-I35 -> 1199.36 | BE35: =E35-AU35-I35 -> 1156.6283 | BF35: =BE35-BC35-Z35 -> 266.50055 | BG35: =BF35/BE35 -> 0.23041158
A36: 0616~0622 | B36: 2025W25 | C36: 63 | D36: 62 | E36: 1371.33 | F36: 7 | G36: 7 | H36: 150.23 | I36: 13.92 | J36: 3 | K36: =J36/C36 -> 0.047619048 | L36: 35.73 | M36: =(C36-C35)/C35 -> 0.14545455 | N36: =(D36-D35)/D35 -> 0.19230769 | O36: =(E36-E35)/E35 -> 0.13732532 | P36: =C36/D36 -> 1.016129 | Q36: =E36/D36 -> 22.118226 | R36: =E36/C36 -> 21.767143 | S36: =C36/7 -> 9 | T36: =D36-Y36 -> 30 | U36: =T36/D36 -> 0.48387097 | V36: =Z36/(E36-I36) -> 0.15868455 | W36: 23646 | X36: 200 | Y36: 32 | Z36: 215.4 | AA36: 694.66 | AB36: 1.08 | AC36: =Z36/AA36 -> 0.31007975 | AD36: =X36/W36 -> 0.0084580902 | AE36: =Y36/X36 -> 0.16 | AF36: =Z36/Y36 -> 6.73125 | AG36: 26 | AH36: 19 | AI36: 16 | AJ36: 2 | AK36: =AG36*产品成本!$D$5+AH36*产品成本!$D$6+AI36*产品成本!$D$7+AJ36*产品成本!$D$8 -> 192.95775 | AL36: =AG36*产品成本!$E$5+AH36*产品成本!$E$6+AI36*产品成本!$E$7+AJ36*产品成本!$E$8 -> 21.1 | AM36: =AG36*产品成本!$F$5+AH36*产品成本!$F$6+AI36*产品成本!$F$7+AJ36*产品成本!$F$8 -> 24.5 | AN36: =AG36*产品成本!$G$5+AH36*产品成本!$G$6+AI36*产品成本!$G$7+AJ36*产品成本!$G$8 -> 300.44 | AO36: =(E36-I36)*0.15 -> 203.6115 | AP36: =SUM(AK36:AO36) -> 742.60925 | AQ36: 2 | AR36: 0 | AS36: 1 | AT36: 0 | AU36: =L36/(1-0.15-0.15*0.2) -> 43.573171 | AV36: =AQ36*产品成本!$D$5+AR36*产品成本!$D$6+AS36*产品成本!$D$7+AT36*产品成本!D45 -> 9.0140845 | AW36: =AQ36*产品成本!$E$5+AR36*产品成本!$E$6+AS36*产品成本!$E$7+AT36*产品成本!E45 -> 0.94 | AX36: =AQ36*产品成本!$F$5+AR36*产品成本!$F$6+AS36*产品成本!$F$7+AT36*产品成本!F45 -> 1.23 | AZ36: =AU36*0.15 -> 6.5359756 | BA36: =-AZ36*0.2 -> -1.3071951 | BB36: =SUM(AV36:BA36) -> 16.412865 | BC36: =AP36-BB36 -> 726.19638 | BD36: =E36-I36 -> 1357.41 | BE36: =E36-AU36-I36 -> 1313.8368 | BF36: =BE36-BC36-Z36 -> 372.24045 | BG36: =BF36/BE36 -> 0.28332319
A37: 0623~0629 | B37: 2025W26 | C37: 47 | D37: 47 | E37: 1055.77 | F37: 3 | G37: 3 | H37: 64.77 | I37: 6.48 | J37: 4 | K37: =J37/C37 -> 0.085106383 | L37: 69.91 | M37: =(C37-C36)/C36 -> -0.25396825 | N37: =(D37-D36)/D36 -> -0.24193548 | O37: =(E37-E36)/E36 -> -0.23011237 | P37: =C37/D37 -> 1 | Q37: =E37/D37 -> 22.463191 | R37: =E37/C37 -> 22.463191 | S37: =C37/7 -> 6.7142857 | T37: =D37-Y37 -> 15 | U37: =T37/D37 -> 0.31914894 | V37: =Z37/(E37-I37) -> 0.21846201 | W37: 24533 | X37: 218 | Y37: 32 | Z37: 229.23 | AA37: 714.53 | AB37: 1.05 | AC37: =Z37/AA37 -> 0.32081228 | AD37: =X37/W37 -> 0.0088859903 | AE37: =Y37/X37 -> 0.14678899 | AF37: =Z37/Y37 -> 7.1634375 | AG37: 12 | AH37: 20 | AI37: 12 | AJ37: 3 | AK37: =AG37*产品成本!$D$5+AH37*产品成本!$D$6+AI37*产品成本!$D$7+AJ37*产品成本!$D$8 -> 149.29577 | AL37: =AG37*产品成本!$E$5+AH37*产品成本!$E$6+AI37*产品成本!$E$7+AJ37*产品成本!$E$8 -> 16.84 | AM37: =AG37*产品成本!$F$5+AH37*产品成本!$F$6+AI37*产品成本!$F$7+AJ37*产品成本!$F$8 -> 17.87 | AN37: =AG37*产品成本!$G$5+AH37*产品成本!$G$6+AI37*产品成本!$G$7+AJ37*产品成本!$G$8 -> 220.32 | AO37: =(E37-I37)*0.15 -> 157.3935 | AP37: =SUM(AK37:AO37) -> 561.71927 | AQ37: 2 | AR37: 1 | AS37: 0 | AT37: 0 | AU37: =L37/(1-0.15-0.15*0.2) -> 85.256098 | AV37: =AQ37*产品成本!$D$5+AR37*产品成本!$D$6+AS37*产品成本!$D$7+AT37*产品成本!D46 -> 8.1690141 | AW37: =AQ37*产品成本!$E$5+AR37*产品成本!$E$6+AS37*产品成本!$E$7+AT37*产品成本!E46 -> 0.86 | AX37: =AQ37*产品成本!$F$5+AR37*产品成本!$F$6+AS37*产品成本!$F$7+AT37*产品成本!F46 -> 1.16 | AZ37: =AU37*0.15 -> 12.788415 | BA37: =-AZ37*0.2 -> -2.5576829 | BB37: =SUM(AV37:BA37) -> 20.419746 | BC37: =AP37-BB37 -> 541.29953 | BD37: =E37-I37 -> 1049.29 | BE37: =E37-AU37-I37 -> 964.0339 | BF37: =BE37-BC37-Z37 -> 193.50437 | BG37: =BF37/BE37 -> 0.20072362
A38: 0630~0706 | B38: 2025W27 | C38: 47 | D38: 45 | E38: 993.62 | F38: 1 | G38: 1 | H38: 18.78 | I38: 1.88 | J38: 4 | K38: =J38/C38 -> 0.085106383 | L38: 68.29 | M38: =(C38-C37)/C37 -> 0 | N38: =(D38-D37)/D37 -> -0.042553191 | O38: =(E38-E37)/E37 -> -0.058866988 | P38: =C38/D38 -> 1.0444444 | Q38: =E38/D38 -> 22.080444 | R38: =E38/C38 -> 21.140851 | S38: =C38/7 -> 6.7142857 | T38: =D38-Y38 -> 14 | U38: =T38/D38 -> 0.31111111 | V38: =Z38/(E38-I38) -> 0.23797568 | W38: 21172 | X38: 214 | Y38: 31 | Z38: 236.01 | AA38: 665.06 | AB38: 1.1 | AC38: =Z38/AA38 -> 0.35487024 | AD38: =X38/W38 -> 0.010107689 | AE38: =Y38/X38 -> 0.14485981 | AF38: =Z38/Y38 -> 7.6132258 | AG38: 13 | AH38: 20 | AI38: 11 | AJ38: 3 | AK38: =AG38*产品成本!$D$5+AH38*产品成本!$D$6+AI38*产品成本!$D$7+AJ38*产品成本!$D$8 -> 148.30986 | AL38: =AG38*产品成本!$E$5+AH38*产品成本!$E$6+AI38*产品成本!$E$7+AJ38*产品成本!$E$8 -> 16.71 | AM38: =AG38*产品成本!$F$5+AH38*产品成本!$F$6+AI38*产品成本!$F$7+AJ38*产品成本!$F$8 -> 17.87 | AN38: =AG38*产品成本!$G$5+AH38*产品成本!$G$6+AI38*产品成本!$G$7+AJ38*产品成本!$G$8 -> 219.94 | AO38: =(E38-I38)*0.15 -> 148.761 | AP38: =SUM(AK38:AO38) -> 551.59086 | AQ38: 1 | AR38: 1 | AS38: 2 | AT38: 0 | AU38: =L38/(1-0.15-0.15*0.2) -> 83.280488 | AV38: =AQ38*产品成本!$D$5+AR38*产品成本!$D$6+AS38*产品成本!$D$7+AT38*产品成本!D47 -> 12.816901 | AW38: =AQ38*产品成本!$E$5+AR38*产品成本!$E$6+AS38*产品成本!$E$7+AT38*产品成本!E47 -> 1.39 | AX38: =AQ38*产品成本!$F$5+AR38*产品成本!$F$6+AS38*产品成本!$F$7+AT38*产品成本!F47 -> 1.57 | AZ38: =AU38*0.15 -> 12.492073 | BA38: =-AZ38*0.2 -> -2.4984146 | BB38: =SUM(AV38:BA38) -> 25.77056 | BC38: =AP38-BB38 -> 525.8203 | BD38: =E38-I38 -> 991.74 | BE38: =E38-AU38-I38 -> 908.45951 | BF38: =BE38-BC38-Z38 -> 146.62921 | BG38: =BF38/BE38 -> 0.16140424
A39: 0708~0711 | B39: PD2025 4 Days | C39: 51 | D39: 46 | E39: 967.06 | F39: 0 | G39: 0 | H39: 0 | I39: 0 | J39: 2 | K39: =J39/C39 -> 0.039215686 | L39: 32.36 | M39: =(C39-C38)/C38 -> 0.085106383 | N39: =(D39-D38)/D38 -> 0.022222222 | O39: =(E39-E38)/E38 -> -0.026730541 | P39: =C39/D39 -> 1.1086957 | Q39: =E39/D39 -> 21.023043 | R39: =E39/C39 -> 18.961961 | S39: =C39/4 -> 12.75 | T39: =D39-Y39 -> 24 | U39: =T39/D39 -> 0.52173913 | V39: =Z39/(E39-I39) -> 0.24940541 | W39: 20363 | X39: 187 | Y39: 22 | Z39: 241.19 | AA39: 469.42 | AB39: 1.29 | AC39: =Z39/AA39 -> 0.51380427 | AD39: =X39/W39 -> 0.0091833227 | AE39: =Y39/X39 -> 0.11764706 | AF39: =Z39/Y39 -> 10.963182 | AG39: 13 | AH39: 18 | AI39: 16 | AJ39: 2 | AK39: =AG39*产品成本!$D$5+AH39*产品成本!$D$6+AI39*产品成本!$D$7+AJ39*产品成本!$D$8 -> 155.35211 | AL39: =AG39*产品成本!$E$5+AH39*产品成本!$E$6+AI39*产品成本!$E$7+AJ39*产品成本!$E$8 -> 17.27 | AM39: =AG39*产品成本!$F$5+AH39*产品成本!$F$6+AI39*产品成本!$F$7+AJ39*产品成本!$F$8 -> 18.83 | AN39: =AG39*产品成本!$G$5+AH39*产品成本!$G$6+AI39*产品成本!$G$7+AJ39*产品成本!$G$8 -> 232.66 | AO39: =(E39-I39)*0.15 -> 145.059 | AP39: =SUM(AK39:AO39) -> 569.17111 | AQ39: 1 | AR39: 0 | AS39: 1 | AT39: 0 | AU39: =L39/(1-0.15-0.15*0.2) -> 39.463415 | AV39: =AQ39*产品成本!$D$5+AR39*产品成本!$D$6+AS39*产品成本!$D$7+AT39*产品成本!D48 -> 6.3380282 | AW39: =AQ39*产品成本!$E$5+AR39*产品成本!$E$6+AS39*产品成本!$E$7+AT39*产品成本!E48 -> 0.67 | AX39: =AQ39*产品成本!$F$5+AR39*产品成本!$F$6+AS39*产品成本!$F$7+AT39*产品成本!F48 -> 0.82 | AZ39: =AU39*0.15 -> 5.9195122 | BA39: =-AZ39*0.2 -> -1.1839024 | BB39: =SUM(AV39:BA39) -> 12.563638 | BC39: =AP39-BB39 -> 556.60747 | BD39: =E39-I39 -> 967.06 | BE39: =E39-AU39-I39 -> 927.59659 | BF39: =BE39-BC39-Z39 -> 129.79911 | BG39: =BF39/BE39 -> 0.13993056
A40: 0707~0713 | B40: 2025W28 | C40: 68 | D40: 63 | E40: 1333.48 | F40: 0 | G40: 0 | H40: 0 | I40: 0 | J40: 4 | K40: =J40/C40 -> 0.058823529 | L40: 65.13 | M40: =(C40-C39)/C39 -> 0.33333333 | N40: =(D40-D39)/D39 -> 0.36956522 | O40: =(E40-E39)/E39 -> 0.378901 | P40: =C40/D40 -> 1.0793651 | Q40: =E40/D40 -> 21.166349 | R40: =E40/C40 -> 19.61 | S40: =C40/4 -> 17 | T40: =D40-Y40 -> 28 | U40: =T40/D40 -> 0.44444444 | V40: =Z40/(E40-I40) -> 0.24685035 | W40: 27726 | X40: 262 | Y40: 35 | Z40: 329.17 | AA40: 735.36 | AB40: 1.26 | AC40: =Z40/AA40 -> 0.44763109 | AD40: =X40/W40 -> 0.0094496141 | AE40: =Y40/X40 -> 0.13358779 | AF40: =Z40/Y40 -> 9.4048571 | AG40: 14 | AH40: 28 | AI40: 23 | AJ40: 3 | AK40: =AG40*产品成本!$D$5+AH40*产品成本!$D$6+AI40*产品成本!$D$7+AJ40*产品成本!$D$8 -> 217.46479 | AL40: =AG40*产品成本!$E$5+AH40*产品成本!$E$6+AI40*产品成本!$E$7+AJ40*产品成本!$E$8 -> 24.34 | AM40: =AG40*产品成本!$F$5+AH40*产品成本!$F$6+AI40*产品成本!$F$7+AJ40*产品成本!$F$8 -> 25.92 | AN40: =AG40*产品成本!$G$5+AH40*产品成本!$G$6+AI40*产品成本!$G$7+AJ40*产品成本!$G$8 -> 320.84 | AO40: =(E40-I40)*0.15 -> 200.022 | AP40: =SUM(AK40:AO40) -> 788.58679 | AQ40: 1 | AR40: 1 | AS40: 2 | AT40: 0 | AU40: =L40/(1-0.15-0.15*0.2) -> 79.426829 | AV40: =AQ40*产品成本!$D$5+AR40*产品成本!$D$6+AS40*产品成本!$D$7+AT40*产品成本!D49 -> 12.816901 | AW40: =AQ40*产品成本!$E$5+AR40*产品成本!$E$6+AS40*产品成本!$E$7+AT40*产品成本!E49 -> 1.39 | AX40: =AQ40*产品成本!$F$5+AR40*产品成本!$F$6+AS40*产品成本!$F$7+AT40*产品成本!F49 -> 1.57 | AZ40: =AU40*0.15 -> 11.914024 | BA40: =-AZ40*0.2 -> -2.3828049 | BB40: =SUM(AV40:BA40) -> 25.308121 | BC40: =AP40-BB40 -> 763.27867 | BD40: =E40-I40 -> 1333.48 | BE40: =E40-AU40-I40 -> 1254.0532 | BF40: =BE40-BC40-Z40 -> 161.6045 | BG40: =BF40/BE40 -> 0.12886575
A41: 0714~0720 | B41: 2025W29 | C41: 56 | D41: 52 | E41: 1253.65 | F41: 1 | G41: 1 | H41: 20.39 | I41: 2.04 | J41: 4 | K41: =J41/C41 -> 0.071428571 | L41: 72.55 | M41: =(C41-C40)/C40 -> -0.17647059 | N41: =(D41-D40)/D40 -> -0.17460317 | O41: =(E41-E40)/E40 -> -0.059865915 | P41: =C41/D41 -> 1.0769231 | Q41: =E41/D41 -> 24.108654 | R41: =E41/C41 -> 22.386607 | S41: =C41/4 -> 14 | T41: =D41-Y41 -> 17 | U41: =T41/D41 -> 0.32692308 | V41: =Z41/(E41-I41) -> 0.20624635 | W41: 19871 | X41: 226 | Y41: 35 | Z41: 258.14 | AA41: 824.14 | AB41: 1.14 | AC41: =Z41/AA41 -> 0.31322348 | AD41: =X41/W41 -> 0.011373358 | AE41: =Y41/X41 -> 0.15486726 | AF41: =Z41/Y41 -> 7.3754286 | AG41: 15 | AH41: 13 | AI41: 27 | AJ41: 1 | AK41: =AG41*产品成本!$D$5+AH41*产品成本!$D$6+AI41*产品成本!$D$7+AJ41*产品成本!$D$8 -> 181.26761 | AL41: =AG41*产品成本!$E$5+AH41*产品成本!$E$6+AI41*产品成本!$E$7+AJ41*产品成本!$E$8 -> 19.81 | AM41: =AG41*产品成本!$F$5+AH41*产品成本!$F$6+AI41*产品成本!$F$7+AJ41*产品成本!$F$8 -> 22.05 | AN41: =AG41*产品成本!$G$5+AH41*产品成本!$G$6+AI41*产品成本!$G$7+AJ41*产品成本!$G$8 -> 274.62 | AO41: =(E41-I41)*0.15 -> 187.7415 | AP41: =SUM(AK41:AO41) -> 685.48911 | AQ41: 3 | AR41: 1 | AS41: 0 | AT41: 0 | AU41: =L41/(1-0.15-0.15*0.2) -> 88.47561 | AV41: =AQ41*产品成本!$D$5+AR41*产品成本!$D$6+AS41*产品成本!$D$7+AT41*产品成本!D50 -> 10.84507 | AW41: =AQ41*产品成本!$E$5+AR41*产品成本!$E$6+AS41*产品成本!$E$7+AT41*产品成本!E50 -> 1.13 | AX41: =AQ41*产品成本!$F$5+AR41*产品成本!$F$6+AS41*产品成本!$F$7+AT41*产品成本!F50 -> 1.57 | AZ41: =AU41*0.15 -> 13.271341 | BA41: =-AZ41*0.2 -> -2.6542683 | BB41: =SUM(AV41:BA41) -> 24.162144 | BC41: =AP41-BB41 -> 661.32696 | BD41: =E41-I41 -> 1251.61 | BE41: =E41-AU41-I41 -> 1163.1344 | BF41: =BE41-BC41-Z41 -> 243.66743 | BG41: =BF41/BE41 -> 0.20949207
A42: 0721~0727 | B42: 2025W30 | C42: 74 | D42: 72 | E42: 1502.9 | F42: 7 | G42: 6 | H42: 152.64 | I42: 11.46 | J42: 3 | K42: =J42/C42 -> 0.040540541 | L42: 52.93 | M42: =(C42-C41)/C41 -> 0.32142857 | N42: =(D42-D41)/D41 -> 0.38461538 | O42: =(E42-E41)/E41 -> 0.19881945 | P42: =C42/D42 -> 1.0277778 | Q42: =E42/D42 -> 20.873611 | R42: =E42/C42 -> 20.309459 | S42: =C42/4 -> 18.5 | T42: =D42-Y42 -> 27 | U42: =T42/D42 -> 0.375 | V42: =Z42/(E42-I42) -> 0.22161133 | W42: 26370 | X42: 294 | Y42: 45 | Z42: 330.52 | AA42: 986.95 | AB42: 1.12 | AC42: =Z42/AA42 -> 0.33489032 | AD42: =X42/W42 -> 0.011149033 | AE42: =Y42/X42 -> 0.15306122 | AF42: =Z42/Y42 -> 7.3448889 | AG42: 33 | AH42: 21 | AI42: 17 | AJ42: 3 | AK42: =AG42*产品成本!$D$5+AH42*产品成本!$D$6+AI42*产品成本!$D$7+AJ42*产品成本!$D$8 -> 226.61972 | AL42: =AG42*产品成本!$E$5+AH42*产品成本!$E$6+AI42*产品成本!$E$7+AJ42*产品成本!$E$8 -> 24.83 | AM42: =AG42*产品成本!$F$5+AH42*产品成本!$F$6+AI42*产品成本!$F$7+AJ42*产品成本!$F$8 -> 28.87 | AN42: =AG42*产品成本!$G$5+AH42*产品成本!$G$6+AI42*产品成本!$G$7+AJ42*产品成本!$G$8 -> 353.7 | AO42: =(E42-I42)*0.15 -> 223.716 | AP42: =SUM(AK42:AO42) -> 857.73572 | AQ42: 1 | AR42: 1 | AS42: 1 | AT42: 0 | AU42: =L42/(1-0.15-0.15*0.2) -> 64.54878 | AV42: =AQ42*产品成本!$D$5+AR42*产品成本!$D$6+AS42*产品成本!$D$7+AT42*产品成本!D51 -> 9.1549296 | AW42: =AQ42*产品成本!$E$5+AR42*产品成本!$E$6+AS42*产品成本!$E$7+AT42*产品成本!E51 -> 0.99 | AX42: =AQ42*产品成本!$F$5+AR42*产品成本!$F$6+AS42*产品成本!$F$7+AT42*产品成本!F51 -> 1.16 | AZ42: =AU42*0.15 -> 9.6823171 | BA42: =-AZ42*0.2 -> -1.9364634 | BB42: =SUM(AV42:BA42) -> 19.050783 | BC42: =AP42-BB42 -> 838.68494 | BD42: =E42-I42 -> 1491.44 | BE42: =E42-AU42-I42 -> 1426.8912 | BF42: =BE42-BC42-Z42 -> 257.68628 | BG42: =BF42/BE42 -> 0.1805928
A43: 0728~0803 | B43: 2025W31 | C43: 44 | D43: 44 | E43: 1057.76 | F43: 3 | G43: 3 | H43: 71.97 | I43: 7.2 | J43: 4 | K43: =J43/C43 -> 0.090909091 | L43: 49.83 | M43: =(C43-C42)/C42 -> -0.40540541 | N43: =(D43-D42)/D42 -> -0.38888889 | O43: =(E43-E42)/E42 -> -0.29618737 | P43: =C43/D43 -> 1 | Q43: =E43/D43 -> 24.04 | R43: =E43/C43 -> 24.04 | S43: =C43/4 -> 11 | T43: =D43-Y43 -> 19 | U43: =T43/D43 -> 0.43181818 | V43: =Z43/(E43-I43) -> 0.26853297 | W43: 25424 | X43: 250 | Y43: 25 | Z43: 282.11 | AA43: 588.75 | AB43: 1.13 | AC43: =Z43/AA43 -> 0.47916773 | AD43: =X43/W43 -> 0.0098332284 | AE43: =Y43/X43 -> 0.1 | AF43: =Z43/Y43 -> 11.2844 | AG43: 17 | AH43: 11 | AI43: 15 | AJ43: 1 | AK43: =AG43*产品成本!$D$5+AH43*产品成本!$D$6+AI43*产品成本!$D$7+AJ43*产品成本!$D$8 -> 137.04225 | AL43: =AG43*产品成本!$E$5+AH43*产品成本!$E$6+AI43*产品成本!$E$7+AJ43*产品成本!$E$8 -> 14.91 | AM43: =AG43*产品成本!$F$5+AH43*产品成本!$F$6+AI43*产品成本!$F$7+AJ43*产品成本!$F$8 -> 17.27 | AN43: =AG43*产品成本!$G$5+AH43*产品成本!$G$6+AI43*产品成本!$G$7+AJ43*产品成本!$G$8 -> 212.9 | AO43: =(E43-I43)*0.15 -> 157.584 | AP43: =SUM(AK43:AO43) -> 539.70625 | AQ43: 2 | AR43: 2 | AS43: 0 | AT43: 0 | AU43: =L43/(1-0.15-0.15*0.2) -> 60.768293 | AV43: =AQ43*产品成本!$D$5+AR43*产品成本!$D$6+AS43*产品成本!$D$7+AT43*产品成本!D52 -> 10.985915 | AW43: =AQ43*产品成本!$E$5+AR43*产品成本!$E$6+AS43*产品成本!$E$7+AT43*产品成本!E52 -> 1.18 | AX43: =AQ43*产品成本!$F$5+AR43*产品成本!$F$6+AS43*产品成本!$F$7+AT43*产品成本!F52 -> 1.5 | AZ43: =AU43*0.15 -> 9.1152439 | BA43: =-AZ43*0.2 -> -1.8230488 | BB43: =SUM(AV43:BA43) -> 20.958111 | BC43: =AP43-BB43 -> 518.74814 | BD43: =E43-I43 -> 1050.56 | BE43: =E43-AU43-I43 -> 989.79171 | BF43: =BE43-BC43-Z43 -> 188.93356 | BG43: =BF43/BE43 -> 0.19088215 | BI43: 原价，没做折扣
A44: 0804~0810 | B44: 2025W32 | C44: 60 | D44: 60 | E44: 1272.53 | F44: 0 | G44: 0 | H44: 0 | I44: 0 | J44: 5 | K44: =J44/C44 -> 0.083333333 | L44: 84.76 | M44: =(C44-C43)/C43 -> 0.36363636 | N44: =(D44-D43)/D43 -> 0.36363636 | O44: =(E44-E43)/E43 -> 0.20304228 | P44: =C44/D44 -> 1 | Q44: =E44/D44 -> 21.208833 | R44: =E44/C44 -> 21.208833 | S44: =C44/4 -> 15 | T44: =D44-Y44 -> 20 | U44: =T44/D44 -> 0.33333333 | V44: =Z44/(E44-I44) -> 0.2638759 | W44: 23851 | X44: 295 | Y44: 40 | Z44: 335.79 | AA44: 842.42 | AB44: 1.14 | AC44: =Z44/AA44 -> 0.39860165 | AD44: =X44/W44 -> 0.012368454 | AE44: =Y44/X44 -> 0.13559322 | AF44: =Z44/Y44 -> 8.39475 | AG44: 19 | AH44: 19 | AI44: 18 | AJ44: 4 | AK44: =AG44*产品成本!$D$5+AH44*产品成本!$D$6+AI44*产品成本!$D$7+AJ44*产品成本!$D$8 -> 192.8169 | AL44: =AG44*产品成本!$E$5+AH44*产品成本!$E$6+AI44*产品成本!$E$7+AJ44*产品成本!$E$8 -> 21.61 | AM44: =AG44*产品成本!$F$5+AH44*产品成本!$F$6+AI44*产品成本!$F$7+AJ44*产品成本!$F$8 -> 23.27 | AN44: =AG44*产品成本!$G$5+AH44*产品成本!$G$6+AI44*产品成本!$G$7+AJ44*产品成本!$G$8 -> 287.74 | AO44: =(E44-I44)*0.15 -> 190.8795 | AP44: =SUM(AK44:AO44) -> 716.3164 | AQ44: 3 | AR44: 2 | AS44: 0 | AT44: 0 | AU44: =L44/(1-0.15-0.15*0.2) -> 103.36585 | AV44: =AQ44*产品成本!$D$5+AR44*产品成本!$D$6+AS44*产品成本!$D$7+AT44*产品成本!D53 -> 13.661972 | AW44: =AQ44*产品成本!$E$5+AR44*产品成本!$E$6+AS44*产品成本!$E$7+AT44*产品成本!E53 -> 1.45 | AX44: =AQ44*产品成本!$F$5+AR44*产品成本!$F$6+AS44*产品成本!$F$7+AT44*产品成本!F53 -> 1.91 | AZ44: =AU44*0.15 -> 15.504878 | BA44: =-AZ44*0.2 -> -3.1009756 | BB44: =SUM(AV44:BA44) -> 29.425874 | BC44: =AP44-BB44 -> 686.89053 | BD44: =E44-I44 -> 1272.53 | BE44: =E44-AU44-I44 -> 1169.1641 | BF44: =BE44-BC44-Z44 -> 146.48362 | BG44: =BF44/BE44 -> 0.12528918
A45: 0811~0817 | B45: 2025W33 | C45: 57 | D45: 56 | E45: 1193.34 | F45: 1 | G45: 1 | H45: 20.39 | I45: 20.39 | J45: 1 | K45: =J45/C45 -> 0.01754386 | L45: 17.2 | M45: =(C45-C44)/C44 -> -0.05 | N45: =(D45-D44)/D44 -> -0.066666667 | O45: =(E45-E44)/E44 -> -0.06223036 | P45: =C45/D45 -> 1.0178571 | Q45: =E45/D45 -> 21.309643 | R45: =E45/C45 -> 20.935789 | S45: =C45/4 -> 14.25 | T45: =D45-Y45 -> 20 | U45: =T45/D45 -> 0.35714286 | V45: =Z45/(E45-I45) -> 0.25092289 | W45: 22921 | X45: 255 | Y45: 36 | Z45: 294.32 | AA45: 772.76 | AB45: 1.15 | AC45: =Z45/AA45 -> 0.38086857 | AD45: =X45/W45 -> 0.011125169 | AE45: =Y45/X45 -> 0.14117647 | AF45: =Z45/Y45 -> 8.1755556 | AG45: 21 | AH45: 18 | AI45: 15 | AJ45: 3 | AK45: =AG45*产品成本!$D$5+AH45*产品成本!$D$6+AI45*产品成本!$D$7+AJ45*产品成本!$D$8 -> 178.73239 | AL45: =AG45*产品成本!$E$5+AH45*产品成本!$E$6+AI45*产品成本!$E$7+AJ45*产品成本!$E$8 -> 19.83 | AM45: =AG45*产品成本!$F$5+AH45*产品成本!$F$6+AI45*产品成本!$F$7+AJ45*产品成本!$F$8 -> 22.11 | AN45: =AG45*产品成本!$G$5+AH45*产品成本!$G$6+AI45*产品成本!$G$7+AJ45*产品成本!$G$8 -> 272.1 | AO45: =(E45-I45)*0.15 -> 175.9425 | AP45: =SUM(AK45:AO45) -> 668.71489 | AQ45: 1 | AR45: 0 | AS45: 0 | AT45: 0 | AU45: =L45/(1-0.15-0.15*0.2) -> 20.97561 | AV45: =AQ45*产品成本!$D$5+AR45*产品成本!$D$6+AS45*产品成本!$D$7+AT45*产品成本!D54 -> 2.6760563 | AW45: =AQ45*产品成本!$E$5+AR45*产品成本!$E$6+AS45*产品成本!$E$7+AT45*产品成本!E54 -> 0.27 | AX45: =AQ45*产品成本!$F$5+AR45*产品成本!$F$6+AS45*产品成本!$F$7+AT45*产品成本!F54 -> 0.41 | AZ45: =AU45*0.15 -> 3.1463415 | BA45: =-AZ45*0.2 -> -0.62926829 | BB45: =SUM(AV45:BA45) -> 5.8731295 | BC45: =AP45-BB45 -> 662.84176 | BD45: =E45-I45 -> 1172.95 | BE45: =E45-AU45-I45 -> 1151.9744 | BF45: =BE45-BC45-Z45 -> 194.81263 | BG45: =BF45/BE45 -> 0.16911194
A46: 0818~0824 | B46: 2025W34 | C46: 92 | D46: 90 | E46: 1872.8 | F46: 7 | G46: 7 | H46: 139.33 | I46: 19.9 | J46: 1 | K46: =J46/C46 -> 0.010869565 | L46: 17.94 | M46: =(C46-C45)/C45 -> 0.61403509 | N46: =(D46-D45)/D45 -> 0.60714286 | O46: =(E46-E45)/E45 -> 0.56937671 | P46: =C46/D46 -> 1.0222222 | Q46: =E46/D46 -> 20.808889 | R46: =E46/C46 -> 20.356522 | S46: =C46/4 -> 23 | T46: =D46-Y46 -> 33 | U46: =T46/D46 -> 0.36666667 | V46: =Z46/(E46-I46) -> 0.1886988 | W46: 36290 | X46: 334 | Y46: 57 | Z46: 349.64 | AA46: 1161.87 | AB46: 1.05 | AC46: =Z46/AA46 -> 0.30092868 | AD46: =X46/W46 -> 0.0092036374 | AE46: =Y46/X46 -> 0.17065868 | AF46: =Z46/Y46 -> 6.1340351 | AG46: 30 | AH46: 32 | AI46: 27 | AJ46: 3 | AK46: =AG46*产品成本!$D$5+AH46*产品成本!$D$6+AI46*产品成本!$D$7+AJ46*产品成本!$D$8 -> 286.19718 | AL46: =AG46*产品成本!$E$5+AH46*产品成本!$E$6+AI46*产品成本!$E$7+AJ46*产品成本!$E$8 -> 31.54 | AM46: =AG46*产品成本!$F$5+AH46*产品成本!$F$6+AI46*产品成本!$F$7+AJ46*产品成本!$F$8 -> 35.48 | AN46: =AG46*产品成本!$G$5+AH46*产品成本!$G$6+AI46*产品成本!$G$7+AJ46*产品成本!$G$8 -> 436.68 | AO46: =(E46-I46)*0.15 -> 277.935 | AP46: =SUM(AK46:AO46) -> 1067.8322 | AQ46: 0 | AR46: 0 | AS46: 1 | AT46: 0 | AU46: =L46/(1-0.15-0.15*0.2) -> 21.878049 | AV46: =AQ46*产品成本!$D$5+AR46*产品成本!$D$6+AS46*产品成本!$D$7+AT46*产品成本!D55 -> 3.6619718 | AW46: =AQ46*产品成本!$E$5+AR46*产品成本!$E$6+AS46*产品成本!$E$7+AT46*产品成本!E55 -> 0.4 | AX46: =AQ46*产品成本!$F$5+AR46*产品成本!$F$6+AS46*产品成本!$F$7+AT46*产品成本!F55 -> 0.41 | AZ46: =AU46*0.15 -> 3.2817073 | BA46: =-AZ46*0.2 -> -0.65634146 | BB46: =SUM(AV46:BA46) -> 7.0973377 | BC46: =AP46-BB46 -> 1060.7348 | BD46: =E46-I46 -> 1852.9 | BE46: =E46-AU46-I46 -> 1831.022 | BF46: =BE46-BC46-Z46 -> 420.64711 | BG46: =BF46/BE46 -> 0.22973351
A47: 0825~0831 | B47: 2025W35 | C47: 65 | D47: 65 | E47: 1337.59 | F47: 8 | G47: 8 | H47: 161.42 | I47: 20.18 | J47: 2 | K47: =J47/C47 -> 0.030769231 | L47: 39.05 | M47: =(C47-C46)/C46 -> -0.29347826 | N47: =(D47-D46)/D46 -> -0.27777778 | O47: =(E47-E46)/E46 -> -0.28578065 | P47: =C47/D47 -> 1 | Q47: =E47/D47 -> 20.578308 | R47: =E47/C47 -> 20.578308 | S47: =G47/7 -> 1.1428571 | T47: =D47-Y47 -> 29 | U47: =T47/D47 -> 0.44615385 | V47: =Z47/(E47-I47) -> 0.22626214 | W47: 26377 | X47: 253 | Y47: 36 | Z47: 298.08 | AA47: 741.06 | AB47: 1.18 | AC47: =Z47/AA47 -> 0.40223464 | AD47: =X47/W47 -> 0.0095916897 | AE47: =Y47/X47 -> 0.14229249 | AF47: =Z47/Y47 -> 8.28 | AG47: 24 | AH47: 19 | AI47: 20 | AJ47: 2 | AK47: =AG47*产品成本!$D$5+AH47*产品成本!$D$6+AI47*产品成本!$D$7+AJ47*产品成本!$D$8 -> 202.25352 | AL47: =AG47*产品成本!$E$5+AH47*产品成本!$E$6+AI47*产品成本!$E$7+AJ47*产品成本!$E$8 -> 22.16 | AM47: =AG47*产品成本!$F$5+AH47*产品成本!$F$6+AI47*产品成本!$F$7+AJ47*产品成本!$F$8 -> 25.32 | AN47: =AG47*产品成本!$G$5+AH47*产品成本!$G$6+AI47*产品成本!$G$7+AJ47*产品成本!$G$8 -> 311.76 | AO47: =(E47-I47)*0.15 -> 197.6115 | AP47: =SUM(AK47:AO47) -> 759.10502 | AQ47: 0 | AR47: 1 | AS47: 1 | AT47: 0 | AU47: =L47/(1-0.15-0.15*0.2) -> 47.621951 | AV47: =AQ47*产品成本!$D$5+AR47*产品成本!$D$6+AS47*产品成本!$D$7+AT47*产品成本!D56 -> 6.4788732 | AW47: =AQ47*产品成本!$E$5+AR47*产品成本!$E$6+AS47*产品成本!$E$7+AT47*产品成本!E56 -> 0.72 | AX47: =AQ47*产品成本!$F$5+AR47*产品成本!$F$6+AS47*产品成本!$F$7+AT47*产品成本!F56 -> 0.75 | AZ47: =AU47*0.15 -> 7.1432927 | BA47: =-AZ47*0.2 -> -1.4286585 | BB47: =SUM(AV47:BA47) -> 13.663507 | BC47: =AP47-BB47 -> 745.44151 | BD47: =E47-I47 -> 1317.41 | BE47: =E47-AU47-I47 -> 1269.788 | BF47: =BE47-BC47-Z47 -> 226.26654 | BG47: =BF47/BE47 -> 0.17819236
A48: 0901~0907 | B48: 2025W36 | C48: 51 | D48: 49 | E48: 1027.52 | F48: 1 | G48: 1 | H48: 18.39 | I48: 18.39 | J48: 5 | K48: =J48/C48 -> 0.098039216 | L48: 87.48 | M48: =(C48-C47)/C47 -> -0.21538462 | N48: =(D48-D47)/D47 -> -0.24615385 | O48: =(E48-E47)/E47 -> -0.23181244 | P48: =C48/D48 -> 1.0408163 | Q48: =E48/D48 -> 20.969796 | R48: =E48/C48 -> 20.147451 | S48: =G48/7 -> 0.14285714 | T48: =D48-Y48 -> 25 | U48: =T48/D48 -> 0.51020408 | V48: =Z48/(E48-I48) -> 0.28340253 | W48: 24380 | X48: 242 | Y48: 24 | Z48: 285.99 | AA48: 509.27 | AB48: 1.18 | AC48: =Z48/AA48 -> 0.56156852 | AD48: =X48/W48 -> 0.009926169 | AE48: =Y48/X48 -> 0.099173554 | AF48: =Z48/Y48 -> 11.91625 | AG48: 13 | AH48: 19 | AI48: 16 | AJ48: 3 | AK48: =AG48*产品成本!$D$5+AH48*产品成本!$D$6+AI48*产品成本!$D$7+AJ48*产品成本!$D$8 -> 163.80282 | AL48: =AG48*产品成本!$E$5+AH48*产品成本!$E$6+AI48*产品成本!$E$7+AJ48*产品成本!$E$8 -> 18.39 | AM48: =AG48*产品成本!$F$5+AH48*产品成本!$F$6+AI48*产品成本!$F$7+AJ48*产品成本!$F$8 -> 19.58 | AN48: =AG48*产品成本!$G$5+AH48*产品成本!$G$6+AI48*产品成本!$G$7+AJ48*产品成本!$G$8 -> 242.26 | AO48: =(E48-I48)*0.15 -> 151.3695 | AP48: =SUM(AK48:AO48) -> 595.40232 | AQ48: 3 | AR48: 1 | AS48: 1 | AT48: 0 | AU48: =L48/(1-0.15-0.15*0.2) -> 106.68293 | AV48: =AQ48*产品成本!$D$5+AR48*产品成本!$D$6+AS48*产品成本!$D$7+AT48*产品成本!D57 -> 14.507042 | AW48: =AQ48*产品成本!$E$5+AR48*产品成本!$E$6+AS48*产品成本!$E$7+AT48*产品成本!E57 -> 1.53 | AX48: =AQ48*产品成本!$F$5+AR48*产品成本!$F$6+AS48*产品成本!$F$7+AT48*产品成本!F57 -> 1.98 | AZ48: =AU48*0.15 -> 16.002439 | BA48: =-AZ48*0.2 -> -3.2004878 | BB48: =SUM(AV48:BA48) -> 30.818993 | BC48: =AP48-BB48 -> 564.58332 | BD48: =E48-I48 -> 1009.13 | BE48: =E48-AU48-I48 -> 902.44707 | BF48: =BE48-BC48-Z48 -> 51.87375 | BG48: =BF48/BE48 -> 0.05748121
A49: 0908~0914 | B49: 2025W37 | C49: 63 | D49: 61 | E49: 1222.09 | F49: 7 | G49: 7 | H49: 132.73 | I49: 18.96 | J49: 3 | K49: =J49/C49 -> 0.047619048 | L49: 52.03 | M49: =(C49-C48)/C48 -> 0.23529412 | N49: =(D49-D48)/D48 -> 0.24489796 | O49: =(E49-E48)/E48 -> 0.18935884 | P49: =C49/D49 -> 1.0327869 | Q49: =E49/D49 -> 20.034262 | R49: =E49/C49 -> 19.398254 | S49: =G49/7 -> 1 | T49: =D49-Y49 -> 29 | U49: =T49/D49 -> 0.47540984 | V49: =Z49/(E49-I49) -> 0.27100978 | W49: 26878 | X49: 275 | Y49: 32 | Z49: 326.06 | AA49: 642.23 | AB49: 1.19 | AC49: =Z49/AA49 -> 0.50769973 | AD49: =X49/W49 -> 0.010231416 | AE49: =Y49/X49 -> 0.11636364 | AF49: =Z49/Y49 -> 10.189375 | AG49: 22 | AH49: 21 | AI49: 18 | AJ49: 2 | AK49: =AG49*产品成本!$D$5+AH49*产品成本!$D$6+AI49*产品成本!$D$7+AJ49*产品成本!$D$8 -> 195.21127 | AL49: =AG49*产品成本!$E$5+AH49*产品成本!$E$6+AI49*产品成本!$E$7+AJ49*产品成本!$E$8 -> 21.46 | AM49: =AG49*产品成本!$F$5+AH49*产品成本!$F$6+AI49*产品成本!$F$7+AJ49*产品成本!$F$8 -> 24.36 | AN49: =AG49*产品成本!$G$5+AH49*产品成本!$G$6+AI49*产品成本!$G$7+AJ49*产品成本!$G$8 -> 299.56 | AO49: =(E49-I49)*0.15 -> 180.4695 | AP49: =SUM(AK49:AO49) -> 721.06077 | AQ49: 1 | AR49: 1 | AS49: 1 | AT49: 0 | AU49: =L49/(1-0.15-0.15*0.2) -> 63.45122 | AV49: =AQ49*产品成本!$D$5+AR49*产品成本!$D$6+AS49*产品成本!$D$7+AT49*产品成本!D58 -> 9.1549296 | AW49: =AQ49*产品成本!$E$5+AR49*产品成本!$E$6+AS49*产品成本!$E$7+AT49*产品成本!E58 -> 0.99 | AX49: =AQ49*产品成本!$F$5+AR49*产品成本!$F$6+AS49*产品成本!$F$7+AT49*产品成本!F58 -> 1.16 | AZ49: =AU49*0.15 -> 9.5176829 | BA49: =-AZ49*0.2 -> -1.9035366 | BB49: =SUM(AV49:BA49) -> 18.919076 | BC49: =AP49-BB49 -> 702.14169 | BD49: =E49-I49 -> 1203.13 | BE49: =E49-AU49-I49 -> 1139.6788 | BF49: =BE49-BC49-Z49 -> 111.47709 | BG49: =BF49/BE49 -> 0.097814481
A50: 0915~0921 | B50: 2025W38 | C50: 78 | D50: 75 | E50: 1503.54 | F50: 9 | G50: 7 | H50: 170.31 | I50: 18.92 | J50: 0 | K50: =J50/C50 -> 0 | L50: 0 | M50: =(C50-C49)/C49 -> 0.23809524 | N50: =(D50-D49)/D49 -> 0.2295082 | O50: =(E50-E49)/E49 -> 0.23030219 | P50: =C50/D50 -> 1.04 | Q50: =E50/D50 -> 20.0472 | R50: =E50/C50 -> 19.276154 | S50: =G50/7 -> 1 | T50: =D50-Y50 -> 33 | U50: =T50/D50 -> 0.44 | V50: =Z50/(E50-I50) -> 0.2441837 | W50: 43106 | X50: 313 | Y50: 42 | Z50: 362.52 | AA50: 828.53 | AB50: 1.16 | AC50: =Z50/AA50 -> 0.43754602 | AD50: =X50/W50 -> 0.0072611701 | AE50: =Y50/X50 -> 0.1341853 | AF50: =Z50/Y50 -> 8.6314286 | AG50: 30 | AH50: 24 | AI50: 22 | AJ50: 2 | AK50: =AG50*产品成本!$D$5+AH50*产品成本!$D$6+AI50*产品成本!$D$7+AJ50*产品成本!$D$8 -> 239.71831 | AL50: =AG50*产品成本!$E$5+AH50*产品成本!$E$6+AI50*产品成本!$E$7+AJ50*产品成本!$E$8 -> 26.18 | AM50: =AG50*产品成本!$F$5+AH50*产品成本!$F$6+AI50*产品成本!$F$7+AJ50*产品成本!$F$8 -> 30.3 | AN50: =AG50*产品成本!$G$5+AH50*产品成本!$G$6+AI50*产品成本!$G$7+AJ50*产品成本!$G$8 -> 372.12 | AO50: =(E50-I50)*0.15 -> 222.693 | AP50: =SUM(AK50:AO50) -> 891.01131 | AQ50: 0 | AR50: 0 | AS50: 0 | AT50: 0 | AU50: =L50/(1-0.15-0.15*0.2) -> 0 | AV50: =AQ50*产品成本!$D$5+AR50*产品成本!$D$6+AS50*产品成本!$D$7+AT50*产品成本!D59 -> 0 | AW50: =AQ50*产品成本!$E$5+AR50*产品成本!$E$6+AS50*产品成本!$E$7+AT50*产品成本!E59 -> 0 | AX50: =AQ50*产品成本!$F$5+AR50*产品成本!$F$6+AS50*产品成本!$F$7+AT50*产品成本!F59 -> 0 | AZ50: =AU50*0.15 -> 0 | BA50: =-AZ50*0.2 -> 0 | BB50: =SUM(AV50:BA50) -> 0 | BC50: =AP50-BB50 -> 891.01131 | BD50: =E50-I50 -> 1484.62 | BE50: =E50-AU50-I50 -> 1484.62 | BF50: =BE50-BC50-Z50 -> 231.08869 | BG50: =BF50/BE50 -> 0.15565511
A51: 0922~0928 | B51: 2025W39 | C51: 55 | D51: 51 | E51: 1128.94 | F51: 2 | G51: 2 | H51: 39.93 | I51: 3.99 | J51: 0 | K51: =J51/C51 -> 0 | L51: 0 | M51: =(C51-C50)/C50 -> -0.29487179 | N51: =(D51-D50)/D50 -> -0.32 | O51: =(E51-E50)/E50 -> -0.24914535 | P51: =C51/D51 -> 1.0784314 | Q51: =E51/D51 -> 22.136078 | R51: =E51/C51 -> 20.526182 | S51: =G51/7 -> 0.28571429 | T51: =D51-Y51 -> 20 | U51: =T51/D51 -> 0.39215686 | V51: =Z51/(E51-I51) -> 0.27777235 | W51: 36559 | X51: 274 | Y51: 31 | Z51: 312.48 | AA51: 663.58 | AB51: 1.14 | AC51: =Z51/AA51 -> 0.47090027 | AD51: =X51/W51 -> 0.0074947345 | AE51: =Y51/X51 -> 0.11313869 | AF51: =Z51/Y51 -> 10.08 | AG51: 20 | AH51: 18 | AI51: 15 | AJ51: 2 | AK51: =AG51*产品成本!$D$5+AH51*产品成本!$D$6+AI51*产品成本!$D$7+AJ51*产品成本!$D$8 -> 170.42254 | AL51: =AG51*产品成本!$E$5+AH51*产品成本!$E$6+AI51*产品成本!$E$7+AJ51*产品成本!$E$8 -> 18.76 | AM51: =AG51*产品成本!$F$5+AH51*产品成本!$F$6+AI51*产品成本!$F$7+AJ51*产品成本!$F$8 -> 21.29 | AN51: =AG51*产品成本!$G$5+AH51*产品成本!$G$6+AI51*产品成本!$G$7+AJ51*产品成本!$G$8 -> 261.68 | AO51: =(E51-I51)*0.15 -> 168.7425 | AP51: =SUM(AK51:AO51) -> 640.89504 | AQ51: 0 | AR51: 0 | AS51: 0 | AT51: 0 | AU51: =L51/(1-0.15-0.15*0.2) -> 0 | AV51: =AQ51*产品成本!$D$5+AR51*产品成本!$D$6+AS51*产品成本!$D$7+AT51*产品成本!D60 -> 0 | AW51: =AQ51*产品成本!$E$5+AR51*产品成本!$E$6+AS51*产品成本!$E$7+AT51*产品成本!E60 -> 0 | AX51: =AQ51*产品成本!$F$5+AR51*产品成本!$F$6+AS51*产品成本!$F$7+AT51*产品成本!F60 -> 0 | AZ51: =AU51*0.15 -> 0 | BA51: =-AZ51*0.2 -> 0 | BB51: =SUM(AV51:BA51) -> 0 | BC51: =AP51-BB51 -> 640.89504 | BD51: =E51-I51 -> 1124.95 | BE51: =E51-AU51-I51 -> 1124.95 | BF51: =BE51-BC51-Z51 -> 171.57496 | BG51: =BF51/BE51 -> 0.15251786
